{
  "updated_at": "2026-03-30T20:10:13.079002+08:00",
  "count": 89,
  "topics": [
    {
      "id": "ca1de3c2b790",
      "title": "如何才能获得退税？关于个人所得税汇算清缴的一切",
      "summary": "2019年的个人所得税汇算清缴工作已经开始了，纳税人要在2020年6月30日之前申报自己的收入支出情况。有些人可以拿到一大笔退税，也有些人要补裞，这是为什么呢？国家为什么要进行个税改革和汇算清缴呢？如何才能减少补税或者拿到退税呢？点开视频，你会了解到个人所得税的一切。",
      "source": "B站",
      "platform_class": "platform-bilibili",
      "author": "李永乐老师官方",
      "url": "http://www.bilibili.com/video/av625265594",
      "time": "2026-03-30 20:10",
      "heat": 145885,
      "discussions": "6727",
      "tags": [
        "个人所得税",
        "个税",
        "纳税"
      ],
      "isHot": true,
      "detail": "<p>2019年的个人所得税汇算清缴工作已经开始了，纳税人要在2020年6月30日之前申报自己的收入支出情况。有些人可以拿到一大笔退税，也有些人要补裞，这是为什么呢？国家为什么要进行个税改革和汇算清缴呢？如何才能减少补税或者拿到退税呢？点开视频，你会了解到个人所得税的一切。</p>"
    },
    {
      "id": "f4da56ac61e3",
      "title": "会计实操： 实务、做账（50个行业的全盘账务处理）、报税（增值税、企业所得税、个人所得税等25种税费）、报表、发票、新政策解读、税务筹划与稽查、预算、财税热点",
      "summary": "这是近200门收费课的免费试听课，想学习完整版会计实操课，V我：fewone001",
      "source": "B站",
      "platform_class": "platform-bilibili",
      "author": "跟刘老师学会计实操",
      "url": "http://www.bilibili.com/video/av838338435",
      "time": "2026-03-30 20:10",
      "heat": 113882,
      "discussions": "394",
      "tags": [
        "增值税",
        "企业所得税",
        "个人所得税"
      ],
      "isHot": true,
      "detail": "<p>这是近200门收费课的免费试听课，想学习完整版会计实操课，V我：fewone001</p>"
    },
    {
      "id": "7eedcfe6bc4c",
      "title": "一次读懂中国在征的18种税",
      "summary": "一次读懂中国在征的18种税",
      "source": "B站",
      "platform_class": "platform-bilibili",
      "author": "慕有枝613",
      "url": "http://www.bilibili.com/video/av936197233",
      "time": "2026-03-30 20:10",
      "heat": 80672,
      "discussions": "2396",
      "tags": [],
      "isHot": true,
      "detail": "<p>一次读懂中国在征的18种税</p>"
    },
    {
      "id": "1625d38c4630",
      "title": "2025退税时间到！打工人必看，手把手教你领钱！【深蓝保】",
      "summary": "更多保险攻略👇：\n年中保险测评：BV1Jo4y1P7Tf\n爸妈医疗险测评：BV1SM4y1a7G9\n61款重疾险全测评：BV1Zo4y1J7pa\n30岁值得买的保险：BV1E24y1A7Qh\n增额寿优缺点一览：BV1qo4y1F74E\n\n社保扫盲合集（指路）：\n个人养老金困境：BV1yX4y1q7SL\n医保改革解析：BV17o4y177BP\n打工人必看五险一金：BV1nh4y1s7dW\n毕业补贴：",
      "source": "B站",
      "platform_class": "platform-bilibili",
      "author": "深蓝保",
      "url": "http://www.bilibili.com/video/av114081092607353",
      "time": "2026-03-30 20:10",
      "heat": 48027,
      "discussions": "1210",
      "tags": [
        "退税",
        "社保",
        "五险一金"
      ],
      "isHot": false,
      "detail": "<p>更多保险攻略👇：\n年中保险测评：BV1Jo4y1P7Tf\n爸妈医疗险测评：BV1SM4y1a7G9\n61款重疾险全测评：BV1Zo4y1J7pa\n30岁值得买的保险：BV1E24y1A7Qh\n增额寿优缺点一览：BV1qo4y1F74E\n\n社保扫盲合集（指路）：\n个人养老金困境：BV1yX4y1q7SL\n医保改革解析：BV17o4y177BP\n打工人必看五险一金：BV1nh4y1s7dW\n毕业补贴：</p>"
    },
    {
      "id": "ba72137854cc",
      "title": "说人话！10分钟学会个人所得税怎么算，专项附加扣除是什么？打工人工资里的个税小知识都在这里！",
      "summary": "关于工资里个人所得税的小知识：个人所得税怎么计算？个税的计税逻辑？应纳税所得额和应纳税额是什么？专项附加扣除是什么、怎么填？打工人工资里的个税小知识都在这里！",
      "source": "B站",
      "platform_class": "platform-bilibili",
      "author": "安税Entax",
      "url": "http://www.bilibili.com/video/av563784292",
      "time": "2026-03-30 20:10",
      "heat": 40240,
      "discussions": "659",
      "tags": [
        "个人所得税",
        "个税",
        "纳税"
      ],
      "isHot": false,
      "detail": "<p>关于工资里个人所得税的小知识：个人所得税怎么计算？个税的计税逻辑？应纳税所得额和应纳税额是什么？专项附加扣除是什么、怎么填？打工人工资里的个税小知识都在这里！</p>"
    },
    {
      "id": "939954cf3276",
      "title": "个人所得税如何申请退税，详细退税流程来了，看看你能退多少",
      "summary": "-",
      "source": "B站",
      "platform_class": "platform-bilibili",
      "author": "焱火同学",
      "url": "http://www.bilibili.com/video/av1151317255",
      "time": "2026-03-30 20:10",
      "heat": 38817,
      "discussions": "465",
      "tags": [
        "个人所得税",
        "退税"
      ],
      "isHot": false,
      "detail": "<p>-</p>"
    },
    {
      "id": "1af0c7000446",
      "title": "个人所得税退税终极指南",
      "summary": "个人所得税退税底层逻辑+录屏实操，讲清楚税是怎么被计算出来的，到底有没有被多扣税，个人也有高阶的避税+节税操作",
      "source": "B站",
      "platform_class": "platform-bilibili",
      "author": "独生指南",
      "url": "http://www.bilibili.com/video/av114132581948426",
      "time": "2026-03-30 20:10",
      "heat": 34088,
      "discussions": "776",
      "tags": [
        "个人所得税",
        "退税",
        "避税"
      ],
      "isHot": false,
      "detail": "<p>个人所得税退税底层逻辑+录屏实操，讲清楚税是怎么被计算出来的，到底有没有被多扣税，个人也有高阶的避税+节税操作</p>"
    },
    {
      "id": "ec2ee8beaabc",
      "title": "一个例子说清楚增值税",
      "summary": "增值税到底是个啥？通过一个小例子说清楚",
      "source": "B站",
      "platform_class": "platform-bilibili",
      "author": "旗商",
      "url": "http://www.bilibili.com/video/av771824168",
      "time": "2026-03-30 20:10",
      "heat": 31947,
      "discussions": "921",
      "tags": [
        "增值税"
      ],
      "isHot": false,
      "detail": "<p>增值税到底是个啥？通过一个小例子说清楚</p>"
    },
    {
      "id": "3a44c08abf89",
      "title": "手把手教你个人所得税退税，快来退钱吧！ 全网最全退税流程！与每个人都有关系！年终奖怎么算交税最少！个人所得税退税，个人所得税退钱了！小手一抖，税钱到手！",
      "summary": "官方政策及操作指引链接：\nhttp://www.chinatax.gov.cn/chinatax/n810219/n810744/n3752930/index.html\n如果大家有疑问，欢迎评论留言，我尽量回答。",
      "source": "B站",
      "platform_class": "platform-bilibili",
      "author": "猫哥da",
      "url": "http://www.bilibili.com/video/av327697881",
      "time": "2026-03-30 20:10",
      "heat": 29062,
      "discussions": "486",
      "tags": [
        "个人所得税",
        "退税"
      ],
      "isHot": false,
      "detail": "<p>官方政策及操作指引链接：\nhttp://www.chinatax.gov.cn/chinatax/n810219/n810744/n3752930/index.html\n如果大家有疑问，欢迎评论留言，我尽量回答。</p>"
    },
    {
      "id": "bb705dd1ca93",
      "title": "增值税",
      "summary": "增值税",
      "source": "B站",
      "platform_class": "platform-bilibili",
      "author": "法正财税",
      "url": "http://www.bilibili.com/video/av73145099",
      "time": "2026-03-30 20:10",
      "heat": 27973,
      "discussions": "1391",
      "tags": [
        "增值税"
      ],
      "isHot": false,
      "detail": "<p>增值税</p>"
    },
    {
      "id": "eb3848b04ff6",
      "title": "个人所得税上涨27.26%（看视频下方详情）",
      "summary": "此视频被连续下架多次！后台存在恶意举报行为。官方如需要此视频的原稿件跟制作过程我随时可以提供。",
      "source": "B站",
      "platform_class": "platform-bilibili",
      "author": "飞洋杂谈",
      "url": "http://www.bilibili.com/video/av115624613251516",
      "time": "2026-03-30 20:10",
      "heat": 21499,
      "discussions": "850",
      "tags": [
        "个人所得税"
      ],
      "isHot": false,
      "detail": "<p>此视频被连续下架多次！后台存在恶意举报行为。官方如需要此视频的原稿件跟制作过程我随时可以提供。</p>"
    },
    {
      "id": "38d09b208733",
      "title": "聪明的抵扣制度：增值税的底层逻辑",
      "summary": "初级会计报名时间已经落地，汤姆课堂又开始营业啦~今天为大家介绍增值税的底层逻辑。让我们一起打开会计思维吧！",
      "source": "B站",
      "platform_class": "platform-bilibili",
      "author": "大聪明老汤",
      "url": "http://www.bilibili.com/video/av834503258",
      "time": "2026-03-30 20:10",
      "heat": 20503,
      "discussions": "580",
      "tags": [
        "增值税",
        "会计",
        "初级会计"
      ],
      "isHot": false,
      "detail": "<p>初级会计报名时间已经落地，汤姆课堂又开始营业啦~今天为大家介绍增值税的底层逻辑。让我们一起打开会计思维吧！</p>"
    },
    {
      "id": "e277f46cfb1d",
      "title": "21天税收筹划（全）",
      "summary": "21天税收筹划",
      "source": "B站",
      "platform_class": "platform-bilibili",
      "author": "努力的冰美式",
      "url": "http://www.bilibili.com/video/av243055235",
      "time": "2026-03-30 20:10",
      "heat": 19062,
      "discussions": "536",
      "tags": [
        "税收"
      ],
      "isHot": false,
      "detail": "<p>21天税收筹划</p>"
    },
    {
      "id": "282bce9a6fd9",
      "title": "税务基础知识",
      "summary": "税务基础知识",
      "source": "B站",
      "platform_class": "platform-bilibili",
      "author": "小辉教你开公司",
      "url": "http://www.bilibili.com/video/av1902567208",
      "time": "2026-03-30 20:10",
      "heat": 18618,
      "discussions": "125",
      "tags": [
        "税务"
      ],
      "isHot": false,
      "detail": "<p>税务基础知识</p>"
    },
    {
      "id": "239bf753d7a6",
      "title": "T3. 一口气看懂中国税收之王——增值税。从税制历史到核心架构，增值税为什么存在？",
      "summary": "本期视频，我们将展开一幅增值税的“全景地图”：\n1️⃣ 洞悉本质：为什么说增值税的最终承担者是消费者，却又是企业的“价外税”？“进项抵扣”这个精妙设计，如何像齿轮一样驱动商业运转？\n2️⃣ 穿越历史：从法国诞生时的“天才构想”，到为何它最终取代了“重复征税”的营业税？这不仅是税制的演进，更是经济思维的升级。\n3️⃣ 聚焦中国：中国的增值税有何独特之处？它如何从零发展到如今支撑国家运转的“第一税种”",
      "source": "B站",
      "platform_class": "platform-bilibili",
      "author": "财税解码",
      "url": "http://www.bilibili.com/video/av115682846967144",
      "time": "2026-03-30 20:10",
      "heat": 14889,
      "discussions": "720",
      "tags": [
        "增值税",
        "税收",
        "税率"
      ],
      "isHot": false,
      "detail": "<p>本期视频，我们将展开一幅增值税的“全景地图”：\n1️⃣ 洞悉本质：为什么说增值税的最终承担者是消费者，却又是企业的“价外税”？“进项抵扣”这个精妙设计，如何像齿轮一样驱动商业运转？\n2️⃣ 穿越历史：从法国诞生时的“天才构想”，到为何它最终取代了“重复征税”的营业税？这不仅是税制的演进，更是经济思维的升级。\n3️⃣ 聚焦中国：中国的增值税有何独特之处？它如何从零发展到如今支撑国家运转的“第一税种”</p>"
    },
    {
      "id": "9d2722ff2cea",
      "title": "个人所得税如何进行退税，保姆级退税教程来了",
      "summary": "-",
      "source": "B站",
      "platform_class": "platform-bilibili",
      "author": "焱火同学",
      "url": "http://www.bilibili.com/video/av116175325367144",
      "time": "2026-03-30 20:10",
      "heat": 14037,
      "discussions": "366",
      "tags": [
        "个人所得税",
        "退税"
      ],
      "isHot": false,
      "detail": "<p>-</p>"
    },
    {
      "id": "368ba664cc5f",
      "title": "税法一 增值税",
      "summary": "税法 一【增值税】",
      "source": "B站",
      "platform_class": "platform-bilibili",
      "author": "hao好壹贰叁",
      "url": "http://www.bilibili.com/video/av939022305",
      "time": "2026-03-30 20:10",
      "heat": 10669,
      "discussions": "408",
      "tags": [
        "增值税",
        "税法"
      ],
      "isHot": false,
      "detail": "<p>税法 一【增值税】</p>"
    },
    {
      "id": "ee295bd66bfb",
      "title": "【2025】税务师-税法一-精讲班",
      "summary": "【2025】税务师-税法一-精讲班",
      "source": "B站",
      "platform_class": "platform-bilibili",
      "author": "陈清泉的外语老师",
      "url": "http://www.bilibili.com/video/av115475564666153",
      "time": "2026-03-30 20:10",
      "heat": 10245,
      "discussions": "94",
      "tags": [
        "税务",
        "税法",
        "税务师"
      ],
      "isHot": false,
      "detail": "<p>【2025】税务师-税法一-精讲班</p>"
    },
    {
      "id": "52a7cd71ae54",
      "title": "增值税法实施后的十七点重要变化",
      "summary": "增值税法实施后的十七点重要变化",
      "source": "B站",
      "platform_class": "platform-bilibili",
      "author": "慕有枝613",
      "url": "http://www.bilibili.com/video/av115815504418744",
      "time": "2026-03-30 20:10",
      "heat": 9985,
      "discussions": "162",
      "tags": [
        "增值税",
        "税法"
      ],
      "isHot": false,
      "detail": "<p>增值税法实施后的十七点重要变化</p>"
    },
    {
      "id": "d87f5e5688f6",
      "title": "65、 个人所得税 1",
      "summary": "65、 个人所得税 1",
      "source": "B站",
      "platform_class": "platform-bilibili",
      "author": "法正财税",
      "url": "http://www.bilibili.com/video/av82695619",
      "time": "2026-03-30 20:10",
      "heat": 9016,
      "discussions": "400",
      "tags": [
        "个人所得税"
      ],
      "isHot": false,
      "detail": "<p>65、 个人所得税 1</p>"
    },
    {
      "id": "f8e3b7cef313",
      "title": "看看你的钱是怎么被收走的吧，5分钟让你了解我国税收！",
      "summary": "看看你的钱是怎么被收走的吧，5分钟让你了解我国税收！",
      "source": "B站",
      "platform_class": "platform-bilibili",
      "author": "大木金融",
      "url": "http://www.bilibili.com/video/av970944087",
      "time": "2026-03-30 20:10",
      "heat": 8400,
      "discussions": "123",
      "tags": [
        "税收"
      ],
      "isHot": false,
      "detail": "<p>看看你的钱是怎么被收走的吧，5分钟让你了解我国税收！</p>"
    },
    {
      "id": "400c36ab5633",
      "title": "所谓的税务筹划，不过如此",
      "summary": "所谓的税务筹划，不过如此",
      "source": "B站",
      "platform_class": "platform-bilibili",
      "author": "血刀喵祖",
      "url": "http://www.bilibili.com/video/av1453415050",
      "time": "2026-03-30 20:10",
      "heat": 7934,
      "discussions": "149",
      "tags": [
        "税务",
        "税务筹划"
      ],
      "isHot": false,
      "detail": "<p>所谓的税务筹划，不过如此</p>"
    },
    {
      "id": "3d090f0005f3",
      "title": "财务实操|财务知识入门|财务主管成长训练营|税务筹划|税务会计实操|财务自由之路",
      "summary": "关注公主号：中欣财经视野，回复：“666”，即可免费领取学习资料 网课及题库",
      "source": "B站",
      "platform_class": "platform-bilibili",
      "author": "中欣财经网校",
      "url": "http://www.bilibili.com/video/av713250479",
      "time": "2026-03-30 20:10",
      "heat": 7346,
      "discussions": "285",
      "tags": [
        "税务",
        "税务筹划",
        "财务"
      ],
      "isHot": false,
      "detail": "<p>关注公主号：中欣财经视野，回复：“666”，即可免费领取学习资料 网课及题库</p>"
    },
    {
      "id": "bc7e780e0531",
      "title": "会计实操：纳税筹划（税务筹划）技巧与案例精讲",
      "summary": "这是试听课，完整版共计36节，一直有效，免费更新，了解完整课程V我15221199445或13818768033",
      "source": "B站",
      "platform_class": "platform-bilibili",
      "author": "跟刘老师学会计实操",
      "url": "http://www.bilibili.com/video/av839689633",
      "time": "2026-03-30 20:10",
      "heat": 7317,
      "discussions": "62",
      "tags": [
        "税务",
        "纳税",
        "税筹"
      ],
      "isHot": false,
      "detail": "<p>这是试听课，完整版共计36节，一直有效，免费更新，了解完整课程V我15221199445或13818768033</p>"
    },
    {
      "id": "16340f1af293",
      "title": "11个人所得税",
      "summary": "本课程为高清录播入门指引课程，围绕《经济法基础》的重点知识点讲解，主要包括法律基础、劳动合同与社会保险、支付结算等相关基础理论，每一个知识点都深入细化，力求让考生学习后续《经济法基础》课程打下扎实的理论基础。",
      "source": "B站",
      "platform_class": "platform-bilibili",
      "author": "快学会计官方",
      "url": "http://www.bilibili.com/video/av464793257",
      "time": "2026-03-30 20:10",
      "heat": 7205,
      "discussions": "253",
      "tags": [
        "个人所得税"
      ],
      "isHot": false,
      "detail": "<p>本课程为高清录播入门指引课程，围绕《经济法基础》的重点知识点讲解，主要包括法律基础、劳动合同与社会保险、支付结算等相关基础理论，每一个知识点都深入细化，力求让考生学习后续《经济法基础》课程打下扎实的理论基础。</p>"
    },
    {
      "id": "17e500115f88",
      "title": "学会计算增值税（增值税的基础入门）",
      "summary": "本节视频为汤姆课程第一阶段（零基础入门阶段）的部分课程~\n手把手从零开始攻破增值税！\n后续会陆续更新完初级会计考试增值税内容\n跟着汤姆轻松攻破增值税\n拿下初级会计考试！",
      "source": "B站",
      "platform_class": "platform-bilibili",
      "author": "大聪明老汤",
      "url": "http://www.bilibili.com/video/av367640175",
      "time": "2026-03-30 20:10",
      "heat": 7186,
      "discussions": "209",
      "tags": [
        "增值税",
        "会计",
        "初级会计"
      ],
      "isHot": false,
      "detail": "<p>本节视频为汤姆课程第一阶段（零基础入门阶段）的部分课程~\n手把手从零开始攻破增值税！\n后续会陆续更新完初级会计考试增值税内容\n跟着汤姆轻松攻破增值税\n拿下初级会计考试！</p>"
    },
    {
      "id": "0036d62df619",
      "title": "税务筹划",
      "summary": "课程系统的介绍了企业所得税，增值税，消费税以及其他小税种的税务筹划。",
      "source": "B站",
      "platform_class": "platform-bilibili",
      "author": "快乐学习的小马",
      "url": "http://www.bilibili.com/video/av228907669",
      "time": "2026-03-30 20:10",
      "heat": 6187,
      "discussions": "56",
      "tags": [
        "增值税",
        "企业所得税",
        "消费税"
      ],
      "isHot": false,
      "detail": "<p>课程系统的介绍了企业所得税，增值税，消费税以及其他小税种的税务筹划。</p>"
    },
    {
      "id": "40215067dd68",
      "title": "个人所得税思路总结",
      "summary": "此视频用于梳理个人所得税的知识框架，希望对你有帮助:D",
      "source": "B站",
      "platform_class": "platform-bilibili",
      "author": "超级猪猪源",
      "url": "http://www.bilibili.com/video/av114126776966446",
      "time": "2026-03-30 20:10",
      "heat": 6169,
      "discussions": "92",
      "tags": [
        "个人所得税"
      ],
      "isHot": false,
      "detail": "<p>此视频用于梳理个人所得税的知识框架，希望对你有帮助:D</p>"
    },
    {
      "id": "2f003b5ccbef",
      "title": "中国财税史-中南财经政法大学",
      "summary": "https://www.icourse163.org/course/ZNUEDU-1207039804\n财政是国家治理的基础和重要支柱。从历史上看，在历次重大社会改革中财政改革都居于核心位置。本门课程从历史学视角，通过深入浅出的语言，在动态的历史长河中探寻国家兴衰更替背后的财政因素，总结中国财税制度向近代化、现代化转型的脉络、特点、规律和经验教训，传承与创新中国优秀财税制度与文化。",
      "source": "B站",
      "platform_class": "platform-bilibili",
      "author": "工地锁螺丝",
      "url": "http://www.bilibili.com/video/av92669549",
      "time": "2026-03-30 20:10",
      "heat": 5599,
      "discussions": "99",
      "tags": [
        "税制",
        "财政"
      ],
      "isHot": false,
      "detail": "<p>https://www.icourse163.org/course/ZNUEDU-1207039804\n财政是国家治理的基础和重要支柱。从历史上看，在历次重大社会改革中财政改革都居于核心位置。本门课程从历史学视角，通过深入浅出的语言，在动态的历史长河中探寻国家兴衰更替背后的财政因素，总结中国财税制度向近代化、现代化转型的脉络、特点、规律和经验教训，传承与创新中国优秀财税制度与文化。</p>"
    },
    {
      "id": "bf65fdf37dfe",
      "title": "【2025】税务师-税法二-精讲班",
      "summary": "【2025】税务师-税法二-精讲班",
      "source": "B站",
      "platform_class": "platform-bilibili",
      "author": "陈清泉的外语老师",
      "url": "http://www.bilibili.com/video/av115475950342846",
      "time": "2026-03-30 20:10",
      "heat": 5461,
      "discussions": "42",
      "tags": [
        "税务",
        "税法",
        "税务师"
      ],
      "isHot": false,
      "detail": "<p>【2025】税务师-税法二-精讲班</p>"
    },
    {
      "id": "81afac999010",
      "title": "【法律公开课】股权架构与税务筹划【轻松搞定“法律+股权+税筹”】（完整有课件）",
      "summary": "内容仅用于学习，课程来源于网络，侵删！！！ \n\n课件链接：https://pan.quark.cn/s/755b3cbac39a",
      "source": "B站",
      "platform_class": "platform-bilibili",
      "author": "资源之家",
      "url": "http://www.bilibili.com/video/av113305985227642",
      "time": "2026-03-30 20:10",
      "heat": 4217,
      "discussions": "25",
      "tags": [
        "税务",
        "税筹",
        "税务筹划"
      ],
      "isHot": false,
      "detail": "<p>内容仅用于学习，课程来源于网络，侵删！！！ \n\n课件链接：https://pan.quark.cn/s/755b3cbac39a</p>"
    },
    {
      "id": "7eb3c3d480dd",
      "title": "T1. 一口气了解中国税收体系！中国开征哪些税？核心税种是什么？中外税制有哪些差异？",
      "summary": "税收，是我们生活中最熟悉的陌生人。它深刻影响着我们的收入、消费和未来，但你真的了解它吗？\n\n为什么说税收是文明的代价，也是社会的基石？\n\n国家的钱从哪里来，又到哪里去？\n\n当我们在讨论税制时，我们到底在讨论什么？\n\n欢迎来到「财税解码」。本系列将带你穿透繁杂的表象，直击硬核的税务底层逻辑。我们将从零开始，用最清晰的视角，解读那些与你息息相关的财税原理。",
      "source": "B站",
      "platform_class": "platform-bilibili",
      "author": "财税解码",
      "url": "http://www.bilibili.com/video/av115587267168391",
      "time": "2026-03-30 20:10",
      "heat": 3985,
      "discussions": "106",
      "tags": [
        "税收",
        "税务",
        "税制"
      ],
      "isHot": false,
      "detail": "<p>税收，是我们生活中最熟悉的陌生人。它深刻影响着我们的收入、消费和未来，但你真的了解它吗？\n\n为什么说税收是文明的代价，也是社会的基石？\n\n国家的钱从哪里来，又到哪里去？\n\n当我们在讨论税制时，我们到底在讨论什么？\n\n欢迎来到「财税解码」。本系列将带你穿透繁杂的表象，直击硬核的税务底层逻辑。我们将从零开始，用最清晰的视角，解读那些与你息息相关的财税原理。</p>"
    },
    {
      "id": "1b690e1edc0d",
      "title": "税收筹划_厦门大学_主讲-童锦治 56讲",
      "summary": "免费获取本视频PPT讲义、试卷、视频合集的办法请看置顶评论！！！\n\n通过本课程的学习，学生能够正确地理解、掌握和运用税收筹划的基本知识、方法与技能，并能够在今后的涉税活动和涉税工作中合理合法地节约税收成本。",
      "source": "B站",
      "platform_class": "platform-bilibili",
      "author": "万卷阁",
      "url": "http://www.bilibili.com/video/av205888002",
      "time": "2026-03-30 20:10",
      "heat": 3776,
      "discussions": "23",
      "tags": [
        "税收"
      ],
      "isHot": false,
      "detail": "<p>免费获取本视频PPT讲义、试卷、视频合集的办法请看置顶评论！！！\n\n通过本课程的学习，学生能够正确地理解、掌握和运用税收筹划的基本知识、方法与技能，并能够在今后的涉税活动和涉税工作中合理合法地节约税收成本。</p>"
    },
    {
      "id": "73359fb006c0",
      "title": "个人所得税详细的操作步骤，注意这几点可多退税",
      "summary": "个人所得税详细的操作步骤，注意这几点可多退税",
      "source": "B站",
      "platform_class": "platform-bilibili",
      "author": "又学到一招",
      "url": "http://www.bilibili.com/video/av114097232288288",
      "time": "2026-03-30 20:10",
      "heat": 3737,
      "discussions": "28",
      "tags": [
        "个人所得税",
        "退税"
      ],
      "isHot": false,
      "detail": "<p>个人所得税详细的操作步骤，注意这几点可多退税</p>"
    },
    {
      "id": "768994f28aa7",
      "title": "2026会计实务做账教程 出纳会计全盘账小规模一般纳税人 商业、工业、建筑工程、记账报税成本核算税务筹划金蝶用友高清课程 吴娟老师",
      "summary": "2026会计实务做账教程 出纳会计全盘账小规模一般纳税人 商业、工业、建筑工程、记账报税成本核算税务筹划金蝶用友高清课程 吴娟老师",
      "source": "B站",
      "platform_class": "platform-bilibili",
      "author": "国学资源文化大本营",
      "url": "http://www.bilibili.com/video/av115761766990115",
      "time": "2026-03-30 20:10",
      "heat": 3576,
      "discussions": "32",
      "tags": [
        "税务",
        "纳税",
        "税务筹划"
      ],
      "isHot": false,
      "detail": "<p>2026会计实务做账教程 出纳会计全盘账小规模一般纳税人 商业、工业、建筑工程、记账报税成本核算税务筹划金蝶用友高清课程 吴娟老师</p>"
    },
    {
      "id": "e3c95aed4862",
      "title": "【小知识点】增值税原理一个视频说清楚",
      "summary": "【小知识点】增值税原理一个视频说清楚",
      "source": "B站",
      "platform_class": "platform-bilibili",
      "author": "晶酱那个RoSe",
      "url": "http://www.bilibili.com/video/av1850145560",
      "time": "2026-03-30 20:10",
      "heat": 3379,
      "discussions": "89",
      "tags": [
        "增值税"
      ],
      "isHot": false,
      "detail": "<p>【小知识点】增值税原理一个视频说清楚</p>"
    },
    {
      "id": "fc344e9cb32f",
      "title": "还搞不懂增值税？增值税完整讲解来啦！",
      "summary": "还搞不懂增值税？增值税完整讲解来啦！",
      "source": "B站",
      "platform_class": "platform-bilibili",
      "author": "审计鱼帮主",
      "url": "http://www.bilibili.com/video/av113837822970283",
      "time": "2026-03-30 20:10",
      "heat": 3204,
      "discussions": "31",
      "tags": [
        "增值税"
      ],
      "isHot": false,
      "detail": "<p>还搞不懂增值税？增值税完整讲解来啦！</p>"
    },
    {
      "id": "3e9e61e67d47",
      "title": "【国考面试05】漫画题“放水养鱼与减税降费”（国税思维vs哲学思维）",
      "summary": "-",
      "source": "B站",
      "platform_class": "platform-bilibili",
      "author": "小野鸭撩公考",
      "url": "http://www.bilibili.com/video/av738747474",
      "time": "2026-03-30 20:10",
      "heat": 3085,
      "discussions": "181",
      "tags": [
        "减税"
      ],
      "isHot": false,
      "detail": "<p>-</p>"
    },
    {
      "id": "ec31ca22aa25",
      "title": "初级会计实务必考知识点：增值税！马老师答应你，就用一瓶可乐，让你成为增值税专家！",
      "summary": "初级会计实务必考知识点：增值税！马老师答应你，就用一瓶可乐，让你成为增值税专家！",
      "source": "B站",
      "platform_class": "platform-bilibili",
      "author": "马勇老师讲会计",
      "url": "http://www.bilibili.com/video/av114199355196310",
      "time": "2026-03-30 20:10",
      "heat": 3006,
      "discussions": "31",
      "tags": [
        "增值税",
        "会计",
        "初级会计"
      ],
      "isHot": false,
      "detail": "<p>初级会计实务必考知识点：增值税！马老师答应你，就用一瓶可乐，让你成为增值税专家！</p>"
    },
    {
      "id": "605d99d846f2",
      "title": "增值税新政，超详细解读",
      "summary": "增值税新政，超详细解读",
      "source": "B站",
      "platform_class": "platform-bilibili",
      "author": "血刀喵祖",
      "url": "http://www.bilibili.com/video/av116151619158045",
      "time": "2026-03-30 20:10",
      "heat": 3000,
      "discussions": "31",
      "tags": [
        "增值税"
      ],
      "isHot": false,
      "detail": "<p>增值税新政，超详细解读</p>"
    },
    {
      "id": "5d00061ea055",
      "title": "解密税收——为什么要收税？",
      "summary": "解密税收——为什么要收税？",
      "source": "B站",
      "platform_class": "platform-bilibili",
      "author": "杨浦税务",
      "url": "http://www.bilibili.com/video/av715499305",
      "time": "2026-03-30 20:10",
      "heat": 2919,
      "discussions": "17",
      "tags": [
        "税收"
      ],
      "isHot": false,
      "detail": "<p>解密税收——为什么要收税？</p>"
    },
    {
      "id": "f5a979db19c4",
      "title": "2025最新 税务筹划课程增值税个税企业所得税风险规避合理避税税务会计教程  吴娟老师",
      "summary": "2025最新 税务筹划课程增值税个税企业所得税风险规避合理避税税务会计教程  吴娟老师",
      "source": "B站",
      "platform_class": "platform-bilibili",
      "author": "笃言教育",
      "url": "http://www.bilibili.com/video/av346661443",
      "time": "2026-03-30 20:10",
      "heat": 2797,
      "discussions": "20",
      "tags": [
        "增值税",
        "企业所得税",
        "个税"
      ],
      "isHot": false,
      "detail": "<p>2025最新 税务筹划课程增值税个税企业所得税风险规避合理避税税务会计教程  吴娟老师</p>"
    },
    {
      "id": "631176223dd9",
      "title": "二次退税实战教学",
      "summary": "二次退税实战教学",
      "source": "B站",
      "platform_class": "platform-bilibili",
      "author": "退税一姐bba7933",
      "url": "http://www.bilibili.com/video/av116217134187702",
      "time": "2026-03-30 20:10",
      "heat": 2578,
      "discussions": "64",
      "tags": [
        "退税"
      ],
      "isHot": false,
      "detail": "<p>二次退税实战教学</p>"
    },
    {
      "id": "0433c7ac23ee",
      "title": "央视纪录片：《皇粮国税》",
      "summary": "-",
      "source": "B站",
      "platform_class": "platform-bilibili",
      "author": "石頁君",
      "url": "http://www.bilibili.com/video/av770441231",
      "time": "2026-03-30 20:10",
      "heat": 2226,
      "discussions": "14",
      "tags": [],
      "isHot": false,
      "detail": "<p>-</p>"
    },
    {
      "id": "73137b0a49c8",
      "title": "21天税收筹划精英特训营",
      "summary": "21天税收筹划精英特训营",
      "source": "B站",
      "platform_class": "platform-bilibili",
      "author": "账号已注销",
      "url": "http://www.bilibili.com/video/av773186871",
      "time": "2026-03-30 20:10",
      "heat": 2133,
      "discussions": "16",
      "tags": [
        "税收"
      ],
      "isHot": false,
      "detail": "<p>21天税收筹划精英特训营</p>"
    },
    {
      "id": "b0441ff3efaf",
      "title": "增值税法及配套政策变化要点与实务风险分析",
      "summary": "https://www.cctaaedu.cn/pc.html#/zhiboingVod?id=1199\n课程主题：增值税法及配套政策变化要点与实务风险分析\n直播时间：2026年2月10日 上午9:30\n老师简介：郭磊 税务师专家，国家税务总局级师资，国家税务总局税务干部学院副教授（兼）",
      "source": "B站",
      "platform_class": "platform-bilibili",
      "author": "良眛阿远",
      "url": "http://www.bilibili.com/video/av116050083454267",
      "time": "2026-03-30 20:10",
      "heat": 2056,
      "discussions": "49",
      "tags": [
        "增值税",
        "税务",
        "税法"
      ],
      "isHot": false,
      "detail": "<p>https://www.cctaaedu.cn/pc.html#/zhiboingVod?id=1199\n课程主题：增值税法及配套政策变化要点与实务风险分析\n直播时间：2026年2月10日 上午9:30\n老师简介：郭磊 税务师专家，国家税务总局级师资，国家税务总局税务干部学院副教授（兼）</p>"
    },
    {
      "id": "ab97d67b28ed",
      "title": "T5. 一口气学会计算个人所得税——工资收入，劳务报酬，综合所得，经营所得，利息，分红，租金全案例",
      "summary": "工资个税怎么扣？家庭开支如何减税？退税申报到底怎么操作？不管是打工人、自由职业者，还是老板、投资人，搞懂个税计算都是必修课！本期视频由易到难拆解工资、劳务报酬、经营所得、利息分红、房租等全品类收入计税规则，用小张的真实案例手把手教你算清应缴税款，吃透汇算退税技巧，看完人人都能自己算个税！下期聚焦资本利得税，点赞收藏关注，解锁更多财税干货～",
      "source": "B站",
      "platform_class": "platform-bilibili",
      "author": "财税解码",
      "url": "http://www.bilibili.com/video/av115779836052507",
      "time": "2026-03-30 20:10",
      "heat": 1853,
      "discussions": "49",
      "tags": [
        "个人所得税",
        "个税",
        "退税"
      ],
      "isHot": false,
      "detail": "<p>工资个税怎么扣？家庭开支如何减税？退税申报到底怎么操作？不管是打工人、自由职业者，还是老板、投资人，搞懂个税计算都是必修课！本期视频由易到难拆解工资、劳务报酬、经营所得、利息分红、房租等全品类收入计税规则，用小张的真实案例手把手教你算清应缴税款，吃透汇算退税技巧，看完人人都能自己算个税！下期聚焦资本利得税，点赞收藏关注，解锁更多财税干货～</p>"
    },
    {
      "id": "a2299896eb03",
      "title": "增值税是什么意思？",
      "summary": "增值税是什么意思？",
      "source": "B站",
      "platform_class": "platform-bilibili",
      "author": "小辉教你开公司",
      "url": "http://www.bilibili.com/video/av115067022478569",
      "time": "2026-03-30 20:10",
      "heat": 1853,
      "discussions": "28",
      "tags": [
        "增值税"
      ],
      "isHot": false,
      "detail": "<p>增值税是什么意思？</p>"
    },
    {
      "id": "01cfe37ef206",
      "title": "26年税务师增值税法变动说明（上）增值税立法第一课，抢先掌握26年新考点",
      "summary": "26年税务师增值税法变动说明（上）增值税立法第一课，抢先掌握26年新考点",
      "source": "B站",
      "platform_class": "platform-bilibili",
      "author": "之了课堂",
      "url": "http://www.bilibili.com/video/av115892075631719",
      "time": "2026-03-30 20:10",
      "heat": 1619,
      "discussions": "26",
      "tags": [
        "增值税",
        "税务",
        "税法"
      ],
      "isHot": false,
      "detail": "<p>26年税务师增值税法变动说明（上）增值税立法第一课，抢先掌握26年新考点</p>"
    },
    {
      "id": "5ead18f5da55",
      "title": "税收宣传微电影《我们》",
      "summary": "音乐为剧情原创制作，分为四个部分。",
      "source": "B站",
      "platform_class": "platform-bilibili",
      "author": "导演胡子",
      "url": "http://www.bilibili.com/video/av547663912",
      "time": "2026-03-30 20:10",
      "heat": 1301,
      "discussions": "9",
      "tags": [
        "税收"
      ],
      "isHot": false,
      "detail": "<p>音乐为剧情原创制作，分为四个部分。</p>"
    },
    {
      "id": "70fa724261c6",
      "title": "增值税优惠政策衔接事项深度解析（财税2026年 第10号公告解读）",
      "summary": "本视频内容深度解析财税2026年第10号公告相关内容\n主要包括\n1.政策背景与核心变化\n2.行业解读与实操案例\n3.风险防控与总结展望\n干货满满，诚意满满。\n财税问题千千万，关注侯哥找答案。\n如果觉得不错，记得一键三连噢。您的支持是我创作的动力！",
      "source": "B站",
      "platform_class": "platform-bilibili",
      "author": "侯哥讲财税",
      "url": "http://www.bilibili.com/video/av116136083457574",
      "time": "2026-03-30 20:10",
      "heat": 1061,
      "discussions": "32",
      "tags": [
        "增值税"
      ],
      "isHot": false,
      "detail": "<p>本视频内容深度解析财税2026年第10号公告相关内容\n主要包括\n1.政策背景与核心变化\n2.行业解读与实操案例\n3.风险防控与总结展望\n干货满满，诚意满满。\n财税问题千千万，关注侯哥找答案。\n如果觉得不错，记得一键三连噢。您的支持是我创作的动力！</p>"
    },
    {
      "id": "0630bad7db14",
      "title": "90秒带你读懂减税降费",
      "summary": "90秒带你读懂减税降费",
      "source": "B站",
      "platform_class": "platform-bilibili",
      "author": "自然人税与法研究室",
      "url": "http://www.bilibili.com/video/av88220139",
      "time": "2026-03-30 20:10",
      "heat": 843,
      "discussions": "1",
      "tags": [
        "减税"
      ],
      "isHot": false,
      "detail": "<p>90秒带你读懂减税降费</p>"
    },
    {
      "id": "e668ca9ded47",
      "title": "2024年税务热点｜结构性减税降费｜综合分析｜小王老师",
      "summary": "2024年税务热点｜结构性减税降费｜综合分析｜小王老师",
      "source": "B站",
      "platform_class": "platform-bilibili",
      "author": "小王老师只教面试",
      "url": "http://www.bilibili.com/video/av1050613719",
      "time": "2026-03-30 20:10",
      "heat": 800,
      "discussions": "10",
      "tags": [
        "税务",
        "减税"
      ],
      "isHot": false,
      "detail": "<p>2024年税务热点｜结构性减税降费｜综合分析｜小王老师</p>"
    },
    {
      "id": "e151d05ddae0",
      "title": "税务筹划，就这几招，不用再去找人咨询了，自己往头上按一下，但是执行落地的时候最好别自己弄，容易那啥",
      "summary": "-",
      "source": "B站",
      "platform_class": "platform-bilibili",
      "author": "我的大头是最大的大头",
      "url": "http://www.bilibili.com/video/av114466968567886",
      "time": "2026-03-30 20:10",
      "heat": 799,
      "discussions": "9",
      "tags": [
        "税务",
        "税务筹划"
      ],
      "isHot": false,
      "detail": "<p>-</p>"
    },
    {
      "id": "4ccb9305d0cf",
      "title": "增值税配套政策详解（全20讲）｜持续更新",
      "summary": "本内容为增值税配套政策详解系列课程，\n总计更新20讲，后续内容持续更新中。\n内容围绕增值税新旧政策核心差异点、实务要点展开讲解，\n适合财会从业者、办税人员、备考同学系统学习。",
      "source": "B站",
      "platform_class": "platform-bilibili",
      "author": "斯尔教育",
      "url": "http://www.bilibili.com/video/av116243810029832",
      "time": "2026-03-30 20:10",
      "heat": 786,
      "discussions": "6",
      "tags": [
        "增值税"
      ],
      "isHot": false,
      "detail": "<p>本内容为增值税配套政策详解系列课程，\n总计更新20讲，后续内容持续更新中。\n内容围绕增值税新旧政策核心差异点、实务要点展开讲解，\n适合财会从业者、办税人员、备考同学系统学习。</p>"
    },
    {
      "id": "86dadd161fa6",
      "title": "一门课轻松搞定个人所得税",
      "summary": "一门课轻松搞定个人所得税",
      "source": "B站",
      "platform_class": "platform-bilibili",
      "author": "bili_17687125472",
      "url": "http://www.bilibili.com/video/av836261477",
      "time": "2026-03-30 20:10",
      "heat": 782,
      "discussions": "2",
      "tags": [
        "个人所得税"
      ],
      "isHot": false,
      "detail": "<p>一门课轻松搞定个人所得税</p>"
    },
    {
      "id": "961f77fbb6ee",
      "title": "个人所得税·专项附加扣除解析",
      "summary": "个人所得税·专项附加扣除解析",
      "source": "B站",
      "platform_class": "platform-bilibili",
      "author": "Shirley_蛮",
      "url": "http://www.bilibili.com/video/av114896045872200",
      "time": "2026-03-30 20:10",
      "heat": 702,
      "discussions": "13",
      "tags": [
        "个人所得税",
        "专项附加扣除"
      ],
      "isHot": false,
      "detail": "<p>个人所得税·专项附加扣除解析</p>"
    },
    {
      "id": "bdfd238a9fc5",
      "title": "香港个人所得税 Hongkong Salaries Tax HKICPA课程",
      "summary": "香港个人所得税 Hongkong Salaries Tax （2021 update）",
      "source": "B站",
      "platform_class": "platform-bilibili",
      "author": "全球财税解析",
      "url": "http://www.bilibili.com/video/av677655694",
      "time": "2026-03-30 20:10",
      "heat": 612,
      "discussions": "2",
      "tags": [
        "个人所得税",
        "CPA"
      ],
      "isHot": false,
      "detail": "<p>香港个人所得税 Hongkong Salaries Tax （2021 update）</p>"
    },
    {
      "id": "071909c8538d",
      "title": "李克强：减税降费是施肥浇到根上",
      "summary": "3月11日上午十三届全国人大五次会议闭幕后，国务院总理李克强在人民大会堂三楼金色大厅出席记者会并回答中外记者提问，就减税降费问题，李克强总理表示，去年我们和十几位企业家交谈，他们谈到运行中的困难。在大规模投资、发放消费券、给企业减税降费中，他们几乎异口同声地选择了第三项，因为这是最直接、最公平、最有效率的。从今年收到的报告看，大家普遍把减税降费作为对政府宏观政策的第一个期待，看来施肥还真是要浇到根",
      "source": "B站",
      "platform_class": "platform-bilibili",
      "author": "BRTV新闻",
      "url": "http://www.bilibili.com/video/av254697766",
      "time": "2026-03-30 20:10",
      "heat": 551,
      "discussions": "1",
      "tags": [
        "减税"
      ],
      "isHot": false,
      "detail": "<p>3月11日上午十三届全国人大五次会议闭幕后，国务院总理李克强在人民大会堂三楼金色大厅出席记者会并回答中外记者提问，就减税降费问题，李克强总理表示，去年我们和十几位企业家交谈，他们谈到运行中的困难。在大规模投资、发放消费券、给企业减税降费中，他们几乎异口同声地选择了第三项，因为这是最直接、最公平、最有效率的。从今年收到的报告看，大家普遍把减税降费作为对政府宏观政策的第一个期待，看来施肥还真是要浇到根</p>"
    },
    {
      "id": "656c4e2d15e9",
      "title": "（全63集）全面税务规划实战训练营",
      "summary": "bilibili\n（全63集）全面税务规划实战训练营",
      "source": "B站",
      "platform_class": "platform-bilibili",
      "author": "网络学习资料整理3",
      "url": "http://www.bilibili.com/video/av115659006543227",
      "time": "2026-03-30 20:10",
      "heat": 502,
      "discussions": "13",
      "tags": [
        "税务"
      ],
      "isHot": false,
      "detail": "<p>bilibili\n（全63集）全面税务规划实战训练营</p>"
    },
    {
      "id": "17949ee1ed77",
      "title": "会计实务mg动画教学|第八章1 增值税",
      "summary": "会计实务mg动画教学|第八章1 增值税",
      "source": "B站",
      "platform_class": "platform-bilibili",
      "author": "中财国培",
      "url": "http://www.bilibili.com/video/av875334855",
      "time": "2026-03-30 20:10",
      "heat": 501,
      "discussions": "0",
      "tags": [
        "增值税",
        "会计"
      ],
      "isHot": false,
      "detail": "<p>会计实务mg动画教学|第八章1 增值税</p>"
    },
    {
      "id": "013f11a542e1",
      "title": "税务筹划 01税筹自述",
      "summary": "税务筹划 01税筹自述",
      "source": "B站",
      "platform_class": "platform-bilibili",
      "author": "bili_56988169334",
      "url": "http://www.bilibili.com/video/av115484221578993",
      "time": "2026-03-30 20:10",
      "heat": 478,
      "discussions": "4",
      "tags": [
        "税务",
        "税筹",
        "税务筹划"
      ],
      "isHot": false,
      "detail": "<p>税务筹划 01税筹自述</p>"
    },
    {
      "id": "8dba85532775",
      "title": "高考政治经济最难的点：减税降费，彻底搞懂",
      "summary": "#高中政治 #高考政治 #高考 #政治 #高中",
      "source": "B站",
      "platform_class": "platform-bilibili",
      "author": "FredTao高考政治",
      "url": "http://www.bilibili.com/video/av114965235107926",
      "time": "2026-03-30 20:10",
      "heat": 448,
      "discussions": "5",
      "tags": [
        "减税"
      ],
      "isHot": false,
      "detail": "<p>#高中政治 #高考政治 #高考 #政治 #高中</p>"
    },
    {
      "id": "97d03200d247",
      "title": "什么是2022年减税降费政策？",
      "summary": "什么是2022年减税降费政策？",
      "source": "B站",
      "platform_class": "platform-bilibili",
      "author": "青声细语话财经",
      "url": "http://www.bilibili.com/video/av423088833",
      "time": "2026-03-30 20:10",
      "heat": 366,
      "discussions": "3",
      "tags": [
        "减税"
      ],
      "isHot": false,
      "detail": "<p>什么是2022年减税降费政策？</p>"
    },
    {
      "id": "cf0d308d54c9",
      "title": "知否知否——减税降费可有享受",
      "summary": "视频转自央视新闻",
      "source": "B站",
      "platform_class": "platform-bilibili",
      "author": "夏雨虫子_会咕OVO",
      "url": "http://www.bilibili.com/video/av47900816",
      "time": "2026-03-30 20:10",
      "heat": 342,
      "discussions": "3",
      "tags": [
        "减税"
      ],
      "isHot": false,
      "detail": "<p>视频转自央视新闻</p>"
    },
    {
      "id": "33da84ae5652",
      "title": "《税务筹划与财务管理》老板的财税课 38视频+1资料 17.5G",
      "summary": "yg\n水印内容是非法侵权者制作的可能是病毒或诈骗，注意信息安全！\r\n对完整内容感兴趣请私信up标题或链接，纯支持请充电，关注，投币，点赞，转发，评论，评论内容：感谢up，喜欢这个视频！\r\n资料来自全球公开开源互联网渠道，版权归原作者，如觉不妥务必请私信删除！\r\n资料仅供学习娱乐交流不作为医学，投资建议！",
      "source": "B站",
      "platform_class": "platform-bilibili",
      "author": "高端网创试错赚钱大师",
      "url": "http://www.bilibili.com/video/av917589275",
      "time": "2026-03-30 20:10",
      "heat": 330,
      "discussions": "4",
      "tags": [
        "税务",
        "税务筹划",
        "财务"
      ],
      "isHot": false,
      "detail": "<p>yg\n水印内容是非法侵权者制作的可能是病毒或诈骗，注意信息安全！\r\n对完整内容感兴趣请私信up标题或链接，纯支持请充电，关注，投币，点赞，转发，评论，评论内容：感谢up，喜欢这个视频！\r\n资料来自全球公开开源互联网渠道，版权归原作者，如觉不妥务必请私信删除！\r\n资料仅供学习娱乐交流不作为医学，投资建议！</p>"
    },
    {
      "id": "24352d376d8c",
      "title": "纳税筹划（税务筹划）技巧与案例分析--增值税、企业所得税、个税、印花税等",
      "summary": "这是试听课，想学习完整版V我：fewone001",
      "source": "B站",
      "platform_class": "platform-bilibili",
      "author": "跟刘老师学会计实操",
      "url": "http://www.bilibili.com/video/av115811578609953",
      "time": "2026-03-30 20:10",
      "heat": 317,
      "discussions": "1",
      "tags": [
        "增值税",
        "企业所得税",
        "个税"
      ],
      "isHot": false,
      "detail": "<p>这是试听课，想学习完整版V我：fewone001</p>"
    },
    {
      "id": "bf1716bbf206",
      "title": "第八讲 企业全流程税务筹划",
      "summary": "税务筹划50讲之第八讲企业全流程税务筹划思路",
      "source": "B站",
      "platform_class": "platform-bilibili",
      "author": "财法价值圈",
      "url": "http://www.bilibili.com/video/av115830838790277",
      "time": "2026-03-30 20:10",
      "heat": 306,
      "discussions": "9",
      "tags": [
        "税务",
        "税务筹划"
      ],
      "isHot": false,
      "detail": "<p>税务筹划50讲之第八讲企业全流程税务筹划思路</p>"
    },
    {
      "id": "b04c87a6bda3",
      "title": "2026年税务师考试-税法一精讲小丰老师",
      "summary": "2026年税务师考试税法一讲解！",
      "source": "B站",
      "platform_class": "platform-bilibili",
      "author": "慧学会考",
      "url": "http://www.bilibili.com/video/av116300080811867",
      "time": "2026-03-30 20:10",
      "heat": 287,
      "discussions": "8",
      "tags": [
        "税务",
        "税法",
        "税务师"
      ],
      "isHot": false,
      "detail": "<p>2026年税务师考试税法一讲解！</p>"
    },
    {
      "id": "6d9c022544b0",
      "title": "个人所得税期末速成",
      "summary": "-",
      "source": "B站",
      "platform_class": "platform-bilibili",
      "author": "尹顺涛",
      "url": "http://www.bilibili.com/video/av115191660480913",
      "time": "2026-03-30 20:10",
      "heat": 281,
      "discussions": "1",
      "tags": [
        "个人所得税"
      ],
      "isHot": false,
      "detail": "<p>-</p>"
    },
    {
      "id": "37223d88bc0e",
      "title": "2分钟看懂今年减税降费举措",
      "summary": "2分钟看懂今年减税降费举措",
      "source": "B站",
      "platform_class": "platform-bilibili",
      "author": "青海普法",
      "url": "http://www.bilibili.com/video/av502322992",
      "time": "2026-03-30 20:10",
      "heat": 255,
      "discussions": "0",
      "tags": [
        "减税"
      ],
      "isHot": false,
      "detail": "<p>2分钟看懂今年减税降费举措</p>"
    },
    {
      "id": "88b860d9ed66",
      "title": "2026年最新：报税实务（企业必交的5税2费）--增值税、企业所得税预缴、个税预缴、附加税费、印花税",
      "summary": "这是试听课，想学习完整版V：fewone001",
      "source": "B站",
      "platform_class": "platform-bilibili",
      "author": "跟刘老师学会计实操",
      "url": "http://www.bilibili.com/video/av116281558698754",
      "time": "2026-03-30 20:10",
      "heat": 251,
      "discussions": "1",
      "tags": [
        "增值税",
        "企业所得税",
        "个税"
      ],
      "isHot": false,
      "detail": "<p>这是试听课，想学习完整版V：fewone001</p>"
    },
    {
      "id": "ee15793c6960",
      "title": "（九）国考税务知识（减税降费专题）",
      "summary": "大家一起加油呀！上岸万岁！",
      "source": "B站",
      "platform_class": "platform-bilibili",
      "author": "号嘿哈嘿",
      "url": "http://www.bilibili.com/video/av881845773",
      "time": "2026-03-30 20:10",
      "heat": 234,
      "discussions": "4",
      "tags": [
        "税务",
        "减税"
      ],
      "isHot": false,
      "detail": "<p>大家一起加油呀！上岸万岁！</p>"
    },
    {
      "id": "3cbef5b92a3b",
      "title": "第三集《减税降费 利企惠民》",
      "summary": "第三集《减税降费 利企惠民》",
      "source": "B站",
      "platform_class": "platform-bilibili",
      "author": "中经全媒体",
      "url": "http://www.bilibili.com/video/av380998753",
      "time": "2026-03-30 20:10",
      "heat": 140,
      "discussions": "1",
      "tags": [
        "减税"
      ],
      "isHot": false,
      "detail": "<p>第三集《减税降费 利企惠民》</p>"
    },
    {
      "id": "0d291c541f46",
      "title": "减税降费_认真生活篇",
      "summary": "Director wechat：a582587847",
      "source": "B站",
      "platform_class": "platform-bilibili",
      "author": "Sao小逗",
      "url": "http://www.bilibili.com/video/av53425225",
      "time": "2026-03-30 20:10",
      "heat": 117,
      "discussions": "1",
      "tags": [
        "减税"
      ],
      "isHot": false,
      "detail": "<p>Director wechat：a582587847</p>"
    },
    {
      "id": "5e87931e22b6",
      "title": "2022年减税降费之企业所得税专场",
      "summary": "2022年减税降费之企业所得税专场",
      "source": "B站",
      "platform_class": "platform-bilibili",
      "author": "杨浦税务",
      "url": "http://www.bilibili.com/video/av810762962",
      "time": "2026-03-30 20:10",
      "heat": 108,
      "discussions": "1",
      "tags": [
        "企业所得税",
        "减税"
      ],
      "isHot": false,
      "detail": "<p>2022年减税降费之企业所得税专场</p>"
    },
    {
      "id": "56b353de8392",
      "title": "减税降费 给你更美好的未来",
      "summary": "由国家税务总局景县税务局拍制的减税降费宣传视频",
      "source": "B站",
      "platform_class": "platform-bilibili",
      "author": "三言二拍",
      "url": "http://www.bilibili.com/video/av57812632",
      "time": "2026-03-30 20:10",
      "heat": 78,
      "discussions": "0",
      "tags": [
        "税务",
        "减税",
        "税务总局"
      ],
      "isHot": false,
      "detail": "<p>由国家税务总局景县税务局拍制的减税降费宣传视频</p>"
    },
    {
      "id": "befcb757849b",
      "title": "上海事业单位面试热点分析：减税降费",
      "summary": "2021年上海事业单位笔试已过，5月20日出分，这一个月时间我们要好好利用呀~\n上海事业单位考题类型较广泛：分为岗位匹配、综合分析、人际关系应急应变、计划组织及其他。\n需要以上相关资料或进一步答疑请加19916744766",
      "source": "B站",
      "platform_class": "platform-bilibili",
      "author": "公考小秘书",
      "url": "http://www.bilibili.com/video/av418122236",
      "time": "2026-03-30 20:10",
      "heat": 68,
      "discussions": "0",
      "tags": [
        "减税"
      ],
      "isHot": false,
      "detail": "<p>2021年上海事业单位笔试已过，5月20日出分，这一个月时间我们要好好利用呀~\n上海事业单位考题类型较广泛：分为岗位匹配、综合分析、人际关系应急应变、计划组织及其他。\n需要以上相关资料或进一步答疑请加19916744766</p>"
    },
    {
      "id": "4daf321b86a9",
      "title": "[税收征管 38]“十五五”税制改革热点",
      "summary": "[税收征管 38]“十五五”税制改革热点",
      "source": "B站",
      "platform_class": "platform-bilibili",
      "author": "麦麦麦麦旋风风风",
      "url": "http://www.bilibili.com/video/av116300147854005",
      "time": "2026-03-30 20:10",
      "heat": 67,
      "discussions": "0",
      "tags": [
        "税收",
        "税制"
      ],
      "isHot": false,
      "detail": "<p>[税收征管 38]“十五五”税制改革热点</p>"
    },
    {
      "id": "c897e6baf102",
      "title": "《这一年，我们一起走过》减税降费短片",
      "summary": "去年帮朋友制作的税务局短片。",
      "source": "B站",
      "platform_class": "platform-bilibili",
      "author": "加德纳斯papa",
      "url": "http://www.bilibili.com/video/av627775698",
      "time": "2026-03-30 20:10",
      "heat": 62,
      "discussions": "1",
      "tags": [
        "税务",
        "减税",
        "税务局"
      ],
      "isHot": false,
      "detail": "<p>去年帮朋友制作的税务局短片。</p>"
    },
    {
      "id": "8274e322e30b",
      "title": "叶建平税务筹划案例实战课程",
      "summary": "叶建平税务筹划全程通关班\n叶建平税务筹划一轮基础课\n叶建平税务筹划二轮强化课\n叶建平税务筹划三轮冲刺课\n叶建平税务筹划考点串讲课\n叶建平税务筹划核心方法课\n叶建平税务筹划工具应用课\n叶建平税务筹划案例精讲班\n叶建平税务筹划实务操作课\n叶建平税务筹划避坑指南课\n叶建平税务筹划易错点解析\n叶建平税务筹划易混点对比\n叶建平税务筹划思维导图课\n叶建平税务筹划框架搭建课\n叶建平税务筹划政策解读课\n叶建平税务",
      "source": "B站",
      "platform_class": "platform-bilibili",
      "author": "bili_20763725502",
      "url": "http://www.bilibili.com/video/av116273455303510",
      "time": "2026-03-30 20:10",
      "heat": 61,
      "discussions": "0",
      "tags": [
        "税务",
        "税务筹划"
      ],
      "isHot": false,
      "detail": "<p>叶建平税务筹划全程通关班\n叶建平税务筹划一轮基础课\n叶建平税务筹划二轮强化课\n叶建平税务筹划三轮冲刺课\n叶建平税务筹划考点串讲课\n叶建平税务筹划核心方法课\n叶建平税务筹划工具应用课\n叶建平税务筹划案例精讲班\n叶建平税务筹划实务操作课\n叶建平税务筹划避坑指南课\n叶建平税务筹划易错点解析\n叶建平税务筹划易混点对比\n叶建平税务筹划思维导图课\n叶建平税务筹划框架搭建课\n叶建平税务筹划政策解读课\n叶建平税务</p>"
    },
    {
      "id": "79551682869e",
      "title": "税法一增值税速记，葛瑞老师一句话讲透",
      "summary": "-",
      "source": "B站",
      "platform_class": "platform-bilibili",
      "author": "学习Buff补给站",
      "url": "http://www.bilibili.com/video/av116301909598021",
      "time": "2026-03-30 20:10",
      "heat": 57,
      "discussions": "1",
      "tags": [
        "增值税",
        "税法"
      ],
      "isHot": false,
      "detail": "<p>-</p>"
    },
    {
      "id": "f9b251e7f165",
      "title": "组合式减税降费业务培训",
      "summary": "该视频包含：\n1、留抵退税政策解读+案例解析；\n2、“六税两费”优惠政策解读；\n3、2022年延长的7个税收优惠文件解析；\n4、缓交税费政策解读+案例解析；\n5、固定资产加速折旧、小微企业所得税、加计抵减、小规模纳税人增值税优惠；\n6、亏算弥补，研发费用加计扣除案例。",
      "source": "B站",
      "platform_class": "platform-bilibili",
      "author": "飞鱼PLZ",
      "url": "http://www.bilibili.com/video/av683474100",
      "time": "2026-03-30 20:10",
      "heat": 55,
      "discussions": "3",
      "tags": [
        "增值税",
        "企业所得税",
        "个税"
      ],
      "isHot": false,
      "detail": "<p>该视频包含：\n1、留抵退税政策解读+案例解析；\n2、“六税两费”优惠政策解读；\n3、2022年延长的7个税收优惠文件解析；\n4、缓交税费政策解读+案例解析；\n5、固定资产加速折旧、小微企业所得税、加计抵减、小规模纳税人增值税优惠；\n6、亏算弥补，研发费用加计扣除案例。</p>"
    },
    {
      "id": "8ad84b2cd0fc",
      "title": "公益广告——减税降费，伴您同行",
      "summary": "。",
      "source": "B站",
      "platform_class": "platform-bilibili",
      "author": "梁彦芝",
      "url": "http://www.bilibili.com/video/av816347224",
      "time": "2026-03-30 20:10",
      "heat": 55,
      "discussions": "0",
      "tags": [
        "减税"
      ],
      "isHot": false,
      "detail": "<p>。</p>"
    },
    {
      "id": "0a526370d159",
      "title": "一分钟带你看懂什么是个人所得税。",
      "summary": "-",
      "source": "B站",
      "platform_class": "platform-bilibili",
      "author": "比奇堡原著居民_",
      "url": "http://www.bilibili.com/video/av116278471690865",
      "time": "2026-03-30 20:10",
      "heat": 37,
      "discussions": "0",
      "tags": [
        "个人所得税"
      ],
      "isHot": false,
      "detail": "<p>-</p>"
    },
    {
      "id": "f5dd76d18928",
      "title": "【国税面试】新业态，减税降费，税务宣传",
      "summary": "更多公考资料，请关注公众号：滴水成公公考",
      "source": "B站",
      "platform_class": "platform-bilibili",
      "author": "滴水成公公考",
      "url": "http://www.bilibili.com/video/av113841128081716",
      "time": "2026-03-30 20:10",
      "heat": 25,
      "discussions": "0",
      "tags": [
        "税务",
        "减税"
      ],
      "isHot": false,
      "detail": "<p>更多公考资料，请关注公众号：滴水成公公考</p>"
    },
    {
      "id": "97d317343ee6",
      "title": "《老板头痛的财税问题》5集视频 720P高清",
      "summary": "yg\n张金宝《老板头痛的财税问题》5集视频 720P高清",
      "source": "B站",
      "platform_class": "platform-bilibili",
      "author": "高端网创试错赚钱大师",
      "url": "http://www.bilibili.com/video/av116239448021774",
      "time": "2026-03-30 20:10",
      "heat": 25,
      "discussions": "0",
      "tags": [],
      "isHot": false,
      "detail": "<p>yg\n张金宝《老板头痛的财税问题》5集视频 720P高清</p>"
    },
    {
      "id": "b4cbb8131204",
      "title": "2026年1季度税收政策快报",
      "summary": "-",
      "source": "B站",
      "platform_class": "platform-bilibili",
      "author": "财法税芝士派",
      "url": "http://www.bilibili.com/video/av116290131861343",
      "time": "2026-03-30 20:10",
      "heat": 18,
      "discussions": "0",
      "tags": [
        "税收"
      ],
      "isHot": false,
      "detail": "<p>-</p>"
    },
    {
      "id": "514f3ae9e095",
      "title": "国际EPC工程税务筹划与合同拆分",
      "summary": "视频随时会失效，对完整版感兴趣速丝up学习💌  \n声明：资源收集于网络，仅用于试学及购买课程之参考，切勿用于其他用途！如若侵权，请留言告知删除，谢谢！投稿为自制是为了防止二次搬运添加水印，敬请理解",
      "source": "B站",
      "platform_class": "platform-bilibili",
      "author": "爱学习的小木哥",
      "url": "http://www.bilibili.com/video/av116317730376688",
      "time": "2026-03-30 20:10",
      "heat": 0,
      "discussions": "0",
      "tags": [
        "税务",
        "税务筹划"
      ],
      "isHot": false,
      "detail": "<p>视频随时会失效，对完整版感兴趣速丝up学习💌  \n声明：资源收集于网络，仅用于试学及购买课程之参考，切勿用于其他用途！如若侵权，请留言告知删除，谢谢！投稿为自制是为了防止二次搬运添加水印，敬请理解</p>"
    }
  ]
}