{
  "updated_at": "2026-04-16T23:15:01.099836+08:00",
  "count": 58,
  "topics": [
    {
      "id": "42450c5b9cb0",
      "title": "财税改革问路——最重要改革启动，分税制三十年积弊如何解决？",
      "summary": "中央和地方的财税关系，已开始再博弈。\n \n2024年7月，二十届三中全会通过全面深化改革决定，在宏观经济治理部分中明确了深化财税体制改革，“增加地方自主财力，拓展地方税源，适当扩大地方税收管理权限”。\n \n业内人士的共识是，这次改革的重要程度，能够与三十年前的分税制改革相提并论；业内人士没有达成共识的，是要如何完成改革，如何解决分税制留下的问题，如何平衡中央和地方的关系。\n \n人面向未来，但总要回",
      "source": "B站",
      "platform_class": "platform-bilibili",
      "author": "温竣岩",
      "url": "http://www.bilibili.com/video/av116067766638189",
      "time": "2026-04-16 23:15",
      "heat": 245856,
      "discussions": "5333",
      "tags": [
        "税收",
        "税制",
        "税改"
      ],
      "isHot": true,
      "detail": "<p>中央和地方的财税关系，已开始再博弈。\n \n2024年7月，二十届三中全会通过全面深化改革决定，在宏观经济治理部分中明确了深化财税体制改革，“增加地方自主财力，拓展地方税源，适当扩大地方税收管理权限”。\n \n业内人士的共识是，这次改革的重要程度，能够与三十年前的分税制改革相提并论；业内人士没有达成共识的，是要如何完成改革，如何解决分税制留下的问题，如何平衡中央和地方的关系。\n \n人面向未来，但总要回</p>"
    },
    {
      "id": "c5aa989a91e9",
      "title": "电子税务局纳税申报",
      "summary": "关注！！关注我！！！\n不要把我放进收藏夹吃灰！！！",
      "source": "B站",
      "platform_class": "platform-bilibili",
      "author": "ueez",
      "url": "http://www.bilibili.com/video/av90606906",
      "time": "2026-04-16 23:15",
      "heat": 68208,
      "discussions": "1020",
      "tags": [
        "税务",
        "纳税",
        "纳税申报"
      ],
      "isHot": true,
      "detail": "<p>关注！！关注我！！！\n不要把我放进收藏夹吃灰！！！</p>"
    },
    {
      "id": "a8762e77c18d",
      "title": "2025年税务师涉税法律【磨耳朵记考点】（完结）",
      "summary": "打卡表链接：https://pan.baidu.com/share/init?surl=s3kumroHCD7IhZFgffjKpQ&amp;pwd=zhou\n打卡表使用方法：https://www.bilibili.com/video/BV15WwSetEKF/?spm_id_from=333.1387.homepage.video_card.click&amp;vd_source=b7db83",
      "source": "B站",
      "platform_class": "platform-bilibili",
      "author": "周靖老师",
      "url": "http://www.bilibili.com/video/av114357782447831",
      "time": "2026-04-16 23:15",
      "heat": 56179,
      "discussions": "364",
      "tags": [
        "税务",
        "税法",
        "税务师"
      ],
      "isHot": true,
      "detail": "<p>打卡表链接：https://pan.baidu.com/share/init?surl=s3kumroHCD7IhZFgffjKpQ&amp;pwd=zhou\n打卡表使用方法：https://www.bilibili.com/video/BV15WwSetEKF/?spm_id_from=333.1387.homepage.video_card.click&amp;vd_source=b7db83</p>"
    },
    {
      "id": "d1bbb6ebeae0",
      "title": "财会实操： 金税盘增值税专票开具、电子税务局纳税申报、个税自然人税收管理、汇算清缴、纳税申报、工商年检",
      "summary": "财会实操： 金税盘增值税专票开具、电子税务局纳税申报、汇算清缴、纳税申报、工商年检",
      "source": "B站",
      "platform_class": "platform-bilibili",
      "author": "金蝶培训",
      "url": "http://www.bilibili.com/video/av545857498",
      "time": "2026-04-16 23:15",
      "heat": 33020,
      "discussions": "268",
      "tags": [
        "增值税",
        "个税",
        "税收"
      ],
      "isHot": false,
      "detail": "<p>财会实操： 金税盘增值税专票开具、电子税务局纳税申报、汇算清缴、纳税申报、工商年检</p>"
    },
    {
      "id": "b84e1705ba72",
      "title": "【晓夕手把手带你填写】一般纳税人申报表全流程详解！会计实操\\0基础会计出纳入门",
      "summary": "本课程分成两大板块：\r\n一、申报流程+七张报表的逻辑关系 \r\n二、15个案例分享：账务处理+发票开具+申报表填写",
      "source": "B站",
      "platform_class": "platform-bilibili",
      "author": "晓铃铛课堂",
      "url": "http://www.bilibili.com/video/av1901011080",
      "time": "2026-04-16 23:15",
      "heat": 29417,
      "discussions": "535",
      "tags": [
        "纳税",
        "发票",
        "一般纳税人"
      ],
      "isHot": false,
      "detail": "<p>本课程分成两大板块：\r\n一、申报流程+七张报表的逻辑关系 \r\n二、15个案例分享：账务处理+发票开具+申报表填写</p>"
    },
    {
      "id": "5b5ce2dfadaf",
      "title": "5.税收负担-征税以后谁来承担？谁弹性小谁来承担，谁不敏感谁承担",
      "summary": "-",
      "source": "B站",
      "platform_class": "platform-bilibili",
      "author": "kaka老师-EcoFin",
      "url": "http://www.bilibili.com/video/av887657601",
      "time": "2026-04-16 23:15",
      "heat": 22589,
      "discussions": "246",
      "tags": [
        "税收"
      ],
      "isHot": false,
      "detail": "<p>-</p>"
    },
    {
      "id": "afa04dbb9e47",
      "title": "【酷温】公积金改革：强制缴存 举报有理？！",
      "summary": "【酷温】公积金改革：强制缴存 举报有理？！",
      "source": "B站",
      "platform_class": "platform-bilibili",
      "author": "酷温Coolwin",
      "url": "http://www.bilibili.com/video/av116249195453880",
      "time": "2026-04-16 23:15",
      "heat": 21792,
      "discussions": "1356",
      "tags": [
        "公积金"
      ],
      "isHot": false,
      "detail": "<p>【酷温】公积金改革：强制缴存 举报有理？！</p>"
    },
    {
      "id": "cdcd3750d40a",
      "title": "会计实务做账教程 出纳会计全盘账小规模一般纳税人 商业、工业、建筑工程、记账报税成本核算税务筹划金蝶用友高清课程   吴娟老师",
      "summary": "会计实务做账教程 出纳会计全盘账小规模一般纳税人 商业、工业、建筑工程、记账报税成本核算税务筹划金蝶用友高清课程   吴娟老师",
      "source": "B站",
      "platform_class": "platform-bilibili",
      "author": "笃言教育",
      "url": "http://www.bilibili.com/video/av646689565",
      "time": "2026-04-16 23:15",
      "heat": 11514,
      "discussions": "286",
      "tags": [
        "税务",
        "纳税",
        "税务筹划"
      ],
      "isHot": false,
      "detail": "<p>会计实务做账教程 出纳会计全盘账小规模一般纳税人 商业、工业、建筑工程、记账报税成本核算税务筹划金蝶用友高清课程   吴娟老师</p>"
    },
    {
      "id": "3773af46fb63",
      "title": "教你一分钟完成个体户纳税申报(新电局)",
      "summary": "-",
      "source": "B站",
      "platform_class": "platform-bilibili",
      "author": "暾将出兮-",
      "url": "http://www.bilibili.com/video/av1053137057",
      "time": "2026-04-16 23:15",
      "heat": 11243,
      "discussions": "551",
      "tags": [
        "纳税",
        "纳税申报"
      ],
      "isHot": false,
      "detail": "<p>-</p>"
    },
    {
      "id": "efc4ff75ac20",
      "title": "小规模纳税人+企业纳税申报",
      "summary": "免费资料请加VX: lckjxt（备注来自B站）",
      "source": "B站",
      "platform_class": "platform-bilibili",
      "author": "会计学堂官方",
      "url": "http://www.bilibili.com/video/av500052063",
      "time": "2026-04-16 23:15",
      "heat": 10050,
      "discussions": "159",
      "tags": [
        "纳税",
        "纳税申报",
        "小规模纳税人"
      ],
      "isHot": false,
      "detail": "<p>免费资料请加VX: lckjxt（备注来自B站）</p>"
    },
    {
      "id": "7c8dc140cce4",
      "title": "【微观经济学】税收负担和税收转嫁",
      "summary": "【微观经济学】税收负担和税收转嫁",
      "source": "B站",
      "platform_class": "platform-bilibili",
      "author": "经管老邢",
      "url": "http://www.bilibili.com/video/av728404368",
      "time": "2026-04-16 23:15",
      "heat": 10017,
      "discussions": "226",
      "tags": [
        "税收"
      ],
      "isHot": false,
      "detail": "<p>【微观经济学】税收负担和税收转嫁</p>"
    },
    {
      "id": "109d5ee7ca6d",
      "title": "创业板改革的好消息",
      "summary": "一键三连！",
      "source": "B站",
      "platform_class": "platform-bilibili",
      "author": "李大霄",
      "url": "http://www.bilibili.com/video/av116379671859514",
      "time": "2026-04-16 23:15",
      "heat": 8887,
      "discussions": "687",
      "tags": [],
      "isHot": false,
      "detail": "<p>一键三连！</p>"
    },
    {
      "id": "8da0db090837",
      "title": "🔥网上办理税务登记全流程",
      "summary": "拿到营业执照后足不出户就可以网上办理税务登记啦！",
      "source": "B站",
      "platform_class": "platform-bilibili",
      "author": "跟着可可学实操",
      "url": "http://www.bilibili.com/video/av704446276",
      "time": "2026-04-16 23:15",
      "heat": 7513,
      "discussions": "253",
      "tags": [
        "税务",
        "税务登记"
      ],
      "isHot": false,
      "detail": "<p>拿到营业执照后足不出户就可以网上办理税务登记啦！</p>"
    },
    {
      "id": "69c219267549",
      "title": "【微观经济学】期末速成-征税和补贴的计算（1）",
      "summary": "-",
      "source": "B站",
      "platform_class": "platform-bilibili",
      "author": "小小蛮01",
      "url": "http://www.bilibili.com/video/av549616067",
      "time": "2026-04-16 23:15",
      "heat": 6320,
      "discussions": "82",
      "tags": [],
      "isHot": false,
      "detail": "<p>-</p>"
    },
    {
      "id": "7799cb4d8b92",
      "title": "【对啊网】创业老板创始人必看财税课｜股权设计+融资之道｜企业注册流程指导｜老板必懂基础财务知识+财务视角看业务流程｜纳税申报+税收筹划+避坑指南｜",
      "summary": "关注“对啊课堂” 微信公众号，下载配套讲义和习题，含考试重点、背诵口诀、学霸真题、考前密题。",
      "source": "B站",
      "platform_class": "platform-bilibili",
      "author": "对啊网",
      "url": "http://www.bilibili.com/video/av303994299",
      "time": "2026-04-16 23:15",
      "heat": 6195,
      "discussions": "41",
      "tags": [
        "税收",
        "纳税",
        "纳税申报"
      ],
      "isHot": false,
      "detail": "<p>关注“对啊课堂” 微信公众号，下载配套讲义和习题，含考试重点、背诵口诀、学霸真题、考前密题。</p>"
    },
    {
      "id": "6557c4e45257",
      "title": "税收政策、会计资料收集方法；会计工作网站整理！【梓晖】",
      "summary": "本期视频有两个内容：\n一是介绍我个人收集“税收政策”、“会计资料”的方法。\n二是整理一下会计工作重要网站。\n这两个内容也是我建立“会计工作资料库”的基础。",
      "source": "B站",
      "platform_class": "platform-bilibili",
      "author": "梓晖",
      "url": "http://www.bilibili.com/video/av248776671",
      "time": "2026-04-16 23:15",
      "heat": 5741,
      "discussions": "3",
      "tags": [
        "税收",
        "会计"
      ],
      "isHot": false,
      "detail": "<p>本期视频有两个内容：\n一是介绍我个人收集“税收政策”、“会计资料”的方法。\n二是整理一下会计工作重要网站。\n这两个内容也是我建立“会计工作资料库”的基础。</p>"
    },
    {
      "id": "21ed8abf6f91",
      "title": "网中网财务决策-成本管理岗位4类分配表+纳税申报",
      "summary": "网中网财务决策中“成本管理”岗位的全部操作讲解第一期\n本期主要包括：发票索取、成本分配表的填制、增值税及其他税的申报",
      "source": "B站",
      "platform_class": "platform-bilibili",
      "author": "笑嫣然一醉浮生",
      "url": "http://www.bilibili.com/video/av1351511765",
      "time": "2026-04-16 23:15",
      "heat": 5621,
      "discussions": "203",
      "tags": [
        "增值税",
        "纳税",
        "发票"
      ],
      "isHot": false,
      "detail": "<p>网中网财务决策中“成本管理”岗位的全部操作讲解第一期\n本期主要包括：发票索取、成本分配表的填制、增值税及其他税的申报</p>"
    },
    {
      "id": "2f003b5ccbef",
      "title": "中国财税史-中南财经政法大学",
      "summary": "https://www.icourse163.org/course/ZNUEDU-1207039804\n财政是国家治理的基础和重要支柱。从历史上看，在历次重大社会改革中财政改革都居于核心位置。本门课程从历史学视角，通过深入浅出的语言，在动态的历史长河中探寻国家兴衰更替背后的财政因素，总结中国财税制度向近代化、现代化转型的脉络、特点、规律和经验教训，传承与创新中国优秀财税制度与文化。",
      "source": "B站",
      "platform_class": "platform-bilibili",
      "author": "工地锁螺丝",
      "url": "http://www.bilibili.com/video/av92669549",
      "time": "2026-04-16 23:15",
      "heat": 5619,
      "discussions": "99",
      "tags": [
        "税制",
        "财政"
      ],
      "isHot": false,
      "detail": "<p>https://www.icourse163.org/course/ZNUEDU-1207039804\n财政是国家治理的基础和重要支柱。从历史上看，在历次重大社会改革中财政改革都居于核心位置。本门课程从历史学视角，通过深入浅出的语言，在动态的历史长河中探寻国家兴衰更替背后的财政因素，总结中国财税制度向近代化、现代化转型的脉络、特点、规律和经验教训，传承与创新中国优秀财税制度与文化。</p>"
    },
    {
      "id": "c4d3371b4d0e",
      "title": "个体工商户如何申报纳税",
      "summary": "查账征收的个体户主要就申报增值税和经营所得税，增值税有一个季度30万的免税额度，经营所得也有一年6万的免税额度，不要忘记享受？",
      "source": "B站",
      "platform_class": "platform-bilibili",
      "author": "会计收徒丶信德",
      "url": "http://www.bilibili.com/video/av115863722202805",
      "time": "2026-04-16 23:15",
      "heat": 4591,
      "discussions": "90",
      "tags": [
        "增值税",
        "纳税",
        "免税"
      ],
      "isHot": false,
      "detail": "<p>查账征收的个体户主要就申报增值税和经营所得税，增值税有一个季度30万的免税额度，经营所得也有一年6万的免税额度，不要忘记享受？</p>"
    },
    {
      "id": "f5a979db19c4",
      "title": "2025最新 税务筹划课程增值税个税企业所得税风险规避合理避税税务会计教程  吴娟老师",
      "summary": "2025最新 税务筹划课程增值税个税企业所得税风险规避合理避税税务会计教程  吴娟老师",
      "source": "B站",
      "platform_class": "platform-bilibili",
      "author": "笃言教育",
      "url": "http://www.bilibili.com/video/av346661443",
      "time": "2026-04-16 23:15",
      "heat": 2817,
      "discussions": "20",
      "tags": [
        "增值税",
        "企业所得税",
        "个税"
      ],
      "isHot": false,
      "detail": "<p>2025最新 税务筹划课程增值税个税企业所得税风险规避合理避税税务会计教程  吴娟老师</p>"
    },
    {
      "id": "65d8b91c5fd5",
      "title": "创业板改革，来了！五项改革，与你的钱袋子息息相关",
      "summary": "感谢各位老铁的点赞、投币和转发，如果觉得内容不错，欢迎充电支持。\n柏年的充电视频已经全面上线，包含【柏年财富说】和【深度观察】两个频道。\n其中【柏年财富说】会用更多的图表，更加专业的话语，以类路演的形式为大家带来当月的【宏观与政策分析】，以及当月的【大类资产研判与分析】；\n【深度观察】将聚焦当下的产业现状、社会问题以及地缘局势等热门话题的深度分析和解读。\n两个栏目加在一起，每个月至少会有3篇深度作",
      "source": "B站",
      "platform_class": "platform-bilibili",
      "author": "柏年说",
      "url": "http://www.bilibili.com/video/av116407471708674",
      "time": "2026-04-16 23:15",
      "heat": 2760,
      "discussions": "45",
      "tags": [],
      "isHot": false,
      "detail": "<p>感谢各位老铁的点赞、投币和转发，如果觉得内容不错，欢迎充电支持。\n柏年的充电视频已经全面上线，包含【柏年财富说】和【深度观察】两个频道。\n其中【柏年财富说】会用更多的图表，更加专业的话语，以类路演的形式为大家带来当月的【宏观与政策分析】，以及当月的【大类资产研判与分析】；\n【深度观察】将聚焦当下的产业现状、社会问题以及地缘局势等热门话题的深度分析和解读。\n两个栏目加在一起，每个月至少会有3篇深度作</p>"
    },
    {
      "id": "b68982754996",
      "title": "纳税申报实训任务一",
      "summary": "学校",
      "source": "B站",
      "platform_class": "platform-bilibili",
      "author": "梨绘橙沐",
      "url": "http://www.bilibili.com/video/av980323971",
      "time": "2026-04-16 23:15",
      "heat": 1643,
      "discussions": "24",
      "tags": [
        "纳税",
        "纳税申报"
      ],
      "isHot": false,
      "detail": "<p>学校</p>"
    },
    {
      "id": "d635a4dc05f3",
      "title": "企业所得税基础版本，从0到1教会你",
      "summary": "这是一个完全基础的税务师25教材版本，本科生请寻找主页企税速成期末专用",
      "source": "B站",
      "platform_class": "platform-bilibili",
      "author": "尹顺涛",
      "url": "http://www.bilibili.com/video/av114952417315727",
      "time": "2026-04-16 23:15",
      "heat": 1302,
      "discussions": "20",
      "tags": [
        "企业所得税",
        "税务",
        "税基"
      ],
      "isHot": false,
      "detail": "<p>这是一个完全基础的税务师25教材版本，本科生请寻找主页企税速成期末专用</p>"
    },
    {
      "id": "70fa724261c6",
      "title": "增值税优惠政策衔接事项深度解析（财税2026年 第10号公告解读）",
      "summary": "本视频内容深度解析财税2026年第10号公告相关内容\n主要包括\n1.政策背景与核心变化\n2.行业解读与实操案例\n3.风险防控与总结展望\n干货满满，诚意满满。\n财税问题千千万，关注侯哥找答案。\n如果觉得不错，记得一键三连噢。您的支持是我创作的动力！",
      "source": "B站",
      "platform_class": "platform-bilibili",
      "author": "侯哥讲财税",
      "url": "http://www.bilibili.com/video/av116136083457574",
      "time": "2026-04-16 23:15",
      "heat": 1118,
      "discussions": "26",
      "tags": [
        "增值税"
      ],
      "isHot": false,
      "detail": "<p>本视频内容深度解析财税2026年第10号公告相关内容\n主要包括\n1.政策背景与核心变化\n2.行业解读与实操案例\n3.风险防控与总结展望\n干货满满，诚意满满。\n财税问题千千万，关注侯哥找答案。\n如果觉得不错，记得一键三连噢。您的支持是我创作的动力！</p>"
    },
    {
      "id": "b77d982a9a02",
      "title": "企业重组特殊税务处理-上财田志伟-收购方计税方式的辨析-中国税制-税收专题",
      "summary": "企业重组中的税务处理，其中特殊税务处理有一些争议，我们以股权收购为例对这一问题进行详解",
      "source": "B站",
      "platform_class": "platform-bilibili",
      "author": "田志伟老师",
      "url": "http://www.bilibili.com/video/av1204336459",
      "time": "2026-04-16 23:15",
      "heat": 1025,
      "discussions": "38",
      "tags": [
        "税收",
        "税务",
        "税制"
      ],
      "isHot": false,
      "detail": "<p>企业重组中的税务处理，其中特殊税务处理有一些争议，我们以股权收购为例对这一问题进行详解</p>"
    },
    {
      "id": "d10c8f494677",
      "title": "（一）2-9税务会计填写纳税申报表",
      "summary": "（一）2-9税务会计填写纳税申报表",
      "source": "B站",
      "platform_class": "platform-bilibili",
      "author": "海边山茶花sx",
      "url": "http://www.bilibili.com/video/av1954482507",
      "time": "2026-04-16 23:15",
      "heat": 1020,
      "discussions": "3",
      "tags": [
        "税务",
        "纳税",
        "纳税申报"
      ],
      "isHot": false,
      "detail": "<p>（一）2-9税务会计填写纳税申报表</p>"
    },
    {
      "id": "88b860d9ed66",
      "title": "2026年最新：报税实务（企业必交的5税2费）--增值税、企业所得税预缴、个税预缴、附加税费、印花税",
      "summary": "这是试听课，想学习完整版V：fewone001",
      "source": "B站",
      "platform_class": "platform-bilibili",
      "author": "跟刘老师学会计实操",
      "url": "http://www.bilibili.com/video/av116281558698754",
      "time": "2026-04-16 23:15",
      "heat": 715,
      "discussions": "1",
      "tags": [
        "增值税",
        "企业所得税",
        "个税"
      ],
      "isHot": false,
      "detail": "<p>这是试听课，想学习完整版V：fewone001</p>"
    },
    {
      "id": "8a416256fdd1",
      "title": "2026年税务师涉税法律【磨耳朵记考点】",
      "summary": "打卡表：https://pan.baidu.com/share/init?surl=s3kumroHCD7IhZFgffjKpQ&amp;pwd=zhou\n\n此系列是周靖老师录制的仅是考点的辅记视频（不讲解原理，需要听原理和案例的听基础班哈），按照艾宾浩斯记忆曲线，安排大家回忆，达到用时短、记忆久的效果，助力高效通关！\n磨耳朵记考点，近十年来不仅是几十万考生认证的高效辅记资料，更是成为了很多老师效",
      "source": "B站",
      "platform_class": "platform-bilibili",
      "author": "周靖老师",
      "url": "http://www.bilibili.com/video/av116300718278009",
      "time": "2026-04-16 23:15",
      "heat": 712,
      "discussions": "10",
      "tags": [
        "税务",
        "税法",
        "税务师"
      ],
      "isHot": false,
      "detail": "<p>打卡表：https://pan.baidu.com/share/init?surl=s3kumroHCD7IhZFgffjKpQ&amp;pwd=zhou\n\n此系列是周靖老师录制的仅是考点的辅记视频（不讲解原理，需要听原理和案例的听基础班哈），按照艾宾浩斯记忆曲线，安排大家回忆，达到用时短、记忆久的效果，助力高效通关！\n磨耳朵记考点，近十年来不仅是几十万考生认证的高效辅记资料，更是成为了很多老师效</p>"
    },
    {
      "id": "0fd7543be19e",
      "title": "【税务师】坏消息！税务师政策变了，心疼26年姐妹",
      "summary": "姐妹们，我清明假期本来想躺平的，结果刷到税务师协会那边放了个新通知，瞬间坐不住了。熬夜把26年备考用得上的东西重新捋了一遍，今天这期视频全是硬干货，没有废话，想今年拿证的可以先码住。",
      "source": "B站",
      "platform_class": "platform-bilibili",
      "author": "香草喵ha",
      "url": "http://www.bilibili.com/video/av116328836895072",
      "time": "2026-04-16 23:15",
      "heat": 626,
      "discussions": "77",
      "tags": [
        "税务",
        "税务师"
      ],
      "isHot": false,
      "detail": "<p>姐妹们，我清明假期本来想躺平的，结果刷到税务师协会那边放了个新通知，瞬间坐不住了。熬夜把26年备考用得上的东西重新捋了一遍，今天这期视频全是硬干货，没有废话，想今年拿证的可以先码住。</p>"
    },
    {
      "id": "303cd4523a80",
      "title": "江苏省网上税务局增值税小规模纳税人申报",
      "summary": "讲解增值税小规模纳税人申报表填表及操作注意事项",
      "source": "B站",
      "platform_class": "platform-bilibili",
      "author": "tohotsoft",
      "url": "http://www.bilibili.com/video/av32629527",
      "time": "2026-04-16 23:15",
      "heat": 595,
      "discussions": "2",
      "tags": [
        "增值税",
        "税务",
        "纳税"
      ],
      "isHot": false,
      "detail": "<p>讲解增值税小规模纳税人申报表填表及操作注意事项</p>"
    },
    {
      "id": "4bf697baf8e0",
      "title": "财税【44讲新教材精讲完结】2026年高级经济师 视频和讲义完整 财政与税收",
      "summary": "1",
      "source": "B站",
      "platform_class": "platform-bilibili",
      "author": "学习号1号",
      "url": "http://www.bilibili.com/video/av115942054960755",
      "time": "2026-04-16 23:15",
      "heat": 549,
      "discussions": "5",
      "tags": [
        "税收",
        "财政"
      ],
      "isHot": false,
      "detail": "<p>1</p>"
    },
    {
      "id": "d5335623c5b9",
      "title": "餐饮酒店企业纳税申报实操课程",
      "summary": "需要会计资料【做账实操资料+历年考题+财务模板+视频课件等】加微信 17554070427\n\n本课程为生活服务性企业、一般纳税人纳税申报的实操系列课程，以2019年最新政策财税【2019】第87号文为导向，结合潮鲜餐饮酒店的财务数据，详细讲解了一般纳税人在进行月度增值税申报、附加税（附征税）申报、按季度预缴企业所得税申报时所涉及到的相关申报表的填列方",
      "source": "B站",
      "platform_class": "platform-bilibili",
      "author": "快学会计官方",
      "url": "http://www.bilibili.com/video/av969490107",
      "time": "2026-04-16 23:15",
      "heat": 423,
      "discussions": "0",
      "tags": [
        "增值税",
        "企业所得税",
        "纳税"
      ],
      "isHot": false,
      "detail": "<p>需要会计资料【做账实操资料+历年考题+财务模板+视频课件等】加微信 17554070427\n\n本课程为生活服务性企业、一般纳税人纳税申报的实操系列课程，以2019年最新政策财税【2019】第87号文为导向，结合潮鲜餐饮酒店的财务数据，详细讲解了一般纳税人在进行月度增值税申报、附加税（附征税）申报、按季度预缴企业所得税申报时所涉及到的相关申报表的填列方</p>"
    },
    {
      "id": "9e9090fb74dc",
      "title": "工业企业纳税申报",
      "summary": "工业企业纳税申报",
      "source": "B站",
      "platform_class": "platform-bilibili",
      "author": "会计大咖秀",
      "url": "http://www.bilibili.com/video/av370495726",
      "time": "2026-04-16 23:15",
      "heat": 416,
      "discussions": "7",
      "tags": [
        "纳税",
        "纳税申报"
      ],
      "isHot": false,
      "detail": "<p>工业企业纳税申报</p>"
    },
    {
      "id": "a562ca768bcf",
      "title": "2026年最新：建筑施工企业会计（一般纳税人）--政策解读、全盘账务处理，报税（6税2费）、发票开具",
      "summary": "这是试听课，想想学完整版V我：fewone001",
      "source": "B站",
      "platform_class": "platform-bilibili",
      "author": "跟刘老师学会计实操",
      "url": "http://www.bilibili.com/video/av116141217286356",
      "time": "2026-04-16 23:15",
      "heat": 402,
      "discussions": "5",
      "tags": [
        "纳税",
        "发票",
        "一般纳税人"
      ],
      "isHot": false,
      "detail": "<p>这是试听课，想想学完整版V我：fewone001</p>"
    },
    {
      "id": "a09bb827a07c",
      "title": "分税制之后，最重要的一次财税重构来了",
      "summary": "2026年3月23日 #中国财税 #土地财政 #税制改革\n\n房地产市场深度调整，土地出让收入腰斩，靠土地财政运转二十余年的地方政府，未来该靠什么赚钱？\n\n这是当下所有人都关心的灵魂拷问，而答案就藏在 “税收” 二字里。\n\n中国的税制并非一成不变，从建国后的统收统支，到改革开放的利改税，再到影响深远的 1994 分税制，以及如今的全面深化改革，四次终极进化背后，都是国家应对 “缺钱” 危机、适配经济",
      "source": "B站",
      "platform_class": "platform-bilibili",
      "author": "之乎者也说财经",
      "url": "http://www.bilibili.com/video/av116277247022125",
      "time": "2026-04-16 23:15",
      "heat": 400,
      "discussions": "8",
      "tags": [
        "税收",
        "减税",
        "税制"
      ],
      "isHot": false,
      "detail": "<p>2026年3月23日 #中国财税 #土地财政 #税制改革\n\n房地产市场深度调整，土地出让收入腰斩，靠土地财政运转二十余年的地方政府，未来该靠什么赚钱？\n\n这是当下所有人都关心的灵魂拷问，而答案就藏在 “税收” 二字里。\n\n中国的税制并非一成不变，从建国后的统收统支，到改革开放的利改税，再到影响深远的 1994 分税制，以及如今的全面深化改革，四次终极进化背后，都是国家应对 “缺钱” 危机、适配经济</p>"
    },
    {
      "id": "a520f5bbae58",
      "title": "增值税纳税申报1",
      "summary": "税务代理实务增值税纳税申报表的填写",
      "source": "B站",
      "platform_class": "platform-bilibili",
      "author": "蒋思密达讲会计",
      "url": "http://www.bilibili.com/video/av114627258091688",
      "time": "2026-04-16 23:15",
      "heat": 356,
      "discussions": "10",
      "tags": [
        "增值税",
        "税务",
        "纳税"
      ],
      "isHot": false,
      "detail": "<p>税务代理实务增值税纳税申报表的填写</p>"
    },
    {
      "id": "164b503b5b51",
      "title": "4-1企业所得税纳税人、征税对象、税率+片头片尾",
      "summary": "2026课程节选",
      "source": "B站",
      "platform_class": "platform-bilibili",
      "author": "吃手机不吐手机皮",
      "url": "http://www.bilibili.com/video/av116239028520783",
      "time": "2026-04-16 23:15",
      "heat": 304,
      "discussions": "1",
      "tags": [
        "企业所得税",
        "纳税",
        "税率"
      ],
      "isHot": false,
      "detail": "<p>2026课程节选</p>"
    },
    {
      "id": "7eaf8fbdcfc5",
      "title": "【说课程】朱红云：《智能化税费申报与管理》",
      "summary": "【说课程】朱红云：《智能化税费申报与管理》",
      "source": "B站",
      "platform_class": "platform-bilibili",
      "author": "大会人心",
      "url": "http://www.bilibili.com/video/av339224660",
      "time": "2026-04-16 23:15",
      "heat": 282,
      "discussions": "0",
      "tags": [],
      "isHot": false,
      "detail": "<p>【说课程】朱红云：《智能化税费申报与管理》</p>"
    },
    {
      "id": "b44ed32f4258",
      "title": "房产税与城镇土地使用税申报流程",
      "summary": "房产税与城镇土地使用税申报流程",
      "source": "B站",
      "platform_class": "platform-bilibili",
      "author": "会计收徒丶信德",
      "url": "http://www.bilibili.com/video/av114741578110238",
      "time": "2026-04-16 23:15",
      "heat": 198,
      "discussions": "0",
      "tags": [
        "房产税"
      ],
      "isHot": false,
      "detail": "<p>房产税与城镇土地使用税申报流程</p>"
    },
    {
      "id": "9fe61368b733",
      "title": "【免费分享】汇算清缴全套底稿、税审底稿、纳税申报表、纳税调整明细表",
      "summary": "全套内容，请见置顶评论",
      "source": "B站",
      "platform_class": "platform-bilibili",
      "author": "审计三三",
      "url": "http://www.bilibili.com/video/av116406716734924",
      "time": "2026-04-16 23:15",
      "heat": 156,
      "discussions": "3",
      "tags": [
        "纳税",
        "汇算清缴",
        "纳税申报"
      ],
      "isHot": false,
      "detail": "<p>全套内容，请见置顶评论</p>"
    },
    {
      "id": "43aea42ed1c5",
      "title": "新增值税法差额征税有了大变化！",
      "summary": "新增值税法差额征税有了大变化！",
      "source": "B站",
      "platform_class": "platform-bilibili",
      "author": "会计实操谦谦老师",
      "url": "http://www.bilibili.com/video/av116331923965449",
      "time": "2026-04-16 23:15",
      "heat": 108,
      "discussions": "1",
      "tags": [
        "增值税",
        "税法"
      ],
      "isHot": false,
      "detail": "<p>新增值税法差额征税有了大变化！</p>"
    },
    {
      "id": "b2f3a21de1bc",
      "title": "新一轮财税体制改革聚焦七大关键问题，从财政收入比重调整到地方税收体系完善，再到中央与地方财政关系优化，全面布局应对经济挑战，助力经济高质量发展。",
      "summary": "新一轮财税体制改革聚焦七大关键问题，从财政收入比重调整到地方税收体系完善，再到中央与地方财政关系优化，全面布局应对经济挑战，助力经济高质量发展。",
      "source": "B站",
      "platform_class": "platform-bilibili",
      "author": "禾略财讯",
      "url": "http://www.bilibili.com/video/av115087289354102",
      "time": "2026-04-16 23:15",
      "heat": 107,
      "discussions": "1",
      "tags": [
        "税收",
        "财政",
        "地方财政"
      ],
      "isHot": false,
      "detail": "<p>新一轮财税体制改革聚焦七大关键问题，从财政收入比重调整到地方税收体系完善，再到中央与地方财政关系优化，全面布局应对经济挑战，助力经济高质量发展。</p>"
    },
    {
      "id": "056e9c910182",
      "title": "卢麒元：税政改革--不流血的革命",
      "summary": "卢麒元：税政改革--不流血的革命",
      "source": "B站",
      "platform_class": "platform-bilibili",
      "author": "福睿达-Fred",
      "url": "http://www.bilibili.com/video/av116372592008188",
      "time": "2026-04-16 23:15",
      "heat": 75,
      "discussions": "2",
      "tags": [],
      "isHot": false,
      "detail": "<p>卢麒元：税政改革--不流血的革命</p>"
    },
    {
      "id": "c871eccb5dba",
      "title": "2026年最新：农业会计（种植业、养殖业）--政策解读、全盘账务处理、报税（5税2费）",
      "summary": "这是试听课，想学习完整版V我：fewone001",
      "source": "B站",
      "platform_class": "platform-bilibili",
      "author": "跟刘老师学会计实操",
      "url": "http://www.bilibili.com/video/av116248675354487",
      "time": "2026-04-16 23:15",
      "heat": 69,
      "discussions": "1",
      "tags": [
        "会计",
        "报税"
      ],
      "isHot": false,
      "detail": "<p>这是试听课，想学习完整版V我：fewone001</p>"
    },
    {
      "id": "cfc578006995",
      "title": "财税陈陈不吃香菜_2026-03-13_15-19-27",
      "summary": "douyin.com",
      "source": "B站",
      "platform_class": "platform-bilibili",
      "author": "g的加速",
      "url": "http://www.bilibili.com/video/av116234347610371",
      "time": "2026-04-16 23:15",
      "heat": 60,
      "discussions": "0",
      "tags": [],
      "isHot": false,
      "detail": "<p>douyin.com</p>"
    },
    {
      "id": "59ab895d00f5",
      "title": "医保重磅改革，抓住致富机会！",
      "summary": "-",
      "source": "B站",
      "platform_class": "platform-bilibili",
      "author": "北京羽挣",
      "url": "http://www.bilibili.com/video/av116412504937690",
      "time": "2026-04-16 23:15",
      "heat": 53,
      "discussions": "0",
      "tags": [],
      "isHot": false,
      "detail": "<p>-</p>"
    },
    {
      "id": "e781c36881a9",
      "title": "2026年建筑业税收政策重大变革--郑老师",
      "summary": "2026年建筑业税收政策重大变革--郑老师",
      "source": "B站",
      "platform_class": "platform-bilibili",
      "author": "建筑财税带教",
      "url": "http://www.bilibili.com/video/av116318502129854",
      "time": "2026-04-16 23:15",
      "heat": 46,
      "discussions": "1",
      "tags": [
        "税收"
      ],
      "isHot": false,
      "detail": "<p>2026年建筑业税收政策重大变革--郑老师</p>"
    },
    {
      "id": "53c44e5d3e39",
      "title": "新增值税法下的纳税申报实操",
      "summary": "新增值税法下的纳税申报实操",
      "source": "B站",
      "platform_class": "platform-bilibili",
      "author": "会计学习吧",
      "url": "http://www.bilibili.com/video/av116386164642060",
      "time": "2026-04-16 23:15",
      "heat": 35,
      "discussions": "0",
      "tags": [
        "增值税",
        "纳税",
        "税法"
      ],
      "isHot": false,
      "detail": "<p>新增值税法下的纳税申报实操</p>"
    },
    {
      "id": "e6fd251dd581",
      "title": "【听杭姐说财税】最新视频已上线，快来围观！",
      "summary": "-",
      "source": "B站",
      "platform_class": "platform-bilibili",
      "author": "听杭姐说财税",
      "url": "http://www.bilibili.com/video/av116407270577353",
      "time": "2026-04-16 23:15",
      "heat": 34,
      "discussions": "1",
      "tags": [],
      "isHot": false,
      "detail": "<p>-</p>"
    },
    {
      "id": "a08ef7bd7f51",
      "title": "救市策略之消费税改革",
      "summary": "救市策略之消费税改革",
      "source": "B站",
      "platform_class": "platform-bilibili",
      "author": "Dr_洋芋先生",
      "url": "http://www.bilibili.com/video/av116401834557575",
      "time": "2026-04-16 23:15",
      "heat": 30,
      "discussions": "0",
      "tags": [
        "消费税",
        "税改"
      ],
      "isHot": false,
      "detail": "<p>救市策略之消费税改革</p>"
    },
    {
      "id": "bca1204f9170",
      "title": "【100期打造顶级跨境财税认知】 彻底搞懂BEPS框架！全球税改双支柱+15%最低税率全解析",
      "summary": "🎯 欢迎来到【100期打造顶级跨境财税认知】系列第4期！\n📚 基于OECD最新文件，用一张图讲透：\n✅ 第一层：15项行动计划如何给旧规则&quot;打补丁&quot;？（A13&quot;三层文档&quot;如何给税务局开天眼）\n✅ 第二层：双支柱体系——支柱一（重新划分利润蛋糕/金额A/金额B）+ 支柱二（全球15%最低税率/IIR/UTPR规则）\n✅ 第三层：中国、美国、欧盟如何将国际共识变",
      "source": "B站",
      "platform_class": "platform-bilibili",
      "author": "跨境财税脱口秀",
      "url": "http://www.bilibili.com/video/av116198612143657",
      "time": "2026-04-16 23:15",
      "heat": 26,
      "discussions": "1",
      "tags": [
        "税收",
        "税务",
        "税率"
      ],
      "isHot": false,
      "detail": "<p>🎯 欢迎来到【100期打造顶级跨境财税认知】系列第4期！\n📚 基于OECD最新文件，用一张图讲透：\n✅ 第一层：15项行动计划如何给旧规则&quot;打补丁&quot;？（A13&quot;三层文档&quot;如何给税务局开天眼）\n✅ 第二层：双支柱体系——支柱一（重新划分利润蛋糕/金额A/金额B）+ 支柱二（全球15%最低税率/IIR/UTPR规则）\n✅ 第三层：中国、美国、欧盟如何将国际共识变</p>"
    },
    {
      "id": "e4eba884329b",
      "title": "合规不是负担，是企业的护身符！#财税#财税合规#财税咨询#企业经营#财务体系搭建",
      "summary": "-",
      "source": "B站",
      "platform_class": "platform-bilibili",
      "author": "苏州快智财税",
      "url": "http://www.bilibili.com/video/av116408511961254",
      "time": "2026-04-16 23:15",
      "heat": 26,
      "discussions": "0",
      "tags": [
        "财务"
      ],
      "isHot": false,
      "detail": "<p>-</p>"
    },
    {
      "id": "5a524caeae55",
      "title": "2026高级经济师高经财税：精讲班完整版有讲义",
      "summary": "请大家帮忙一键三连、谢谢大家！\n\n后续包含习题班。冲刺班、押题班等",
      "source": "B站",
      "platform_class": "platform-bilibili",
      "author": "学姐在线168",
      "url": "http://www.bilibili.com/video/av116407824089209",
      "time": "2026-04-16 23:15",
      "heat": 23,
      "discussions": "0",
      "tags": [],
      "isHot": false,
      "detail": "<p>请大家帮忙一键三连、谢谢大家！\n\n后续包含习题班。冲刺班、押题班等</p>"
    },
    {
      "id": "32a13b54d067",
      "title": "香港身份的优势2～优惠的税收政策。#香港#香港身份#香港税务#香港工作#香港永居#香港居民#薪俸税#利得税#个税#香港移民#投资移民#优才计划#高才计划#港险",
      "summary": "-",
      "source": "B站",
      "platform_class": "platform-bilibili",
      "author": "固远之",
      "url": "http://www.bilibili.com/video/av116407656389183",
      "time": "2026-04-16 23:15",
      "heat": 22,
      "discussions": "1",
      "tags": [
        "个税",
        "税收",
        "税务"
      ],
      "isHot": false,
      "detail": "<p>-</p>"
    },
    {
      "id": "fcc67e408ba5",
      "title": "国务院办公厅印发《关于深化投资审批制度改革的意见》",
      "summary": "国务院办公厅印发《关于深化投资审批制度改革的意见》全文",
      "source": "B站",
      "platform_class": "platform-bilibili",
      "author": "财经杂货铺",
      "url": "http://www.bilibili.com/video/av116408562227010",
      "time": "2026-04-16 23:15",
      "heat": 20,
      "discussions": "0",
      "tags": [],
      "isHot": false,
      "detail": "<p>国务院办公厅印发《关于深化投资审批制度改革的意见》全文</p>"
    },
    {
      "id": "5a725494d119",
      "title": "其实报税也不用别人教，直接照着这个网址多练几遍，经验一下子就来了#报税 #报税流程 #纳税申报 #会计实操 #财务",
      "summary": "其实报税也不用别人教，直接照着这个网址多练几遍，经验一下子就来了#报税 #报税流程 #纳税申报 #会计实操 #财务",
      "source": "B站",
      "platform_class": "platform-bilibili",
      "author": "木子会计吖",
      "url": "http://www.bilibili.com/video/av116408058905740",
      "time": "2026-04-16 23:15",
      "heat": 20,
      "discussions": "1",
      "tags": [
        "纳税",
        "纳税申报",
        "财务"
      ],
      "isHot": false,
      "detail": "<p>其实报税也不用别人教，直接照着这个网址多练几遍，经验一下子就来了#报税 #报税流程 #纳税申报 #会计实操 #财务</p>"
    },
    {
      "id": "8c66d9bb9647",
      "title": "消费税立法推进 万亿级税种迎来历史性变革 下一次大机会可能就在这里",
      "summary": "财政部2026年工作报告明确：推进消费税立法、制定地方附加税法。18个税种中已有14个完成立法，消费税是仅存的万亿级主体税种之一。改革方向：征税环节后移至零售、增量收入下划地方。回顾分税制改革史，每一次财税大变革都重塑了经济格局——这一次，你准备好了吗？",
      "source": "B站",
      "platform_class": "platform-bilibili",
      "author": "111epiphany",
      "url": "http://www.bilibili.com/video/av116409417924768",
      "time": "2026-04-16 23:15",
      "heat": 19,
      "discussions": "0",
      "tags": [
        "个税",
        "消费税",
        "税制"
      ],
      "isHot": false,
      "detail": "<p>财政部2026年工作报告明确：推进消费税立法、制定地方附加税法。18个税种中已有14个完成立法，消费税是仅存的万亿级主体税种之一。改革方向：征税环节后移至零售、增量收入下划地方。回顾分税制改革史，每一次财税大变革都重塑了经济格局——这一次，你准备好了吗？</p>"
    },
    {
      "id": "ebc39dc184f6",
      "title": "2026高级经济师财税-精讲视频孙孝群",
      "summary": "#2026高级经济师财税-精讲视频孙孝群#课程",
      "source": "B站",
      "platform_class": "platform-bilibili",
      "author": "考证小周学姐",
      "url": "http://www.bilibili.com/video/av116394838526943",
      "time": "2026-04-16 23:15",
      "heat": 8,
      "discussions": "0",
      "tags": [],
      "isHot": false,
      "detail": "<p>#2026高级经济师财税-精讲视频孙孝群#课程</p>"
    }
  ]
}