{
  "updated_at": "2026-04-19T14:16:41.397504+08:00",
  "count": 58,
  "topics": [
    {
      "id": "45b646b6794f",
      "title": "【实操系列】个税申报流程演示来了，从头到尾诚意满满",
      "summary": "【实操系列】个税申报流程演示来了，从头到尾诚意满满",
      "source": "B站",
      "platform_class": "platform-bilibili",
      "author": "2025税务师上岸",
      "url": "http://www.bilibili.com/video/av402204773",
      "time": "2026-04-19 14:16",
      "heat": 18778,
      "discussions": "296",
      "tags": [],
      "isHot": true,
      "detail": "<p>【实操系列】个税申报流程演示来了，从头到尾诚意满满</p>"
    },
    {
      "id": "b328a7a67cda",
      "title": "《国际税收》 朱青（税务433）",
      "summary": "2022年税务硕士考研群：830952137；\n2022年税务硕士考研群：830952137；\n2022年税务硕士考研群：830952137；\n2022年税务硕士考研群：830952137；\n2022年税务硕士考研群：830952137；",
      "source": "B站",
      "platform_class": "platform-bilibili",
      "author": "小熊老师带你飞",
      "url": "http://www.bilibili.com/video/av717134900",
      "time": "2026-04-19 14:16",
      "heat": 12236,
      "discussions": "565",
      "tags": [],
      "isHot": true,
      "detail": "<p>2022年税务硕士考研群：830952137；\n2022年税务硕士考研群：830952137；\n2022年税务硕士考研群：830952137；\n2022年税务硕士考研群：830952137；\n2022年税务硕士考研群：830952137；</p>"
    },
    {
      "id": "8da0db090837",
      "title": "🔥网上办理税务登记全流程",
      "summary": "拿到营业执照后足不出户就可以网上办理税务登记啦！",
      "source": "B站",
      "platform_class": "platform-bilibili",
      "author": "跟着可可学实操",
      "url": "http://www.bilibili.com/video/av704446276",
      "time": "2026-04-19 14:16",
      "heat": 7516,
      "discussions": "253",
      "tags": [],
      "isHot": true,
      "detail": "<p>拿到营业执照后足不出户就可以网上办理税务登记啦！</p>"
    },
    {
      "id": "85fb3d48699e",
      "title": "新版电子税务局，小规模零申报操作流程",
      "summary": "-",
      "source": "B站",
      "platform_class": "platform-bilibili",
      "author": "百合财税",
      "url": "http://www.bilibili.com/video/av1456007058",
      "time": "2026-04-19 14:16",
      "heat": 7440,
      "discussions": "218",
      "tags": [],
      "isHot": false,
      "detail": "<p>-</p>"
    },
    {
      "id": "8257b0b35fb4",
      "title": "2025年新版电子税务局税务注销全流程",
      "summary": "-",
      "source": "B站",
      "platform_class": "platform-bilibili",
      "author": "晗妈会计",
      "url": "http://www.bilibili.com/video/av114640730195595",
      "time": "2026-04-19 14:16",
      "heat": 3149,
      "discussions": "125",
      "tags": [],
      "isHot": false,
      "detail": "<p>-</p>"
    },
    {
      "id": "84ff5dc72d29",
      "title": "亚马逊报送信息之税务合规（大部份跨境老板和财务可以听下）",
      "summary": "亚马逊报送信息之税务合规（大部份跨境老板和财务可以听下）",
      "source": "B站",
      "platform_class": "platform-bilibili",
      "author": "先飞跨境财税",
      "url": "http://www.bilibili.com/video/av115407851622976",
      "time": "2026-04-19 14:16",
      "heat": 1098,
      "discussions": "9",
      "tags": [],
      "isHot": false,
      "detail": "<p>亚马逊报送信息之税务合规（大部份跨境老板和财务可以听下）</p>"
    },
    {
      "id": "399332c051f8",
      "title": "PropFirm 收入与税务申报",
      "summary": "下半年很多人都遇到的补税情况，了解清楚，不罚款。",
      "source": "B站",
      "platform_class": "platform-bilibili",
      "author": "昵称被注册的-小水果",
      "url": "http://www.bilibili.com/video/av115705143889829",
      "time": "2026-04-19 14:16",
      "heat": 1048,
      "discussions": "110",
      "tags": [],
      "isHot": false,
      "detail": "<p>下半年很多人都遇到的补税情况，了解清楚，不罚款。</p>"
    },
    {
      "id": "b948d5ffe64b",
      "title": "一般纳税人增值税申报讲解",
      "summary": "-",
      "source": "B站",
      "platform_class": "platform-bilibili",
      "author": "李岩讲财税",
      "url": "http://www.bilibili.com/video/av115852296852170",
      "time": "2026-04-19 14:16",
      "heat": 1036,
      "discussions": "12",
      "tags": [],
      "isHot": false,
      "detail": "<p>-</p>"
    },
    {
      "id": "bd166d757038",
      "title": "没有经营的企业申报没头绪？不!5分钟轻松get——个人所得税零申报",
      "summary": "欢迎收看本期视频！\n本期视频是个税0申报，其他省份同样适用。\nUP主在深圳如有需要办理工商税务方面的可以加VX:tf295902766，麻烦备注：B站+称呼\n如有什么建议或者意见，可以评论区评论或者私信。",
      "source": "B站",
      "platform_class": "platform-bilibili",
      "author": "零月ZeroMonth",
      "url": "http://www.bilibili.com/video/av866429415",
      "time": "2026-04-19 14:16",
      "heat": 955,
      "discussions": "37",
      "tags": [],
      "isHot": false,
      "detail": "<p>欢迎收看本期视频！\n本期视频是个税0申报，其他省份同样适用。\nUP主在深圳如有需要办理工商税务方面的可以加VX:tf295902766，麻烦备注：B站+称呼\n如有什么建议或者意见，可以评论区评论或者私信。</p>"
    },
    {
      "id": "b3330fdc3337",
      "title": "「影刀RPA」 财务机器人：税务局自动纳税申报",
      "summary": "如需在企业里使用该自动化应用，填写申请：https://ying-dao.feishu.cn/share/base/form/shrcnhAcnPkKTixfcWiVjqQ2uFh\n加入RPA学习群：https://mp.weixin.qq.com/s/5BLHkJq6Tk4Z-XxLtsjXOw",
      "source": "B站",
      "platform_class": "platform-bilibili",
      "author": "影刀RPA",
      "url": "http://www.bilibili.com/video/av647824949",
      "time": "2026-04-19 14:16",
      "heat": 932,
      "discussions": "14",
      "tags": [],
      "isHot": false,
      "detail": "<p>如需在企业里使用该自动化应用，填写申请：https://ying-dao.feishu.cn/share/base/form/shrcnhAcnPkKTixfcWiVjqQ2uFh\n加入RPA学习群：https://mp.weixin.qq.com/s/5BLHkJq6Tk4Z-XxLtsjXOw</p>"
    },
    {
      "id": "18a8a0b148d2",
      "title": "印花税申报操作流程",
      "summary": "印花税申报操作流程",
      "source": "B站",
      "platform_class": "platform-bilibili",
      "author": "会计收徒丶信德",
      "url": "http://www.bilibili.com/video/av115818205615535",
      "time": "2026-04-19 14:16",
      "heat": 850,
      "discussions": "14",
      "tags": [],
      "isHot": false,
      "detail": "<p>印花税申报操作流程</p>"
    },
    {
      "id": "6bf5e3ad1db2",
      "title": "进出口企业增值税如何申报？详细流程送上",
      "summary": "-",
      "source": "B站",
      "platform_class": "platform-bilibili",
      "author": "晗妈会计",
      "url": "http://www.bilibili.com/video/av872060120",
      "time": "2026-04-19 14:16",
      "heat": 759,
      "discussions": "10",
      "tags": [],
      "isHot": false,
      "detail": "<p>-</p>"
    },
    {
      "id": "ab455d7177f1",
      "title": "2025年七彩假期志愿服务团队经验分享（含申报书撰写，活动策划案，调研报告设计，接收地证明，1500字结项材料撰写）",
      "summary": "这个视频给大家介绍一下25年七彩假期志愿服务活动的相关经验分享",
      "source": "B站",
      "platform_class": "platform-bilibili",
      "author": "柒月竞赛三下乡",
      "url": "http://www.bilibili.com/video/av114421804372581",
      "time": "2026-04-19 14:16",
      "heat": 723,
      "discussions": "15",
      "tags": [],
      "isHot": false,
      "detail": "<p>这个视频给大家介绍一下25年七彩假期志愿服务活动的相关经验分享</p>"
    },
    {
      "id": "eb8411c3962b",
      "title": "境外投资个税指南：如何避免20%资本利得税 | CRS | 个人所得税 | QDII | 港股通 |030",
      "summary": "国内对境外资本利得的20%税收监管已进入全面执行阶段，CRS和金税四期让海外账户的个人所得税无处遁形。普通投资者应通过合规渠道（如港股通、QDII）和主动申报个税降低税务风险。在监管与技术双轮驱动下，合规是唯一出路，忽视规则将导致高昂代价。\n目前A股的买卖差价所得暂免征收个人所得税，但股息红利所得根据持股期限适用差异化税率“0%-20% (按持股期)”。为当前最具税收优势的投资渠道，但前提是您认为",
      "source": "B站",
      "platform_class": "platform-bilibili",
      "author": "呆萌财",
      "url": "http://www.bilibili.com/video/av115910933221499",
      "time": "2026-04-19 14:16",
      "heat": 684,
      "discussions": "23",
      "tags": [],
      "isHot": false,
      "detail": "<p>国内对境外资本利得的20%税收监管已进入全面执行阶段，CRS和金税四期让海外账户的个人所得税无处遁形。普通投资者应通过合规渠道（如港股通、QDII）和主动申报个税降低税务风险。在监管与技术双轮驱动下，合规是唯一出路，忽视规则将导致高昂代价。\n目前A股的买卖差价所得暂免征收个人所得税，但股息红利所得根据持股期限适用差异化税率“0%-20% (按持股期)”。为当前最具税收优势的投资渠道，但前提是您认为</p>"
    },
    {
      "id": "28cfee01309e",
      "title": "外币到账申报流程",
      "summary": "登陆外管平台\n首先需要联系银行开通，次日生效。银行相关人员会告\n诉你用户名和密码，还有网址。\n全称是：国家外汇管理局数字外管平台。\n登进进去，找到涉外收入-申报录入-选日期，找到进账的\n那笔钱-点开-输国别-交易编码******，金额，附言，是\n否保税根据实际选择，然后右上角保存。",
      "source": "B站",
      "platform_class": "platform-bilibili",
      "author": "归玖随汐",
      "url": "http://www.bilibili.com/video/av733009074",
      "time": "2026-04-19 14:16",
      "heat": 637,
      "discussions": "10",
      "tags": [],
      "isHot": false,
      "detail": "<p>登陆外管平台\n首先需要联系银行开通，次日生效。银行相关人员会告\n诉你用户名和密码，还有网址。\n全称是：国家外汇管理局数字外管平台。\n登进进去，找到涉外收入-申报录入-选日期，找到进账的\n那笔钱-点开-输国别-交易编码******，金额，附言，是\n否保税根据实际选择，然后右上角保存。</p>"
    },
    {
      "id": "b8ffbe294340",
      "title": "26年4月盈透又可以了，抓住机会吧",
      "summary": "26年4月盈透又可以了，抓住机会吧",
      "source": "B站",
      "platform_class": "platform-bilibili",
      "author": "钱同学的小课堂",
      "url": "http://www.bilibili.com/video/av116406314080207",
      "time": "2026-04-19 14:16",
      "heat": 613,
      "discussions": "28",
      "tags": [],
      "isHot": false,
      "detail": "<p>26年4月盈透又可以了，抓住机会吧</p>"
    },
    {
      "id": "6f5f26c7bd3e",
      "title": "账面收入和纳税申报表收入，为什么对不上？",
      "summary": "账面收入和纳税申报表收入，为什么对不上？\n6大原因：\n1.增值税纳税义务发生时点\n2.视同销售\n3.总额法和净额法（区别）、差额征税\n4.个税手续费返还、价外费用\n5.不征增值税项目、免征增值税项目\n6.时间性的差异：退货、销售折让",
      "source": "B站",
      "platform_class": "platform-bilibili",
      "author": "审计鱼帮主",
      "url": "http://www.bilibili.com/video/av115411492274706",
      "time": "2026-04-19 14:16",
      "heat": 562,
      "discussions": "23",
      "tags": [],
      "isHot": false,
      "detail": "<p>账面收入和纳税申报表收入，为什么对不上？\n6大原因：\n1.增值税纳税义务发生时点\n2.视同销售\n3.总额法和净额法（区别）、差额征税\n4.个税手续费返还、价外费用\n5.不征增值税项目、免征增值税项目\n6.时间性的差异：退货、销售折让</p>"
    },
    {
      "id": "a57107d3688b",
      "title": "印花税申报",
      "summary": "印花税申报",
      "source": "B站",
      "platform_class": "platform-bilibili",
      "author": "Yoki朝朝呐",
      "url": "http://www.bilibili.com/video/av112941986744440",
      "time": "2026-04-19 14:16",
      "heat": 519,
      "discussions": "0",
      "tags": [],
      "isHot": false,
      "detail": "<p>印花税申报</p>"
    },
    {
      "id": "6262d427a0f0",
      "title": "超详细攻略！四分钟精讲跨区域涉税事项报告操作指引#建筑行业#跨区域涉税事项#电子税务局#会计",
      "summary": "超详细攻略！四分钟精讲跨区域涉税事项报告操作指引#建筑行业#跨区域涉税事项#电子税务局#会计",
      "source": "B站",
      "platform_class": "platform-bilibili",
      "author": "企巴兔财税",
      "url": "http://www.bilibili.com/video/av113588496762554",
      "time": "2026-04-19 14:16",
      "heat": 463,
      "discussions": "9",
      "tags": [],
      "isHot": false,
      "detail": "<p>超详细攻略！四分钟精讲跨区域涉税事项报告操作指引#建筑行业#跨区域涉税事项#电子税务局#会计</p>"
    },
    {
      "id": "5e6e60953b00",
      "title": "取得境外所得如何通过个税APP申报个人所得税(浙江税务)",
      "summary": "宝子们！5月29日还没报境外所得个税的注意啦！今年起用个税APP就能搞定，超省心～\n\n哪些算境外所得？像海外工资、境外股息、转让境外房产等9类收入都要报，具体看财政部2020年3号公告！记得每年3月1日-6月30日申报，现在只剩最后几天，别漏了！\n\n操作超简单：打开个税APP，首页搜“年度汇算（取得境外所得适用）”，填境内外综合所得、经营所得，利息股息等分类所得单独填；境外已缴税别慌，系统自动算抵",
      "source": "B站",
      "platform_class": "platform-bilibili",
      "author": "税务师木木",
      "url": "http://www.bilibili.com/video/av114588066516202",
      "time": "2026-04-19 14:16",
      "heat": 431,
      "discussions": "3",
      "tags": [],
      "isHot": false,
      "detail": "<p>宝子们！5月29日还没报境外所得个税的注意啦！今年起用个税APP就能搞定，超省心～\n\n哪些算境外所得？像海外工资、境外股息、转让境外房产等9类收入都要报，具体看财政部2020年3号公告！记得每年3月1日-6月30日申报，现在只剩最后几天，别漏了！\n\n操作超简单：打开个税APP，首页搜“年度汇算（取得境外所得适用）”，填境内外综合所得、经营所得，利息股息等分类所得单独填；境外已缴税别慌，系统自动算抵</p>"
    },
    {
      "id": "10af62c770d6",
      "title": "环境保护税基础信息采集和申报操作演示（重庆税务）",
      "summary": "环境保护税基础信息采集和申报操作演示（重庆税务）",
      "source": "B站",
      "platform_class": "platform-bilibili",
      "author": "采集软件分享",
      "url": "http://www.bilibili.com/video/av406039877",
      "time": "2026-04-19 14:16",
      "heat": 429,
      "discussions": "0",
      "tags": [],
      "isHot": false,
      "detail": "<p>环境保护税基础信息采集和申报操作演示（重庆税务）</p>"
    },
    {
      "id": "0821633d5907",
      "title": "拼多多电商涉税信息报送收入确认路径",
      "summary": "-",
      "source": "B站",
      "platform_class": "platform-bilibili",
      "author": "桂纶镁的晴天",
      "url": "http://www.bilibili.com/video/av115388239059550",
      "time": "2026-04-19 14:16",
      "heat": 364,
      "discussions": "1",
      "tags": [],
      "isHot": false,
      "detail": "<p>-</p>"
    },
    {
      "id": "aa8ff6c3d6c6",
      "title": "受益所有人信息如何申报",
      "summary": "-",
      "source": "B站",
      "platform_class": "platform-bilibili",
      "author": "凡小赛说财税",
      "url": "http://www.bilibili.com/video/av115008302220367",
      "time": "2026-04-19 14:16",
      "heat": 340,
      "discussions": "6",
      "tags": [],
      "isHot": false,
      "detail": "<p>-</p>"
    },
    {
      "id": "626cd9ccfd29",
      "title": "2025年白癜风慢病医保申请指南：这些地区可申报，这样报销更省钱！",
      "summary": "符合条件的人每年可以享受上千元的专项报销。",
      "source": "B站",
      "platform_class": "platform-bilibili",
      "author": "杰升的白白抗复发日记",
      "url": "http://www.bilibili.com/video/av114799006452466",
      "time": "2026-04-19 14:16",
      "heat": 289,
      "discussions": "19",
      "tags": [],
      "isHot": false,
      "detail": "<p>符合条件的人每年可以享受上千元的专项报销。</p>"
    },
    {
      "id": "13c8d12ddd95",
      "title": "第十章（四）：来料加工贸易业务流程与税务申报",
      "summary": "第十章（四）：来料加工贸易业务流程与税务申报",
      "source": "B站",
      "platform_class": "platform-bilibili",
      "author": "雨暹",
      "url": "http://www.bilibili.com/video/av446014909",
      "time": "2026-04-19 14:16",
      "heat": 265,
      "discussions": "1",
      "tags": [],
      "isHot": false,
      "detail": "<p>第十章（四）：来料加工贸易业务流程与税务申报</p>"
    },
    {
      "id": "0da40072e9ed",
      "title": "企业所得税如何申报，一个视频教会你",
      "summary": "-",
      "source": "B站",
      "platform_class": "platform-bilibili",
      "author": "薄荷说财会",
      "url": "http://www.bilibili.com/video/av116384755352202",
      "time": "2026-04-19 14:16",
      "heat": 246,
      "discussions": "0",
      "tags": [],
      "isHot": false,
      "detail": "<p>-</p>"
    },
    {
      "id": "2babf1f810ef",
      "title": "Ozon小卖家如何进行纳税申报？",
      "summary": "Ozon小卖家如何进行纳税申报？",
      "source": "B站",
      "platform_class": "platform-bilibili",
      "author": "Ozon官方课程",
      "url": "http://www.bilibili.com/video/av115343259405450",
      "time": "2026-04-19 14:16",
      "heat": 246,
      "discussions": "4",
      "tags": [],
      "isHot": false,
      "detail": "<p>Ozon小卖家如何进行纳税申报？</p>"
    },
    {
      "id": "9b3b3b0c0e78",
      "title": "CRS: 2026 境外投資稅務申報教學：AI 自動計算美股/港股投資所得，個人所得稅 APP 報稅全攻略",
      "summary": "💡 境外投資報稅太複雜？請會計太貴？本視頻手把手教你使用最新的 AI 稅務工具，自動化處理你的券商月報表、年報表，一鍵生成符合審計要求的 Excel 底稿，讓你在個人所得稅 APP 申報時輕鬆無憂！\n\n📌 視頻核心內容：\n00:00 工具背景與核心價值（省時、省錢、防風險）\n01:08 免費體驗額度獲取與定價方案\n02:00 邀請碼機制：雙方均可獲得 50% 額外額度\n02:40 數據安全保障：本",
      "source": "B站",
      "platform_class": "platform-bilibili",
      "author": "财富种植园",
      "url": "http://www.bilibili.com/video/av116132493133650",
      "time": "2026-04-19 14:16",
      "heat": 221,
      "discussions": "14",
      "tags": [],
      "isHot": false,
      "detail": "<p>💡 境外投資報稅太複雜？請會計太貴？本視頻手把手教你使用最新的 AI 稅務工具，自動化處理你的券商月報表、年報表，一鍵生成符合審計要求的 Excel 底稿，讓你在個人所得稅 APP 申報時輕鬆無憂！\n\n📌 視頻核心內容：\n00:00 工具背景與核心價值（省時、省錢、防風險）\n01:08 免費體驗額度獲取與定價方案\n02:00 邀請碼機制：雙方均可獲得 50% 額外額度\n02:40 數據安全保障：本</p>"
    },
    {
      "id": "106948cae932",
      "title": "增值税申报不开票收入如何申报？",
      "summary": "-",
      "source": "B站",
      "platform_class": "platform-bilibili",
      "author": "晗妈会计",
      "url": "http://www.bilibili.com/video/av411371983",
      "time": "2026-04-19 14:16",
      "heat": 220,
      "discussions": "2",
      "tags": [],
      "isHot": false,
      "detail": "<p>-</p>"
    },
    {
      "id": "69e9fed73f1d",
      "title": "抖店涉税申报数据如何核对",
      "summary": "抖店涉税申报数据如何核对",
      "source": "B站",
      "platform_class": "platform-bilibili",
      "author": "电商财务许哈哈",
      "url": "http://www.bilibili.com/video/av115406006132638",
      "time": "2026-04-19 14:16",
      "heat": 214,
      "discussions": "6",
      "tags": [],
      "isHot": false,
      "detail": "<p>抖店涉税申报数据如何核对</p>"
    },
    {
      "id": "d890266d468f",
      "title": "拼多多涉税",
      "summary": "拼多多涉税",
      "source": "B站",
      "platform_class": "platform-bilibili",
      "author": "财会小筑",
      "url": "http://www.bilibili.com/video/av115485295251066",
      "time": "2026-04-19 14:16",
      "heat": 212,
      "discussions": "2",
      "tags": [],
      "isHot": false,
      "detail": "<p>拼多多涉税</p>"
    },
    {
      "id": "6f52948d7a53",
      "title": "【完全搞懂VAT！】欧洲跨境必修课：注册+申报+缴税，一次讲透！连平台代缴功能都教你怎么用！新卖家也能看懂",
      "summary": "这期视频我会用3分钟的结构，带你快速搞懂VAT注册 + 申报 + 缴税的核心流程，\n还会告诉你哪些平台支持免费代缴，怎么操作最省心，一看就懂，少走很多弯路。\n\n✅ 视频对应图文文章：\nhttps://mp.weixin.qq.com/s/Pl0U1pQcJoc5Fs8C4sQZ2Q",
      "source": "B站",
      "platform_class": "platform-bilibili",
      "author": "136F跨境小贴士",
      "url": "http://www.bilibili.com/video/av115434762469798",
      "time": "2026-04-19 14:16",
      "heat": 208,
      "discussions": "5",
      "tags": [],
      "isHot": false,
      "detail": "<p>这期视频我会用3分钟的结构，带你快速搞懂VAT注册 + 申报 + 缴税的核心流程，\n还会告诉你哪些平台支持免费代缴，怎么操作最省心，一看就懂，少走很多弯路。\n\n✅ 视频对应图文文章：\nhttps://mp.weixin.qq.com/s/Pl0U1pQcJoc5Fs8C4sQZ2Q</p>"
    },
    {
      "id": "d30a9577d056",
      "title": "印花税申报--政策解读、申报、热点问题解析",
      "summary": "这是试听课，想学习完整版V我：fewone001",
      "source": "B站",
      "platform_class": "platform-bilibili",
      "author": "跟刘老师学会计实操",
      "url": "http://www.bilibili.com/video/av115381612055082",
      "time": "2026-04-19 14:16",
      "heat": 199,
      "discussions": "1",
      "tags": [],
      "isHot": false,
      "detail": "<p>这是试听课，想学习完整版V我：fewone001</p>"
    },
    {
      "id": "0b9fd2595c3a",
      "title": "【免费分享】企业划分标准，避免纳税申报出错！企业会计准则适用标准",
      "summary": "全套内容，请见置顶评论",
      "source": "B站",
      "platform_class": "platform-bilibili",
      "author": "审计三三",
      "url": "http://www.bilibili.com/video/av114623114125195",
      "time": "2026-04-19 14:16",
      "heat": 198,
      "discussions": "2",
      "tags": [],
      "isHot": false,
      "detail": "<p>全套内容，请见置顶评论</p>"
    },
    {
      "id": "f1e02ee24c01",
      "title": "1688如何申报税务，简单易懂的避坑指南，学不会你过来打我？",
      "summary": "电商税",
      "source": "B站",
      "platform_class": "platform-bilibili",
      "author": "超乎你想象AD",
      "url": "http://www.bilibili.com/video/av115375421259923",
      "time": "2026-04-19 14:16",
      "heat": 191,
      "discussions": "3",
      "tags": [],
      "isHot": false,
      "detail": "<p>电商税</p>"
    },
    {
      "id": "c0123dc6b505",
      "title": "分公司都需要申报哪些税零申报全流程",
      "summary": "-",
      "source": "B站",
      "platform_class": "platform-bilibili",
      "author": "晗妈会计",
      "url": "http://www.bilibili.com/video/av114822914050754",
      "time": "2026-04-19 14:16",
      "heat": 173,
      "discussions": "1",
      "tags": [],
      "isHot": false,
      "detail": "<p>-</p>"
    },
    {
      "id": "f0ec99c0445a",
      "title": "亚马逊税务申报应该申报哪个数据",
      "summary": "亚马逊税务申报应该申报哪个数据",
      "source": "B站",
      "platform_class": "platform-bilibili",
      "author": "泼辣有课",
      "url": "http://www.bilibili.com/video/av115457914904469",
      "time": "2026-04-19 14:16",
      "heat": 111,
      "discussions": "1",
      "tags": [],
      "isHot": false,
      "detail": "<p>亚马逊税务申报应该申报哪个数据</p>"
    },
    {
      "id": "cfee548b0705",
      "title": "CRS：知识篇-非CRS国家大公开",
      "summary": "传说中的富豪克星 CRS 到底是什么？\n它到底怎么执行的让全世界的富豪唯恐不及？\nCRS对海外房地产的影响真的很大吗?\n有哪些国家加入这个制度来避免洗钱问题？\n又有哪些国家在没有CRS的前提下被称为避税天堂呢？\n快看影片来了解吧！\n-\n影片内容：\n0:06 CRS是什么？\n0:23 包含了哪些又不包含哪些？\n1:08 非CRS国家举例\n1:29 非CRS国选哪个好？\n-\n看完之后是否有更了解CRS",
      "source": "B站",
      "platform_class": "platform-bilibili",
      "author": "環球管家",
      "url": "http://www.bilibili.com/video/av82565539",
      "time": "2026-04-19 14:16",
      "heat": 108,
      "discussions": "1",
      "tags": [],
      "isHot": false,
      "detail": "<p>传说中的富豪克星 CRS 到底是什么？\n它到底怎么执行的让全世界的富豪唯恐不及？\nCRS对海外房地产的影响真的很大吗?\n有哪些国家加入这个制度来避免洗钱问题？\n又有哪些国家在没有CRS的前提下被称为避税天堂呢？\n快看影片来了解吧！\n-\n影片内容：\n0:06 CRS是什么？\n0:23 包含了哪些又不包含哪些？\n1:08 非CRS国家举例\n1:29 非CRS国选哪个好？\n-\n看完之后是否有更了解CRS</p>"
    },
    {
      "id": "27c303854ebd",
      "title": "双定个体户如何填写申报表？",
      "summary": "-",
      "source": "B站",
      "platform_class": "platform-bilibili",
      "author": "馒头娘说税",
      "url": "http://www.bilibili.com/video/av113077311766928",
      "time": "2026-04-19 14:16",
      "heat": 106,
      "discussions": "0",
      "tags": [],
      "isHot": false,
      "detail": "<p>-</p>"
    },
    {
      "id": "63f00a111cfb",
      "title": "4月大征期企业所得税和财务报表季度申报操作流程",
      "summary": "-",
      "source": "B站",
      "platform_class": "platform-bilibili",
      "author": "李岩讲财税",
      "url": "http://www.bilibili.com/video/av116391600462409",
      "time": "2026-04-19 14:16",
      "heat": 102,
      "discussions": "0",
      "tags": [],
      "isHot": false,
      "detail": "<p>-</p>"
    },
    {
      "id": "7c9746ad4080",
      "title": "31、干货分享之申报企业税务申报",
      "summary": "31、干货分享之申报企业税务申报",
      "source": "B站",
      "platform_class": "platform-bilibili",
      "author": "努力成为蛋总s",
      "url": "http://www.bilibili.com/video/av115625368296329",
      "time": "2026-04-19 14:16",
      "heat": 102,
      "discussions": "4",
      "tags": [],
      "isHot": false,
      "detail": "<p>31、干货分享之申报企业税务申报</p>"
    },
    {
      "id": "036a3f9b5436",
      "title": "为什么税务说电商企业申报的收入少于互联网平台报送的数字？到底应该填哪个数字？",
      "summary": "-",
      "source": "B站",
      "platform_class": "platform-bilibili",
      "author": "财务沫茉",
      "url": "http://www.bilibili.com/video/av115531063494980",
      "time": "2026-04-19 14:16",
      "heat": 99,
      "discussions": "2",
      "tags": [],
      "isHot": false,
      "detail": "<p>-</p>"
    },
    {
      "id": "41e9712adacf",
      "title": "2025年境外收入在国内缴税的方法",
      "summary": "2025年境外收入在国内缴税的方法",
      "source": "B站",
      "platform_class": "platform-bilibili",
      "author": "淡定的飞马",
      "url": "http://www.bilibili.com/video/av116228072934922",
      "time": "2026-04-19 14:16",
      "heat": 94,
      "discussions": "8",
      "tags": [],
      "isHot": false,
      "detail": "<p>2025年境外收入在国内缴税的方法</p>"
    },
    {
      "id": "e8a4fca47788",
      "title": "电商财务税务申报流程拼多多平台",
      "summary": "-",
      "source": "B站",
      "platform_class": "platform-bilibili",
      "author": "桂纶镁的晴天",
      "url": "http://www.bilibili.com/video/av115525090942757",
      "time": "2026-04-19 14:16",
      "heat": 91,
      "discussions": "0",
      "tags": [],
      "isHot": false,
      "detail": "<p>-</p>"
    },
    {
      "id": "f4a0f55cd773",
      "title": "速卖通按什么收入申报",
      "summary": "-",
      "source": "B站",
      "platform_class": "platform-bilibili",
      "author": "先飞跨境财税",
      "url": "http://www.bilibili.com/video/av115201374557989",
      "time": "2026-04-19 14:16",
      "heat": 72,
      "discussions": "1",
      "tags": [],
      "isHot": false,
      "detail": "<p>-</p>"
    },
    {
      "id": "6ad993af4b09",
      "title": "拼多多涉税信息报送核对",
      "summary": "拼多多平台暂无涉税信息报送模块，大部分电商平台是以结算维度报送，可根据拼多多店铺账单作为申报依据；\n路径一(月汇总):登录拼多多商家后台一左侧菜单找到“账户资金”一点击“对账中心”一选择“货款账户”中的“月汇总”，就能看到当月的收入和支出明细。\n路径二(明细导出):在“对账中心”的“货款账户”页面，选择“货款明细”，筛选好日期后导出Excel文件。这份明细非常关键，上面的“业务描述”会清晰地告诉你",
      "source": "B站",
      "platform_class": "platform-bilibili",
      "author": "电商财务许哈哈",
      "url": "http://www.bilibili.com/video/av116374689094550",
      "time": "2026-04-19 14:16",
      "heat": 68,
      "discussions": "2",
      "tags": [],
      "isHot": false,
      "detail": "<p>拼多多平台暂无涉税信息报送模块，大部分电商平台是以结算维度报送，可根据拼多多店铺账单作为申报依据；\n路径一(月汇总):登录拼多多商家后台一左侧菜单找到“账户资金”一点击“对账中心”一选择“货款账户”中的“月汇总”，就能看到当月的收入和支出明细。\n路径二(明细导出):在“对账中心”的“货款账户”页面，选择“货款明细”，筛选好日期后导出Excel文件。这份明细非常关键，上面的“业务描述”会清晰地告诉你</p>"
    },
    {
      "id": "6d54ef1ba70f",
      "title": "电商财务拼多多涉税申报口径汇总表",
      "summary": "-",
      "source": "B站",
      "platform_class": "platform-bilibili",
      "author": "桂纶镁的晴天",
      "url": "http://www.bilibili.com/video/av116372642339829",
      "time": "2026-04-19 14:16",
      "heat": 54,
      "discussions": "2",
      "tags": [],
      "isHot": false,
      "detail": "<p>-</p>"
    },
    {
      "id": "73442e4405bc",
      "title": "如何界定“中国税务居民”身份，讲透讲清楚",
      "summary": "我们正处在一个新的时代：\n 全球税务透明、全球大数据协同的时代。\n过去是：\n “我不说，你不知道。”\n 现在是：\n “你以为国家不知道？国家都在等你主动申报。”\n所以，记住三件事：\n① 先判断你是不是中国税务居民\n ② 海外收入必须申报\n ③ 税务规划要提前，而不是被动补税\n全球征税时代已经到来，\n 你属于哪个国家的税务居民，比你赚多少钱，更重要。",
      "source": "B站",
      "platform_class": "platform-bilibili",
      "author": "无忧启程移民",
      "url": "http://www.bilibili.com/video/av115512944105575",
      "time": "2026-04-19 14:16",
      "heat": 43,
      "discussions": "1",
      "tags": [],
      "isHot": false,
      "detail": "<p>我们正处在一个新的时代：\n 全球税务透明、全球大数据协同的时代。\n过去是：\n “我不说，你不知道。”\n 现在是：\n “你以为国家不知道？国家都在等你主动申报。”\n所以，记住三件事：\n① 先判断你是不是中国税务居民\n ② 海外收入必须申报\n ③ 税务规划要提前，而不是被动补税\n全球征税时代已经到来，\n 你属于哪个国家的税务居民，比你赚多少钱，更重要。</p>"
    },
    {
      "id": "df4461e6479e",
      "title": "慕有枝：电商涉税报送新规之应对线上视频课解读（上）慕有枝61慕有枝课程慕有枝电商慕有枝课程合集慕有枝新公司法慕有枝股瞰平台即将报送涉税信息",
      "summary": "慕有枝：电商涉税报送新规之应对线上视频课解读（上）慕有枝61慕有枝课程慕有枝电商慕有枝课程合集慕有枝新公司法慕有枝股瞰平台即将报送涉税信息慕有枝：电商涉税报送新规之应对线上视频课解读（上）慕有枝61慕有枝课程慕有枝电商慕有枝课程合集慕有枝新公司法慕有枝股瞰平台即将报送涉税信息慕有枝：电商涉税报送新规之应对线上视频课解读（上）慕有枝61慕有枝课程慕有枝电商慕有枝课程合集慕有枝新公司法慕有枝股瞰平台即",
      "source": "B站",
      "platform_class": "platform-bilibili",
      "author": "窦昕初中语文老师",
      "url": "http://www.bilibili.com/video/av116424701902969",
      "time": "2026-04-19 14:16",
      "heat": 37,
      "discussions": "0",
      "tags": [],
      "isHot": false,
      "detail": "<p>慕有枝：电商涉税报送新规之应对线上视频课解读（上）慕有枝61慕有枝课程慕有枝电商慕有枝课程合集慕有枝新公司法慕有枝股瞰平台即将报送涉税信息慕有枝：电商涉税报送新规之应对线上视频课解读（上）慕有枝61慕有枝课程慕有枝电商慕有枝课程合集慕有枝新公司法慕有枝股瞰平台即将报送涉税信息慕有枝：电商涉税报送新规之应对线上视频课解读（上）慕有枝61慕有枝课程慕有枝电商慕有枝课程合集慕有枝新公司法慕有枝股瞰平台即</p>"
    },
    {
      "id": "985bdb785522",
      "title": "第一季度抖店税务结算口径申报收入",
      "summary": "-",
      "source": "B站",
      "platform_class": "platform-bilibili",
      "author": "桂纶镁的晴天",
      "url": "http://www.bilibili.com/video/av116425674987284",
      "time": "2026-04-19 14:16",
      "heat": 34,
      "discussions": "0",
      "tags": [],
      "isHot": false,
      "detail": "<p>-</p>"
    },
    {
      "id": "1ea2d9511e35",
      "title": "直接申报后台数据的都是“大傻子”！那属于含税价，而申报要的是不含税价，会交税了！",
      "summary": "#数据报送#电商财税#财税合规#电商交税#税务合规",
      "source": "B站",
      "platform_class": "platform-bilibili",
      "author": "春戈讲电商财税",
      "url": "http://www.bilibili.com/video/av116407253604327",
      "time": "2026-04-19 14:16",
      "heat": 33,
      "discussions": "0",
      "tags": [],
      "isHot": false,
      "detail": "<p>#数据报送#电商财税#财税合规#电商交税#税务合规</p>"
    },
    {
      "id": "87b59daa91ea",
      "title": "中国邮政2026校招公告解读✅网申报名→",
      "summary": "关于中国邮政2026校招，这个视频讲透！备考题库已同步更新，建议使用【职题库】系统化准备！\n✅招聘公告解读\n✅网申报名流程\n别再盲目投递！看完少走弯路👉希望对你有帮助~愿大家都顺利上岸哦！@职题库",
      "source": "B站",
      "platform_class": "platform-bilibili",
      "author": "职题库",
      "url": "http://www.bilibili.com/video/av116323065528842",
      "time": "2026-04-19 14:16",
      "heat": 14,
      "discussions": "0",
      "tags": [],
      "isHot": false,
      "detail": "<p>关于中国邮政2026校招，这个视频讲透！备考题库已同步更新，建议使用【职题库】系统化准备！\n✅招聘公告解读\n✅网申报名流程\n别再盲目投递！看完少走弯路👉希望对你有帮助~愿大家都顺利上岸哦！@职题库</p>"
    },
    {
      "id": "3ec7d6992a23",
      "title": "聊聊跨境卖家最近关注的补税以及未来合规思路",
      "summary": "今天视频和大家聊聊补税思路和未来如何布局合规。未来合规是大势所趋，大家要尽早做起来~",
      "source": "B站",
      "platform_class": "platform-bilibili",
      "author": "专诚财税",
      "url": "http://www.bilibili.com/video/av116417739358364",
      "time": "2026-04-19 14:16",
      "heat": 12,
      "discussions": "0",
      "tags": [],
      "isHot": false,
      "detail": "<p>今天视频和大家聊聊补税思路和未来如何布局合规。未来合规是大势所趋，大家要尽早做起来~</p>"
    },
    {
      "id": "c0be014f704a",
      "title": "华腾工业2026届春招公告解读 | 网申报名",
      "summary": "关于华腾工业2026届春招，这个视频帮你搞懂！已同步更新华腾工业备考题库，建议结合【职题库】系统化准备！\n✅招聘公告整理解读\n✅网申报名重点分析\n看完少走弯路，愿大家都能顺利上岸！@职题库",
      "source": "B站",
      "platform_class": "platform-bilibili",
      "author": "职题库",
      "url": "http://www.bilibili.com/video/av116418091682442",
      "time": "2026-04-19 14:16",
      "heat": 5,
      "discussions": "0",
      "tags": [],
      "isHot": false,
      "detail": "<p>关于华腾工业2026届春招，这个视频帮你搞懂！已同步更新华腾工业备考题库，建议结合【职题库】系统化准备！\n✅招聘公告整理解读\n✅网申报名重点分析\n看完少走弯路，愿大家都能顺利上岸！@职题库</p>"
    },
    {
      "id": "7ae64741fa14",
      "title": "【税务技能赛训平台】7.税务-消费税申报案例",
      "summary": "【税务技能赛训平台】7.税务-消费税申报案例",
      "source": "B站",
      "platform_class": "platform-bilibili",
      "author": "郑城_",
      "url": "http://www.bilibili.com/video/av116418896993023",
      "time": "2026-04-19 14:16",
      "heat": 3,
      "discussions": "0",
      "tags": [],
      "isHot": false,
      "detail": "<p>【税务技能赛训平台】7.税务-消费税申报案例</p>"
    },
    {
      "id": "65885e8f7848",
      "title": "26年最新政策 抖音电商老板报税交税全流程",
      "summary": "原创内容来源@晓涛聊电商财税  \n26年最新政策 抖音电商老板报税交税全流程",
      "source": "B站",
      "platform_class": "platform-bilibili",
      "author": "财税晓涛老师",
      "url": "http://www.bilibili.com/video/av116361636354723",
      "time": "2026-04-19 14:16",
      "heat": 2,
      "discussions": "0",
      "tags": [],
      "isHot": false,
      "detail": "<p>原创内容来源@晓涛聊电商财税  \n26年最新政策 抖音电商老板报税交税全流程</p>"
    },
    {
      "id": "ae442abffed0",
      "title": "紧急提醒！3月1号起2025年境外收入申报开始，6月30号截止，超过就收滞纳金！#境外收入申报 #税务申报 #CRS #税务合规",
      "summary": "-",
      "source": "B站",
      "platform_class": "platform-bilibili",
      "author": "小卡的港知识",
      "url": "http://www.bilibili.com/video/av116129238353596",
      "time": "2026-04-19 14:16",
      "heat": 2,
      "discussions": "0",
      "tags": [],
      "isHot": false,
      "detail": "<p>-</p>"
    },
    {
      "id": "d76bce2262c6",
      "title": "税务申报太麻烦？FMS系统自动计税避坑！",
      "summary": "税务申报太麻烦？FMS系统自动计税避坑！",
      "source": "B站",
      "platform_class": "platform-bilibili",
      "author": "大数据民工",
      "url": "http://www.bilibili.com/video/av116420037842693",
      "time": "2026-04-19 14:16",
      "heat": 2,
      "discussions": "0",
      "tags": [],
      "isHot": false,
      "detail": "<p>税务申报太麻烦？FMS系统自动计税避坑！</p>"
    }
  ]
}