{
  "updated_at": "2026-04-14T14:19:19.271148+08:00",
  "count": 57,
  "topics": [
    {
      "id": "7be50726132c",
      "title": "不纳税将全球追逃？中国开始全球征税了，明星富豪们的噩耗来了，移民还会吃香吗？",
      "summary": "不纳税将全球追逃？中国开始全球征税了，明星富豪们的噩耗来了，移民还会吃香吗？",
      "source": "B站",
      "platform_class": "platform-bilibili",
      "author": "账号已注销",
      "url": "http://www.bilibili.com/video/av800112755",
      "time": "2026-04-14 14:19",
      "heat": 102368,
      "discussions": "3081",
      "tags": [
        "全球征税"
      ],
      "isHot": true,
      "detail": "<p>不纳税将全球追逃？中国开始全球征税了，明星富豪们的噩耗来了，移民还会吃香吗？</p>"
    },
    {
      "id": "b328a7a67cda",
      "title": "《国际税收》 朱青（税务433）",
      "summary": "2022年税务硕士考研群：830952137；\n2022年税务硕士考研群：830952137；\n2022年税务硕士考研群：830952137；\n2022年税务硕士考研群：830952137；\n2022年税务硕士考研群：830952137；",
      "source": "B站",
      "platform_class": "platform-bilibili",
      "author": "小熊老师带你飞",
      "url": "http://www.bilibili.com/video/av717134900",
      "time": "2026-04-14 14:19",
      "heat": 12211,
      "discussions": "559",
      "tags": [],
      "isHot": true,
      "detail": "<p>2022年税务硕士考研群：830952137；\n2022年税务硕士考研群：830952137；\n2022年税务硕士考研群：830952137；\n2022年税务硕士考研群：830952137；\n2022年税务硕士考研群：830952137；</p>"
    },
    {
      "id": "85fb3d48699e",
      "title": "新版电子税务局，小规模零申报操作流程",
      "summary": "-",
      "source": "B站",
      "platform_class": "platform-bilibili",
      "author": "百合财税",
      "url": "http://www.bilibili.com/video/av1456007058",
      "time": "2026-04-14 14:19",
      "heat": 7428,
      "discussions": "218",
      "tags": [],
      "isHot": true,
      "detail": "<p>-</p>"
    },
    {
      "id": "b383472acb8d",
      "title": "大明帝国，全球征税？",
      "summary": "大明帝国，全球征税？",
      "source": "B站",
      "platform_class": "platform-bilibili",
      "author": "历史侦查处",
      "url": "http://www.bilibili.com/video/av115653218535873",
      "time": "2026-04-14 14:19",
      "heat": 7330,
      "discussions": "223",
      "tags": [
        "全球征税"
      ],
      "isHot": false,
      "detail": "<p>大明帝国，全球征税？</p>"
    },
    {
      "id": "2b192ce20290",
      "title": "全球征税时代到来",
      "summary": "全球征税时代到来",
      "source": "B站",
      "platform_class": "platform-bilibili",
      "author": "EverEstate",
      "url": "http://www.bilibili.com/video/av115983377238843",
      "time": "2026-04-14 14:19",
      "heat": 6996,
      "discussions": "341",
      "tags": [
        "全球征税"
      ],
      "isHot": false,
      "detail": "<p>全球征税时代到来</p>"
    },
    {
      "id": "73a95a1ad689",
      "title": "为什么现在才开始大范围的CRS交换，境外收入补税？【David.D】",
      "summary": "为什么现在才开始大范围的CRS交换，境外收入补税？【David.D】",
      "source": "B站",
      "platform_class": "platform-bilibili",
      "author": "David邓博士金融学长",
      "url": "http://www.bilibili.com/video/av114901347472563",
      "time": "2026-04-14 14:19",
      "heat": 6501,
      "discussions": "233",
      "tags": [],
      "isHot": false,
      "detail": "<p>为什么现在才开始大范围的CRS交换，境外收入补税？【David.D】</p>"
    },
    {
      "id": "72a742456147",
      "title": "我们国家的税高不高？",
      "summary": "很多人感觉我们国家的税很高，真的是这样吗？你又是怎么认为的？",
      "source": "B站",
      "platform_class": "platform-bilibili",
      "author": "刘初旺讲财税",
      "url": "http://www.bilibili.com/video/av853509150",
      "time": "2026-04-14 14:19",
      "heat": 5655,
      "discussions": "373",
      "tags": [],
      "isHot": false,
      "detail": "<p>很多人感觉我们国家的税很高，真的是这样吗？你又是怎么认为的？</p>"
    },
    {
      "id": "6895e2e9909e",
      "title": "世界税收最高的国家 (美元)",
      "summary": "https://www.youtube.com/watch?v=DYRUBG1KJYY\n资源来源于外网，无泄漏机密",
      "source": "B站",
      "platform_class": "platform-bilibili",
      "author": "洛天依上单",
      "url": "http://www.bilibili.com/video/av1706271442",
      "time": "2026-04-14 14:19",
      "heat": 4424,
      "discussions": "222",
      "tags": [],
      "isHot": false,
      "detail": "<p>https://www.youtube.com/watch?v=DYRUBG1KJYY\n资源来源于外网，无泄漏机密</p>"
    },
    {
      "id": "b82175d964da",
      "title": "中国的信托是什么?和国外有什么差别？中国信托的现状",
      "summary": "上一集视频呢主要讲了信托的由来，主要是英美国家的信托制度。这集视频来讲讲中国的信托，看看和国外的信托到底有什么差别。视频中介绍了国内信托公司的发展背景、中国第一家信托公司设立的过程、信托行业的历史性转折时刻、中国信托的现状、自益信托以及最为重要的【中外信托的差别】，其中还谈到了中国信托的本质。创作不易，欢迎点赞、评论、转发！",
      "source": "B站",
      "platform_class": "platform-bilibili",
      "author": "信托研栗说",
      "url": "http://www.bilibili.com/video/av978800293",
      "time": "2026-04-14 14:19",
      "heat": 4301,
      "discussions": "73",
      "tags": [],
      "isHot": false,
      "detail": "<p>上一集视频呢主要讲了信托的由来，主要是英美国家的信托制度。这集视频来讲讲中国的信托，看看和国外的信托到底有什么差别。视频中介绍了国内信托公司的发展背景、中国第一家信托公司设立的过程、信托行业的历史性转折时刻、中国信托的现状、自益信托以及最为重要的【中外信托的差别】，其中还谈到了中国信托的本质。创作不易，欢迎点赞、评论、转发！</p>"
    },
    {
      "id": "dfae4266a939",
      "title": "一口气讲清楚，海外收入征税的8大问题【David.D】",
      "summary": "一口气讲清楚，海外收入征税的8大问题【David.D】",
      "source": "B站",
      "platform_class": "platform-bilibili",
      "author": "David邓博士金融学长",
      "url": "http://www.bilibili.com/video/av114987112599731",
      "time": "2026-04-14 14:19",
      "heat": 3264,
      "discussions": "90",
      "tags": [],
      "isHot": false,
      "detail": "<p>一口气讲清楚，海外收入征税的8大问题【David.D】</p>"
    },
    {
      "id": "dbb9b7c2f835",
      "title": "【史诗级提分干货】全网最好理解的国际税收框架——大白话的国际税收||433||国际税收||税务专硕||经验||方法||",
      "summary": "【史诗级提分干货】全网最好理解的国际税收框架——大白话的国际税收||433||国际税收||税务专硕||经验||方法||",
      "source": "B站",
      "platform_class": "platform-bilibili",
      "author": "映山学长税务专硕433",
      "url": "http://www.bilibili.com/video/av322096277",
      "time": "2026-04-14 14:19",
      "heat": 3217,
      "discussions": "23",
      "tags": [],
      "isHot": false,
      "detail": "<p>【史诗级提分干货】全网最好理解的国际税收框架——大白话的国际税收||433||国际税收||税务专硕||经验||方法||</p>"
    },
    {
      "id": "8257b0b35fb4",
      "title": "2025年新版电子税务局税务注销全流程",
      "summary": "-",
      "source": "B站",
      "platform_class": "platform-bilibili",
      "author": "晗妈会计",
      "url": "http://www.bilibili.com/video/av114640730195595",
      "time": "2026-04-14 14:19",
      "heat": 3101,
      "discussions": "121",
      "tags": [],
      "isHot": false,
      "detail": "<p>-</p>"
    },
    {
      "id": "bf17a2401eb1",
      "title": "T4. 一口气了解跨境税务规则！为什么需要双边税务协议？避税天堂为何能避税？科技巨头的零税魔术是如何运作的？",
      "summary": "你有没有想过，当一笔钱跨越国界，到底该向谁交税？为什么苹果、谷歌的实际税率能远低于美国法定税率？这背后，远不止“避税”这么简单。\n本期视频，我们将为你系统拆解 “跨境税务” 的完整知识版图：\n第一部分：规则的基石 —— 双边税收协定\n国家之间如何谈判，才能避免对同一笔收入“双重征税”？理解这份国家间的“税收合约”，是看懂所有跨国商业活动的第一课。\n第二部分：资本的舞台 —— 避税天堂的逻辑\n开曼群",
      "source": "B站",
      "platform_class": "platform-bilibili",
      "author": "财税解码",
      "url": "http://www.bilibili.com/video/av115728430663446",
      "time": "2026-04-14 14:19",
      "heat": 2989,
      "discussions": "49",
      "tags": [],
      "isHot": false,
      "detail": "<p>你有没有想过，当一笔钱跨越国界，到底该向谁交税？为什么苹果、谷歌的实际税率能远低于美国法定税率？这背后，远不止“避税”这么简单。\n本期视频，我们将为你系统拆解 “跨境税务” 的完整知识版图：\n第一部分：规则的基石 —— 双边税收协定\n国家之间如何谈判，才能避免对同一笔收入“双重征税”？理解这份国家间的“税收合约”，是看懂所有跨国商业活动的第一课。\n第二部分：资本的舞台 —— 避税天堂的逻辑\n开曼群</p>"
    },
    {
      "id": "93e4e7f6afd9",
      "title": "境外收入申报缴税动真格 有人补税近700万!",
      "summary": "境外收入申报缴税动真格了，有人补税近700万！税务部门公布多起境外所得补税典型案例。",
      "source": "B站",
      "platform_class": "platform-bilibili",
      "author": "看看新闻Knews",
      "url": "http://www.bilibili.com/video/av115549182891924",
      "time": "2026-04-14 14:19",
      "heat": 2202,
      "discussions": "83",
      "tags": [],
      "isHot": false,
      "detail": "<p>境外收入申报缴税动真格了，有人补税近700万！税务部门公布多起境外所得补税典型案例。</p>"
    },
    {
      "id": "fcf312c18522",
      "title": "【文韬】毕业以后去了一家信托公司的业务部门，需要多跟人打交道！专业知识虽然很重要，但更看重资源和人脉！如果不愿意和人打交道，那么要慎重考虑是否选择金融！",
      "summary": "20250625 夸克直播",
      "source": "B站",
      "platform_class": "platform-bilibili",
      "author": "llj_小草",
      "url": "http://www.bilibili.com/video/av114746510542127",
      "time": "2026-04-14 14:19",
      "heat": 1570,
      "discussions": "2",
      "tags": [],
      "isHot": false,
      "detail": "<p>20250625 夸克直播</p>"
    },
    {
      "id": "083ad58d5465",
      "title": "外媒披露：英国军工货走比利时转运以色列未申报，列日机场前被截，激光射控等关键装备全扣押",
      "summary": "► 本期看点：外媒披露：英国军工货走比利时转运以色列未申报，列日机场前被截，激光射控等关键装备全扣押\n\n🌐 精校熟肉，直击地缘博弈现场，听懂背后真实逻辑。\n\n与其选边站队，不如先把事实搞清楚。我们坚持原创精校，力求每一分钟都有价值。\n\n💬 理性交流欢迎，评论区见。\n\n⚠️ 老家已被抄，Ｂ站充电通道不知为何被关，请大家多多点赞支持，您的支持是更新的最大动力！",
      "source": "B站",
      "platform_class": "platform-bilibili",
      "author": "浪潮字幕组",
      "url": "http://www.bilibili.com/video/av116387188117767",
      "time": "2026-04-14 14:19",
      "heat": 1066,
      "discussions": "26",
      "tags": [],
      "isHot": false,
      "detail": "<p>► 本期看点：外媒披露：英国军工货走比利时转运以色列未申报，列日机场前被截，激光射控等关键装备全扣押\n\n🌐 精校熟肉，直击地缘博弈现场，听懂背后真实逻辑。\n\n与其选边站队，不如先把事实搞清楚。我们坚持原创精校，力求每一分钟都有价值。\n\n💬 理性交流欢迎，评论区见。\n\n⚠️ 老家已被抄，Ｂ站充电通道不知为何被关，请大家多多点赞支持，您的支持是更新的最大动力！</p>"
    },
    {
      "id": "b3330fdc3337",
      "title": "「影刀RPA」 财务机器人：税务局自动纳税申报",
      "summary": "如需在企业里使用该自动化应用，填写申请：https://ying-dao.feishu.cn/share/base/form/shrcnhAcnPkKTixfcWiVjqQ2uFh\n加入RPA学习群：https://mp.weixin.qq.com/s/5BLHkJq6Tk4Z-XxLtsjXOw",
      "source": "B站",
      "platform_class": "platform-bilibili",
      "author": "影刀RPA",
      "url": "http://www.bilibili.com/video/av647824949",
      "time": "2026-04-14 14:19",
      "heat": 928,
      "discussions": "14",
      "tags": [],
      "isHot": false,
      "detail": "<p>如需在企业里使用该自动化应用，填写申请：https://ying-dao.feishu.cn/share/base/form/shrcnhAcnPkKTixfcWiVjqQ2uFh\n加入RPA学习群：https://mp.weixin.qq.com/s/5BLHkJq6Tk4Z-XxLtsjXOw</p>"
    },
    {
      "id": "cc80469679a7",
      "title": "【海外家族信托】第十六讲 P1 信托如何影响税务？",
      "summary": "本节主要讲述信托在税收优化上的应用。请在视频中找到以下问题的答案：\n1、对于全球化布局的高净值人士，如何判定TA的税务居民身份？\n2、如何判断一个海外公司的税务居民身份？\n3、在税收上，居住管辖权和收入来源管辖权分别指什么？\n4、在不同的环节上，信托如何为您的税收作出优化？",
      "source": "B站",
      "platform_class": "platform-bilibili",
      "author": "施炳",
      "url": "http://www.bilibili.com/video/av828119337",
      "time": "2026-04-14 14:19",
      "heat": 876,
      "discussions": "11",
      "tags": [],
      "isHot": false,
      "detail": "<p>本节主要讲述信托在税收优化上的应用。请在视频中找到以下问题的答案：\n1、对于全球化布局的高净值人士，如何判定TA的税务居民身份？\n2、如何判断一个海外公司的税务居民身份？\n3、在税收上，居住管辖权和收入来源管辖权分别指什么？\n4、在不同的环节上，信托如何为您的税收作出优化？</p>"
    },
    {
      "id": "ab9bcb422773",
      "title": "境外所得抵免专题（全）",
      "summary": "上课玲一金玲财税课堂",
      "source": "B站",
      "platform_class": "platform-bilibili",
      "author": "财税会计实操UP主",
      "url": "http://www.bilibili.com/video/av39192226",
      "time": "2026-04-14 14:19",
      "heat": 574,
      "discussions": "12",
      "tags": [],
      "isHot": false,
      "detail": "<p>上课玲一金玲财税课堂</p>"
    },
    {
      "id": "1957a3f32f25",
      "title": "美国报税指南：美国报税注意事项及申报内容",
      "summary": "美国报税指南：美国报税注意事项及申报内容\n相关资源：\n美国国税局：https://www.irs.gov\n美国华人网：https://www.funinusa.net",
      "source": "B站",
      "platform_class": "platform-bilibili",
      "author": "很省钱",
      "url": "http://www.bilibili.com/video/av224019872",
      "time": "2026-04-14 14:19",
      "heat": 538,
      "discussions": "11",
      "tags": [],
      "isHot": false,
      "detail": "<p>美国报税指南：美国报税注意事项及申报内容\n相关资源：\n美国国税局：https://www.irs.gov\n美国华人网：https://www.funinusa.net</p>"
    },
    {
      "id": "275e35f8bd20",
      "title": "CRS， 收到税务局通知，境外炒股，到底要补多少钱？别猜了，3分钟算清楚！｜财富种植园",
      "summary": "收到稅務局通知心慌慌？境外資產補稅到底要補多少錢？\n別再自己瞎猜了！這期視頻手把手教你：上傳月結單，AI 3 分鐘幫你算得明明白白！\n很多人最近都收到了要求「境外所得自查」的短信或電話，第一反應都是：\n「我這幾年美股/港股到底賺了多少？」\n「虧損的部分能不能扣除？」\n「稅率是多少？要怎麼寫申報材料？」\n自己算，賬單幾百頁，先進先出（FIFO）算法算到頭大；請會計，收費貴不說，資料往來還麻煩。\n本期",
      "source": "B站",
      "platform_class": "platform-bilibili",
      "author": "财富种植园",
      "url": "http://www.bilibili.com/video/av115896269932539",
      "time": "2026-04-14 14:19",
      "heat": 455,
      "discussions": "12",
      "tags": [],
      "isHot": false,
      "detail": "<p>收到稅務局通知心慌慌？境外資產補稅到底要補多少錢？\n別再自己瞎猜了！這期視頻手把手教你：上傳月結單，AI 3 分鐘幫你算得明明白白！\n很多人最近都收到了要求「境外所得自查」的短信或電話，第一反應都是：\n「我這幾年美股/港股到底賺了多少？」\n「虧損的部分能不能扣除？」\n「稅率是多少？要怎麼寫申報材料？」\n自己算，賬單幾百頁，先進先出（FIFO）算法算到頭大；請會計，收費貴不說，資料往來還麻煩。\n本期</p>"
    },
    {
      "id": "e1fef66ee54f",
      "title": "“走出去”企业常见境外税收涉税风险及防范",
      "summary": "“走出去”企业常见境外税收涉税风险及防范",
      "source": "B站",
      "platform_class": "platform-bilibili",
      "author": "会计学习吧",
      "url": "http://www.bilibili.com/video/av113221059021266",
      "time": "2026-04-14 14:19",
      "heat": 438,
      "discussions": "2",
      "tags": [],
      "isHot": false,
      "detail": "<p>“走出去”企业常见境外税收涉税风险及防范</p>"
    },
    {
      "id": "5e6e60953b00",
      "title": "取得境外所得如何通过个税APP申报个人所得税(浙江税务)",
      "summary": "宝子们！5月29日还没报境外所得个税的注意啦！今年起用个税APP就能搞定，超省心～\n\n哪些算境外所得？像海外工资、境外股息、转让境外房产等9类收入都要报，具体看财政部2020年3号公告！记得每年3月1日-6月30日申报，现在只剩最后几天，别漏了！\n\n操作超简单：打开个税APP，首页搜“年度汇算（取得境外所得适用）”，填境内外综合所得、经营所得，利息股息等分类所得单独填；境外已缴税别慌，系统自动算抵",
      "source": "B站",
      "platform_class": "platform-bilibili",
      "author": "税务师木木",
      "url": "http://www.bilibili.com/video/av114588066516202",
      "time": "2026-04-14 14:19",
      "heat": 417,
      "discussions": "2",
      "tags": [],
      "isHot": false,
      "detail": "<p>宝子们！5月29日还没报境外所得个税的注意啦！今年起用个税APP就能搞定，超省心～\n\n哪些算境外所得？像海外工资、境外股息、转让境外房产等9类收入都要报，具体看财政部2020年3号公告！记得每年3月1日-6月30日申报，现在只剩最后几天，别漏了！\n\n操作超简单：打开个税APP，首页搜“年度汇算（取得境外所得适用）”，填境内外综合所得、经营所得，利息股息等分类所得单独填；境外已缴税别慌，系统自动算抵</p>"
    },
    {
      "id": "974cfea5e48d",
      "title": "CRS海外收入自查补报三年",
      "summary": "-",
      "source": "B站",
      "platform_class": "platform-bilibili",
      "author": "馒头娘说税",
      "url": "http://www.bilibili.com/video/av115942256287349",
      "time": "2026-04-14 14:19",
      "heat": 375,
      "discussions": "15",
      "tags": [],
      "isHot": false,
      "detail": "<p>-</p>"
    },
    {
      "id": "8ccb49f41b35",
      "title": "美国公司税务全解析，从税种解读、EIN申请到申报日期，全都在这个视频里！",
      "summary": "准备在美国开公司吗？那你得小心了，因为美国的税法可不简单。一不小心就可能被罚款，甚至更糟。美国国税局（IRS）在全球都是出了名的厉害，就算是不小心少交点税，后果也可能很严重，比如罚款或者冻结你的资产！所以，无论你是刚开始创业还是已经在经营自己的小企业，了解美国税法是非常重要的。在这个视频里，我们会用简单易懂的方式，告诉你美国税法的基本知识，帮你避开那些可能因为税务问题而遇到的麻烦。",
      "source": "B站",
      "platform_class": "platform-bilibili",
      "author": "Ashley聊境外",
      "url": "http://www.bilibili.com/video/av1800794851",
      "time": "2026-04-14 14:19",
      "heat": 321,
      "discussions": "1",
      "tags": [],
      "isHot": false,
      "detail": "<p>准备在美国开公司吗？那你得小心了，因为美国的税法可不简单。一不小心就可能被罚款，甚至更糟。美国国税局（IRS）在全球都是出了名的厉害，就算是不小心少交点税，后果也可能很严重，比如罚款或者冻结你的资产！所以，无论你是刚开始创业还是已经在经营自己的小企业，了解美国税法是非常重要的。在这个视频里，我们会用简单易懂的方式，告诉你美国税法的基本知识，帮你避开那些可能因为税务问题而遇到的麻烦。</p>"
    },
    {
      "id": "80f9ba12e5c2",
      "title": "查CRS来电的居然是AI，有外面资产必懂的税务新规。",
      "summary": "-",
      "source": "B站",
      "platform_class": "platform-bilibili",
      "author": "Nina海外配配",
      "url": "http://www.bilibili.com/video/av115808340543826",
      "time": "2026-04-14 14:19",
      "heat": 298,
      "discussions": "5",
      "tags": [],
      "isHot": false,
      "detail": "<p>-</p>"
    },
    {
      "id": "94e95f137feb",
      "title": "离岸家族信托：富人藏匿财富的保险箱？新西兰 vs 新加坡 vs BVI，我们到底该在哪里将财富保卫战进行到底？",
      "summary": "新西兰 vs 新加坡 vs BVI，我们到底该在哪里将财富保卫战进行到底？",
      "source": "B站",
      "platform_class": "platform-bilibili",
      "author": "順手牵洋",
      "url": "http://www.bilibili.com/video/av114159542868814",
      "time": "2026-04-14 14:19",
      "heat": 236,
      "discussions": "4",
      "tags": [],
      "isHot": false,
      "detail": "<p>新西兰 vs 新加坡 vs BVI，我们到底该在哪里将财富保卫战进行到底？</p>"
    },
    {
      "id": "9b3b3b0c0e78",
      "title": "CRS: 2026 境外投資稅務申報教學：AI 自動計算美股/港股投資所得，個人所得稅 APP 報稅全攻略",
      "summary": "💡 境外投資報稅太複雜？請會計太貴？本視頻手把手教你使用最新的 AI 稅務工具，自動化處理你的券商月報表、年報表，一鍵生成符合審計要求的 Excel 底稿，讓你在個人所得稅 APP 申報時輕鬆無憂！\n\n📌 視頻核心內容：\n00:00 工具背景與核心價值（省時、省錢、防風險）\n01:08 免費體驗額度獲取與定價方案\n02:00 邀請碼機制：雙方均可獲得 50% 額外額度\n02:40 數據安全保障：本",
      "source": "B站",
      "platform_class": "platform-bilibili",
      "author": "财富种植园",
      "url": "http://www.bilibili.com/video/av116132493133650",
      "time": "2026-04-14 14:19",
      "heat": 215,
      "discussions": "14",
      "tags": [],
      "isHot": false,
      "detail": "<p>💡 境外投資報稅太複雜？請會計太貴？本視頻手把手教你使用最新的 AI 稅務工具，自動化處理你的券商月報表、年報表，一鍵生成符合審計要求的 Excel 底稿，讓你在個人所得稅 APP 申報時輕鬆無憂！\n\n📌 視頻核心內容：\n00:00 工具背景與核心價值（省時、省錢、防風險）\n01:08 免費體驗額度獲取與定價方案\n02:00 邀請碼機制：雙方均可獲得 50% 額外額度\n02:40 數據安全保障：本</p>"
    },
    {
      "id": "923c9bcb2d25",
      "title": "中国开启全球征税时代！境外收入恶意逃税可能要坐牢",
      "summary": "中国税务居民在海外赚了钱，都需要向中国税务机关报税。如果不报税被查出来，则将面临补税+罚款，恶意逃税者还将承担刑事责任，牢饭供应。\n \n本来境外收入报税交税这件事，喊了很多年，但因为技术原因并未普及开来。但是现在，技术的进步与国际合作的紧密，让心存侥幸者无所遁形。\n \n近日，中国的浙江、山东、上海、湖北四地税务机关同步发布公告，针对中国境内居民的境外收入申报问题开展集中核查。\n \n通过大数据识别出",
      "source": "B站",
      "platform_class": "platform-bilibili",
      "author": "无忧启程移民",
      "url": "http://www.bilibili.com/video/av114420143494580",
      "time": "2026-04-14 14:19",
      "heat": 192,
      "discussions": "8",
      "tags": [
        "全球征税"
      ],
      "isHot": false,
      "detail": "<p>中国税务居民在海外赚了钱，都需要向中国税务机关报税。如果不报税被查出来，则将面临补税+罚款，恶意逃税者还将承担刑事责任，牢饭供应。\n \n本来境外收入报税交税这件事，喊了很多年，但因为技术原因并未普及开来。但是现在，技术的进步与国际合作的紧密，让心存侥幸者无所遁形。\n \n近日，中国的浙江、山东、上海、湖北四地税务机关同步发布公告，针对中国境内居民的境外收入申报问题开展集中核查。\n \n通过大数据识别出</p>"
    },
    {
      "id": "c0123dc6b505",
      "title": "分公司都需要申报哪些税零申报全流程",
      "summary": "-",
      "source": "B站",
      "platform_class": "platform-bilibili",
      "author": "晗妈会计",
      "url": "http://www.bilibili.com/video/av114822914050754",
      "time": "2026-04-14 14:19",
      "heat": 172,
      "discussions": "1",
      "tags": [],
      "isHot": false,
      "detail": "<p>-</p>"
    },
    {
      "id": "eab87e383e83",
      "title": "26年4月份个体户有销售收入申报全流程",
      "summary": "-",
      "source": "B站",
      "platform_class": "platform-bilibili",
      "author": "晗妈会计",
      "url": "http://www.bilibili.com/video/av116374873572931",
      "time": "2026-04-14 14:19",
      "heat": 162,
      "discussions": "2",
      "tags": [],
      "isHot": false,
      "detail": "<p>-</p>"
    },
    {
      "id": "3914909338d2",
      "title": "富豪许世勋遗产分配：420亿交信托基金，许晋亨夫妇每月可领200万",
      "summary": "被称为“富豪杀手”的李嘉欣让香港豪门太太警惕，最终她如愿嫁入许家，许爱周家族是香港传统的“四大家族”，与新晋豪门不同，许家有不错的家族底蕴，生意稳定，不会破产，真正是“稳中取胜”。那么许家... ...",
      "source": "B站",
      "platform_class": "platform-bilibili",
      "author": "江山指点",
      "url": "http://www.bilibili.com/video/av287923248",
      "time": "2026-04-14 14:19",
      "heat": 155,
      "discussions": "2",
      "tags": [],
      "isHot": false,
      "detail": "<p>被称为“富豪杀手”的李嘉欣让香港豪门太太警惕，最终她如愿嫁入许家，许爱周家族是香港传统的“四大家族”，与新晋豪门不同，许家有不错的家族底蕴，生意稳定，不会破产，真正是“稳中取胜”。那么许家... ...</p>"
    },
    {
      "id": "2f1858a0a6e9",
      "title": "光大信托、长安信托、国通信托、中江信托等踩雷陕西韩城项目",
      "summary": "光大信托、长安信托、国通信托、中江信托等踩雷陕西韩城项目",
      "source": "B站",
      "platform_class": "platform-bilibili",
      "author": "中队长讲投资",
      "url": "http://www.bilibili.com/video/av290156166",
      "time": "2026-04-14 14:19",
      "heat": 143,
      "discussions": "1",
      "tags": [],
      "isHot": false,
      "detail": "<p>光大信托、长安信托、国通信托、中江信托等踩雷陕西韩城项目</p>"
    },
    {
      "id": "cdaf0da16f01",
      "title": "【1/3】家族信托、家庭信托、保险金信托介绍",
      "summary": "茫茫尘世中一个伴读小书童，温酒与你共同成长~",
      "source": "B站",
      "platform_class": "platform-bilibili",
      "author": "温酒醉琉璃",
      "url": "http://www.bilibili.com/video/av1202068801",
      "time": "2026-04-14 14:19",
      "heat": 111,
      "discussions": "4",
      "tags": [],
      "isHot": false,
      "detail": "<p>茫茫尘世中一个伴读小书童，温酒与你共同成长~</p>"
    },
    {
      "id": "d8fa56c29a87",
      "title": "长安信托现“内鬼”，“阴阳合同”瞒天过海",
      "summary": "长安信托现“内鬼”，“阴阳合同”瞒天过海",
      "source": "B站",
      "platform_class": "platform-bilibili",
      "author": "冯博内控财务正经谈",
      "url": "http://www.bilibili.com/video/av210175304",
      "time": "2026-04-14 14:19",
      "heat": 108,
      "discussions": "2",
      "tags": [],
      "isHot": false,
      "detail": "<p>长安信托现“内鬼”，“阴阳合同”瞒天过海</p>"
    },
    {
      "id": "41e9712adacf",
      "title": "2025年境外收入在国内缴税的方法",
      "summary": "2025年境外收入在国内缴税的方法",
      "source": "B站",
      "platform_class": "platform-bilibili",
      "author": "淡定的飞马",
      "url": "http://www.bilibili.com/video/av116228072934922",
      "time": "2026-04-14 14:19",
      "heat": 88,
      "discussions": "8",
      "tags": [],
      "isHot": false,
      "detail": "<p>2025年境外收入在国内缴税的方法</p>"
    },
    {
      "id": "0e8e2fa17e4b",
      "title": "《如何利用海外家族信托做好财富传承》",
      "summary": "《如何利用海外家族信托做好财富传承》",
      "source": "B站",
      "platform_class": "platform-bilibili",
      "author": "侨外出国",
      "url": "http://www.bilibili.com/video/av947063286",
      "time": "2026-04-14 14:19",
      "heat": 87,
      "discussions": "1",
      "tags": [],
      "isHot": false,
      "detail": "<p>《如何利用海外家族信托做好财富传承》</p>"
    },
    {
      "id": "4d5d678ff878",
      "title": "什么是信托通道业务？如何核实信托产品的真实性？",
      "summary": "-",
      "source": "B站",
      "platform_class": "platform-bilibili",
      "author": "刘sir聊信托",
      "url": "http://www.bilibili.com/video/av701706157",
      "time": "2026-04-14 14:19",
      "heat": 85,
      "discussions": "0",
      "tags": [],
      "isHot": false,
      "detail": "<p>-</p>"
    },
    {
      "id": "6768323b3215",
      "title": "海外机构联合创始人直播技术分享：4月14日周二晚20点，基于ML构建量化模型的全流程拆解～",
      "summary": "-",
      "source": "B站",
      "platform_class": "platform-bilibili",
      "author": "uni的量化日记",
      "url": "http://www.bilibili.com/video/av116395660613119",
      "time": "2026-04-14 14:19",
      "heat": 67,
      "discussions": "3",
      "tags": [],
      "isHot": false,
      "detail": "<p>-</p>"
    },
    {
      "id": "11ceaa5e720c",
      "title": "境外国资工作局成立，海外10万亿资产还会出现流失吗？",
      "summary": "境外国资工作局成立，海外10万亿资产还会出现流失吗？",
      "source": "B站",
      "platform_class": "platform-bilibili",
      "author": "刘一手看财经",
      "url": "http://www.bilibili.com/video/av116390426117338",
      "time": "2026-04-14 14:19",
      "heat": 45,
      "discussions": "0",
      "tags": [],
      "isHot": false,
      "detail": "<p>境外国资工作局成立，海外10万亿资产还会出现流失吗？</p>"
    },
    {
      "id": "a7cb298c7c25",
      "title": "香港信托和内地信托有什么区别?委托人会承担什么风险?",
      "summary": "香港信托和内地信托有什么区别?委托人会承担什么风险?",
      "source": "B站",
      "platform_class": "platform-bilibili",
      "author": "小龙哥说基金",
      "url": "http://www.bilibili.com/video/av1402468848",
      "time": "2026-04-14 14:19",
      "heat": 41,
      "discussions": "1",
      "tags": [],
      "isHot": false,
      "detail": "<p>香港信托和内地信托有什么区别?委托人会承担什么风险?</p>"
    },
    {
      "id": "892fb29e0c13",
      "title": "坚朗五金：海外业务强劲支撑，维持买入评级，目标价23元",
      "summary": "来源 坚朗五金：海外业务强劲，维持买入，目标价23元.pdf 来源指南 Yi Wang, CFA rities Company Limited Shi Xu rities Company Limited Kaiyan Jing es Company Limited with strength in overseas business and cash collection; retain Buy ",
      "source": "B站",
      "platform_class": "platform-bilibili",
      "author": "研报平权",
      "url": "http://www.bilibili.com/video/av116395694101602",
      "time": "2026-04-14 14:19",
      "heat": 36,
      "discussions": "0",
      "tags": [],
      "isHot": false,
      "detail": "<p>来源 坚朗五金：海外业务强劲，维持买入，目标价23元.pdf 来源指南 Yi Wang, CFA rities Company Limited Shi Xu rities Company Limited Kaiyan Jing es Company Limited with strength in overseas business and cash collection; retain Buy </p>"
    },
    {
      "id": "5df38ce2c2ce",
      "title": "境外国资工作局成立，释放什么信号？",
      "summary": "2026年4月8日国资委成立境外国资工作局，这背后，究竟藏着国家怎样的战略深意？是简单的机构调整，还是一场关乎万亿国资安全的“保卫战”？",
      "source": "B站",
      "platform_class": "platform-bilibili",
      "author": "国企改革明律师",
      "url": "http://www.bilibili.com/video/av116369538419474",
      "time": "2026-04-14 14:19",
      "heat": 30,
      "discussions": "0",
      "tags": [],
      "isHot": false,
      "detail": "<p>2026年4月8日国资委成立境外国资工作局，这背后，究竟藏着国家怎样的战略深意？是简单的机构调整，还是一场关乎万亿国资安全的“保卫战”？</p>"
    },
    {
      "id": "7884ec703034",
      "title": "税筹和海外资产申报！第四集                                     #税筹#海外资产申报#全球收入#资产配置#税务居民",
      "summary": "-",
      "source": "B站",
      "platform_class": "platform-bilibili",
      "author": "好好谈出国",
      "url": "http://www.bilibili.com/video/av789277386",
      "time": "2026-04-14 14:19",
      "heat": 28,
      "discussions": "0",
      "tags": [
        "海外资产申报"
      ],
      "isHot": false,
      "detail": "<p>-</p>"
    },
    {
      "id": "5ec031df1ef6",
      "title": "聊聊最近跨境电商税务申报的一些问题",
      "summary": "今天这个视频，和大家聊聊跨境电商税务申报的一些问题~\n第一，关于2025年三、四季度的数据申报；第二，店铺收入超过500w，被要求升级为一般纳税人；第三，个人以及个体户店铺需在3.31之前完成生产经营所得申报。近期和很多地方的税务老师进行沟通，最明确的一点就是：一定要把货物合规出口尽快做起来，这个不要再等啦！！！",
      "source": "B站",
      "platform_class": "platform-bilibili",
      "author": "专诚财税",
      "url": "http://www.bilibili.com/video/av116289158777084",
      "time": "2026-04-14 14:19",
      "heat": 24,
      "discussions": "2",
      "tags": [],
      "isHot": false,
      "detail": "<p>今天这个视频，和大家聊聊跨境电商税务申报的一些问题~\n第一，关于2025年三、四季度的数据申报；第二，店铺收入超过500w，被要求升级为一般纳税人；第三，个人以及个体户店铺需在3.31之前完成生产经营所得申报。近期和很多地方的税务老师进行沟通，最明确的一点就是：一定要把货物合规出口尽快做起来，这个不要再等啦！！！</p>"
    },
    {
      "id": "bb930d2c3a7e",
      "title": "【直播回放】肖兴利 | 境外资产追回的法律实务问题",
      "summary": "欢迎收看涉外刑事法律服务系列课程~ \n本期主要内容：聚焦我国境外资产追回的法律制度，结合典型案例详细拆解缺席审判程序、违法所得没收程序、境外民事诉讼程序、犯罪资产分享制度等四种程序的法律依据、规则内容及优势不足，在提出完善建议的同时，探讨了境外追逃追赃实务中的律师作用及业务机会。\n每周三14:00-15:30，盈科精英教育B站直播间，与您不见不散！",
      "source": "B站",
      "platform_class": "platform-bilibili",
      "author": "盈科精英教育",
      "url": "http://www.bilibili.com/video/av115388322939530",
      "time": "2026-04-14 14:19",
      "heat": 22,
      "discussions": "0",
      "tags": [],
      "isHot": false,
      "detail": "<p>欢迎收看涉外刑事法律服务系列课程~ \n本期主要内容：聚焦我国境外资产追回的法律制度，结合典型案例详细拆解缺席审判程序、违法所得没收程序、境外民事诉讼程序、犯罪资产分享制度等四种程序的法律依据、规则内容及优势不足，在提出完善建议的同时，探讨了境外追逃追赃实务中的律师作用及业务机会。\n每周三14:00-15:30，盈科精英教育B站直播间，与您不见不散！</p>"
    },
    {
      "id": "44081476ba3f",
      "title": "海外账户即将共同申报！海外资产也要报税！",
      "summary": "海外账户即将共同申报！海外资产也要报税！",
      "source": "B站",
      "platform_class": "platform-bilibili",
      "author": "Stephen移民咨询",
      "url": "http://www.bilibili.com/video/av114833852794166",
      "time": "2026-04-14 14:19",
      "heat": 21,
      "discussions": "0",
      "tags": [],
      "isHot": false,
      "detail": "<p>海外账户即将共同申报！海外资产也要报税！</p>"
    },
    {
      "id": "182302ff8e6a",
      "title": "涉外离婚案里中国法院就不能处理境外资产么，哼",
      "summary": "涉外离婚案里中国法院就不能处理境外资产么，哼",
      "source": "B站",
      "platform_class": "platform-bilibili",
      "author": "法律人江风",
      "url": "http://www.bilibili.com/video/av116199635552368",
      "time": "2026-04-14 14:19",
      "heat": 17,
      "discussions": "0",
      "tags": [],
      "isHot": false,
      "detail": "<p>涉外离婚案里中国法院就不能处理境外资产么，哼</p>"
    },
    {
      "id": "708d4c7c017c",
      "title": "开曼BVI信托被查！海外资产全可视，往外转钱=踩红线（必看）",
      "summary": "各位朋友，今天说一个重磅消息 ——3 月 31 号，彭博社正式报道：中国税务部门，对持有港股的海外信托，开始全面严查、全面穿透。开曼、BVI 这些曾经的 “避税天堂”，现在彻底不隐秘了。",
      "source": "B站",
      "platform_class": "platform-bilibili",
      "author": "Miss杨聊财富管理",
      "url": "http://www.bilibili.com/video/av116373279804108",
      "time": "2026-04-14 14:19",
      "heat": 11,
      "discussions": "1",
      "tags": [
        "海外信托"
      ],
      "isHot": false,
      "detail": "<p>各位朋友，今天说一个重磅消息 ——3 月 31 号，彭博社正式报道：中国税务部门，对持有港股的海外信托，开始全面严查、全面穿透。开曼、BVI 这些曾经的 “避税天堂”，现在彻底不隐秘了。</p>"
    },
    {
      "id": "76b389a5dc9c",
      "title": "海外资产申报汇总",
      "summary": "海外资产都要申报什么？国内房子出租租金要申报吗？别人欠我钱也要申报吗？资产很少也要申报吗？",
      "source": "B站",
      "platform_class": "platform-bilibili",
      "author": "多咨处",
      "url": "http://www.bilibili.com/video/av876902196",
      "time": "2026-04-14 14:19",
      "heat": 9,
      "discussions": "0",
      "tags": [
        "海外资产申报"
      ],
      "isHot": false,
      "detail": "<p>海外资产都要申报什么？国内房子出租租金要申报吗？别人欠我钱也要申报吗？资产很少也要申报吗？</p>"
    },
    {
      "id": "85b7aa181d9a",
      "title": "英国网银Wise支持内地身份证护照远程办理，新出的港元账户选择香港星展银行合作，内地身份注册可以免费获取一个香港星展DBS银行账户，支持港美股出入金",
      "summary": "英国Wise网银，内地身份在线办理开户：https://wise.com/invite/dit/yuc126\n\n-海外券商港美股远程开户\n盈立新加坡：\n邀请码：n759q9\nusmart.sg/?HCode=n759q9\n\nWealth Broker华通玖安：\n邀请码：U604M\np.wbroker.info/Hra0Dk7?lan=en",
      "source": "B站",
      "platform_class": "platform-bilibili",
      "author": "爱打劫的警长",
      "url": "http://www.bilibili.com/video/av116401113137792",
      "time": "2026-04-14 14:19",
      "heat": 9,
      "discussions": "0",
      "tags": [],
      "isHot": false,
      "detail": "<p>英国Wise网银，内地身份在线办理开户：https://wise.com/invite/dit/yuc126\n\n-海外券商港美股远程开户\n盈立新加坡：\n邀请码：n759q9\nusmart.sg/?HCode=n759q9\n\nWealth Broker华通玖安：\n邀请码：U604M\np.wbroker.info/Hra0Dk7?lan=en</p>"
    },
    {
      "id": "bc195f2c9520",
      "title": "隐忍五年，我在等信托协议生效！",
      "summary": "富家千金许清媛为爱下嫁凤凰男林慕城，五年倾尽嫁妆扶持丈夫、照料婆婆。可林慕城早已变心，挪用她的钱财供养情人江映雪，还为她开办康复中心。一次就医中，江映雪用报废仪器烫伤婆婆，当众欺凌、辱骂许清媛，气死婆婆，林慕城却偏袒小三，狠心赶走母女。心死的许清媛决定反击。她本是鼎盛集团千金，婚后满五年便可继承股权。在父亲帮助下，她收集两人非法行医、挪用公款、做空股票等罪证。发布会当天，许清媛惊艳登场，当众曝光所",
      "source": "B站",
      "platform_class": "platform-bilibili",
      "author": "掌邦剧场",
      "url": "http://www.bilibili.com/video/av116374101820441",
      "time": "2026-04-14 14:19",
      "heat": 9,
      "discussions": "0",
      "tags": [],
      "isHot": false,
      "detail": "<p>富家千金许清媛为爱下嫁凤凰男林慕城，五年倾尽嫁妆扶持丈夫、照料婆婆。可林慕城早已变心，挪用她的钱财供养情人江映雪，还为她开办康复中心。一次就医中，江映雪用报废仪器烫伤婆婆，当众欺凌、辱骂许清媛，气死婆婆，林慕城却偏袒小三，狠心赶走母女。心死的许清媛决定反击。她本是鼎盛集团千金，婚后满五年便可继承股权。在父亲帮助下，她收集两人非法行医、挪用公款、做空股票等罪证。发布会当天，许清媛惊艳登场，当众曝光所</p>"
    },
    {
      "id": "8702926db90a",
      "title": "跳槽灵感｜从新媒体运营到海外用增，文科生涨薪100%的职业选择思路！",
      "summary": "🟢 Part 1 从跨界跳槽到爆单实战：职业路径的多样探索\n00:01:04 鸽子老师分享跳槽经历：职场选择与生活方式的多样性\n00:01:55 职业转变实录：从新媒体运营到海外用户增长，像换了游戏模式！\n00:03:29 携程潜伏社群发小广告：一场游击战式的运营初体验\n00:04:21 小红书攻略成利器：百赞引爆留学生市场订单询问潮\n00:05:30 用领导小号试水小红书，第三条内容即实现爆单\n",
      "source": "B站",
      "platform_class": "platform-bilibili",
      "author": "加七个七",
      "url": "http://www.bilibili.com/video/av116392707820706",
      "time": "2026-04-14 14:19",
      "heat": 7,
      "discussions": "0",
      "tags": [],
      "isHot": false,
      "detail": "<p>🟢 Part 1 从跨界跳槽到爆单实战：职业路径的多样探索\n00:01:04 鸽子老师分享跳槽经历：职场选择与生活方式的多样性\n00:01:55 职业转变实录：从新媒体运营到海外用户增长，像换了游戏模式！\n00:03:29 携程潜伏社群发小广告：一场游击战式的运营初体验\n00:04:21 小红书攻略成利器：百赞引爆留学生市场订单询问潮\n00:05:30 用领导小号试水小红书，第三条内容即实现爆单\n</p>"
    },
    {
      "id": "7d237b79bffb",
      "title": "海外公司的信息被平台推送给中国sj了？",
      "summary": "-",
      "source": "B站",
      "platform_class": "platform-bilibili",
      "author": "卓信karen",
      "url": "http://www.bilibili.com/video/av116398076466451",
      "time": "2026-04-14 14:19",
      "heat": 4,
      "discussions": "0",
      "tags": [],
      "isHot": false,
      "detail": "<p>-</p>"
    },
    {
      "id": "4043474eb895",
      "title": "如果子女常年定居在海外 国内的父母最好提前订立公证遗嘱",
      "summary": "如果子女常年定居在海外\n国内的父母最好提前订立公证遗嘱",
      "source": "B站",
      "platform_class": "platform-bilibili",
      "author": "公证员宁姐",
      "url": "http://www.bilibili.com/video/av116396717512115",
      "time": "2026-04-14 14:19",
      "heat": 4,
      "discussions": "0",
      "tags": [],
      "isHot": false,
      "detail": "<p>如果子女常年定居在海外\n国内的父母最好提前订立公证遗嘱</p>"
    },
    {
      "id": "7d902473439c",
      "title": "海外资产申报一定要评估报告吗",
      "summary": "海外资产申报一定要评估报告吗",
      "source": "B站",
      "platform_class": "platform-bilibili",
      "author": "深美林评估",
      "url": "http://www.bilibili.com/video/av116396784682194",
      "time": "2026-04-14 14:19",
      "heat": 0,
      "discussions": "0",
      "tags": [
        "海外资产申报"
      ],
      "isHot": false,
      "detail": "<p>海外资产申报一定要评估报告吗</p>"
    },
    {
      "id": "81e2a42b0e36",
      "title": "别挑房！先拿希腊身份才是硬道理#希腊购房移民 #华侨生联考 #海外资产配置 #特蕾西海外",
      "summary": "-",
      "source": "B站",
      "platform_class": "platform-bilibili",
      "author": "特蕾西海外-希腊规划",
      "url": "http://www.bilibili.com/video/av116400525934816",
      "time": "2026-04-14 14:19",
      "heat": 0,
      "discussions": "0",
      "tags": [],
      "isHot": false,
      "detail": "<p>-</p>"
    }
  ]
}