{
  "updated_at": "2026-04-29T00:29:24.481165+08:00",
  "count": 51,
  "topics": [
    {
      "id": "b328a7a67cda",
      "title": "《国际税收》 朱青（税务433）",
      "summary": "2022年税务硕士考研群：830952137；\n2022年税务硕士考研群：830952137；\n2022年税务硕士考研群：830952137；\n2022年税务硕士考研群：830952137；\n2022年税务硕士考研群：830952137；",
      "source": "B站",
      "platform_class": "platform-bilibili",
      "author": "小熊老师带你飞",
      "url": "http://www.bilibili.com/video/av717134900",
      "time": "2026-04-29 00:29",
      "heat": 12292,
      "discussions": "565",
      "tags": [],
      "isHot": true,
      "detail": "<p>2022年税务硕士考研群：830952137；\n2022年税务硕士考研群：830952137；\n2022年税务硕士考研群：830952137；\n2022年税务硕士考研群：830952137；\n2022年税务硕士考研群：830952137；</p>"
    },
    {
      "id": "8da0db090837",
      "title": "🔥网上办理税务登记全流程",
      "summary": "拿到营业执照后足不出户就可以网上办理税务登记啦！",
      "source": "B站",
      "platform_class": "platform-bilibili",
      "author": "跟着可可学实操",
      "url": "http://www.bilibili.com/video/av704446276",
      "time": "2026-04-29 00:29",
      "heat": 7536,
      "discussions": "253",
      "tags": [],
      "isHot": true,
      "detail": "<p>拿到营业执照后足不出户就可以网上办理税务登记啦！</p>"
    },
    {
      "id": "2b192ce20290",
      "title": "全球征税时代到来",
      "summary": "全球征税时代到来",
      "source": "B站",
      "platform_class": "platform-bilibili",
      "author": "EverEstate",
      "url": "http://www.bilibili.com/video/av115983377238843",
      "time": "2026-04-29 00:29",
      "heat": 7165,
      "discussions": "347",
      "tags": [
        "全球征税"
      ],
      "isHot": true,
      "detail": "<p>全球征税时代到来</p>"
    },
    {
      "id": "73a95a1ad689",
      "title": "为什么现在才开始大范围的CRS交换，境外收入补税？【David.D】",
      "summary": "为什么现在才开始大范围的CRS交换，境外收入补税？【David.D】",
      "source": "B站",
      "platform_class": "platform-bilibili",
      "author": "David邓博士金融学长",
      "url": "http://www.bilibili.com/video/av114901347472563",
      "time": "2026-04-29 00:29",
      "heat": 6542,
      "discussions": "237",
      "tags": [],
      "isHot": false,
      "detail": "<p>为什么现在才开始大范围的CRS交换，境外收入补税？【David.D】</p>"
    },
    {
      "id": "72a742456147",
      "title": "我们国家的税高不高？",
      "summary": "很多人感觉我们国家的税很高，真的是这样吗？你又是怎么认为的？",
      "source": "B站",
      "platform_class": "platform-bilibili",
      "author": "刘初旺讲财税",
      "url": "http://www.bilibili.com/video/av853509150",
      "time": "2026-04-29 00:29",
      "heat": 5690,
      "discussions": "375",
      "tags": [],
      "isHot": false,
      "detail": "<p>很多人感觉我们国家的税很高，真的是这样吗？你又是怎么认为的？</p>"
    },
    {
      "id": "e3273c15b705",
      "title": "税务会计【全54讲】【含资料】【中南财经政法大学】【国家级精品课】",
      "summary": "参考教材：税务会计学 作者：郭月梅 出版社：西安交通大学出版社 出版月份：2018-02\n税收会计是一门综合应用性很强的学科，它以财务会计和税法为基础，是同时如合并重组中的税务问题又和财务管理、金融学、投资学、法学等学科相联系。因此，通过本课程的学习，学生应获得以下基本技能：将税法知识与会计处理对应，掌握纳税过程从纳税义务产生、缴纳税务、申报退税等环节的会计处理；重点掌握会计准则与所得税法的区别，",
      "source": "B站",
      "platform_class": "platform-bilibili",
      "author": "爱学习的小刚子",
      "url": "http://www.bilibili.com/video/av115073011946776",
      "time": "2026-04-29 00:29",
      "heat": 3739,
      "discussions": "10",
      "tags": [],
      "isHot": false,
      "detail": "<p>参考教材：税务会计学 作者：郭月梅 出版社：西安交通大学出版社 出版月份：2018-02\n税收会计是一门综合应用性很强的学科，它以财务会计和税法为基础，是同时如合并重组中的税务问题又和财务管理、金融学、投资学、法学等学科相联系。因此，通过本课程的学习，学生应获得以下基本技能：将税法知识与会计处理对应，掌握纳税过程从纳税义务产生、缴纳税务、申报退税等环节的会计处理；重点掌握会计准则与所得税法的区别，</p>"
    },
    {
      "id": "dfae4266a939",
      "title": "一口气讲清楚，海外收入征税的8大问题【David.D】",
      "summary": "一口气讲清楚，海外收入征税的8大问题【David.D】",
      "source": "B站",
      "platform_class": "platform-bilibili",
      "author": "David邓博士金融学长",
      "url": "http://www.bilibili.com/video/av114987112599731",
      "time": "2026-04-29 00:29",
      "heat": 3262,
      "discussions": "90",
      "tags": [],
      "isHot": false,
      "detail": "<p>一口气讲清楚，海外收入征税的8大问题【David.D】</p>"
    },
    {
      "id": "dbb9b7c2f835",
      "title": "【史诗级提分干货】全网最好理解的国际税收框架——大白话的国际税收||433||国际税收||税务专硕||经验||方法||",
      "summary": "【史诗级提分干货】全网最好理解的国际税收框架——大白话的国际税收||433||国际税收||税务专硕||经验||方法||",
      "source": "B站",
      "platform_class": "platform-bilibili",
      "author": "映山学长税务专硕433",
      "url": "http://www.bilibili.com/video/av322096277",
      "time": "2026-04-29 00:29",
      "heat": 3238,
      "discussions": "23",
      "tags": [],
      "isHot": false,
      "detail": "<p>【史诗级提分干货】全网最好理解的国际税收框架——大白话的国际税收||433||国际税收||税务专硕||经验||方法||</p>"
    },
    {
      "id": "8257b0b35fb4",
      "title": "2025年新版电子税务局税务注销全流程",
      "summary": "-",
      "source": "B站",
      "platform_class": "platform-bilibili",
      "author": "晗妈会计",
      "url": "http://www.bilibili.com/video/av114640730195595",
      "time": "2026-04-29 00:29",
      "heat": 3229,
      "discussions": "125",
      "tags": [],
      "isHot": false,
      "detail": "<p>-</p>"
    },
    {
      "id": "bf17a2401eb1",
      "title": "T4. 一口气了解跨境税务规则！为什么需要双边税务协议？避税天堂为何能避税？科技巨头的零税魔术是如何运作的？",
      "summary": "你有没有想过，当一笔钱跨越国界，到底该向谁交税？为什么苹果、谷歌的实际税率能远低于美国法定税率？这背后，远不止“避税”这么简单。\n本期视频，我们将为你系统拆解 “跨境税务” 的完整知识版图：\n第一部分：规则的基石 —— 双边税收协定\n国家之间如何谈判，才能避免对同一笔收入“双重征税”？理解这份国家间的“税收合约”，是看懂所有跨国商业活动的第一课。\n第二部分：资本的舞台 —— 避税天堂的逻辑\n开曼群",
      "source": "B站",
      "platform_class": "platform-bilibili",
      "author": "财税解码",
      "url": "http://www.bilibili.com/video/av115728430663446",
      "time": "2026-04-29 00:29",
      "heat": 3101,
      "discussions": "51",
      "tags": [],
      "isHot": false,
      "detail": "<p>你有没有想过，当一笔钱跨越国界，到底该向谁交税？为什么苹果、谷歌的实际税率能远低于美国法定税率？这背后，远不止“避税”这么简单。\n本期视频，我们将为你系统拆解 “跨境税务” 的完整知识版图：\n第一部分：规则的基石 —— 双边税收协定\n国家之间如何谈判，才能避免对同一笔收入“双重征税”？理解这份国家间的“税收合约”，是看懂所有跨国商业活动的第一课。\n第二部分：资本的舞台 —— 避税天堂的逻辑\n开曼群</p>"
    },
    {
      "id": "dba05acd7af8",
      "title": "华信信托、四川信托、安信信托、民生信托爆雷事件之反思与启示",
      "summary": "第100期：华信信托、四川信托、安信信托、民生信托爆雷事件之反思与启示",
      "source": "B站",
      "platform_class": "platform-bilibili",
      "author": "中队长讲投资",
      "url": "http://www.bilibili.com/video/av419305848",
      "time": "2026-04-29 00:29",
      "heat": 2024,
      "discussions": "38",
      "tags": [],
      "isHot": false,
      "detail": "<p>第100期：华信信托、四川信托、安信信托、民生信托爆雷事件之反思与启示</p>"
    },
    {
      "id": "1937a06033af",
      "title": "房产税、土地使用税在电子税务局怎么采集？",
      "summary": "-",
      "source": "B站",
      "platform_class": "platform-bilibili",
      "author": "晗妈会计",
      "url": "http://www.bilibili.com/video/av113208526440945",
      "time": "2026-04-29 00:29",
      "heat": 1216,
      "discussions": "23",
      "tags": [],
      "isHot": false,
      "detail": "<p>-</p>"
    },
    {
      "id": "399332c051f8",
      "title": "PropFirm 收入与税务申报",
      "summary": "下半年很多人都遇到的补税情况，了解清楚，不罚款。",
      "source": "B站",
      "platform_class": "platform-bilibili",
      "author": "昵称被注册的-小水果",
      "url": "http://www.bilibili.com/video/av115705143889829",
      "time": "2026-04-29 00:29",
      "heat": 1053,
      "discussions": "110",
      "tags": [],
      "isHot": false,
      "detail": "<p>下半年很多人都遇到的补税情况，了解清楚，不罚款。</p>"
    },
    {
      "id": "b3330fdc3337",
      "title": "「影刀RPA」 财务机器人：税务局自动纳税申报",
      "summary": "如需在企业里使用该自动化应用，填写申请：https://ying-dao.feishu.cn/share/base/form/shrcnhAcnPkKTixfcWiVjqQ2uFh\n加入RPA学习群：https://mp.weixin.qq.com/s/5BLHkJq6Tk4Z-XxLtsjXOw",
      "source": "B站",
      "platform_class": "platform-bilibili",
      "author": "影刀RPA",
      "url": "http://www.bilibili.com/video/av647824949",
      "time": "2026-04-29 00:29",
      "heat": 941,
      "discussions": "14",
      "tags": [],
      "isHot": false,
      "detail": "<p>如需在企业里使用该自动化应用，填写申请：https://ying-dao.feishu.cn/share/base/form/shrcnhAcnPkKTixfcWiVjqQ2uFh\n加入RPA学习群：https://mp.weixin.qq.com/s/5BLHkJq6Tk4Z-XxLtsjXOw</p>"
    },
    {
      "id": "cc80469679a7",
      "title": "【海外家族信托】第十六讲 P1 信托如何影响税务？",
      "summary": "本节主要讲述信托在税收优化上的应用。请在视频中找到以下问题的答案：\n1、对于全球化布局的高净值人士，如何判定TA的税务居民身份？\n2、如何判断一个海外公司的税务居民身份？\n3、在税收上，居住管辖权和收入来源管辖权分别指什么？\n4、在不同的环节上，信托如何为您的税收作出优化？",
      "source": "B站",
      "platform_class": "platform-bilibili",
      "author": "施炳",
      "url": "http://www.bilibili.com/video/av828119337",
      "time": "2026-04-29 00:29",
      "heat": 877,
      "discussions": "11",
      "tags": [],
      "isHot": false,
      "detail": "<p>本节主要讲述信托在税收优化上的应用。请在视频中找到以下问题的答案：\n1、对于全球化布局的高净值人士，如何判定TA的税务居民身份？\n2、如何判断一个海外公司的税务居民身份？\n3、在税收上，居住管辖权和收入来源管辖权分别指什么？\n4、在不同的环节上，信托如何为您的税收作出优化？</p>"
    },
    {
      "id": "80e450e68203",
      "title": "【李建伟7.16】锐评公司传承与家族信托（热点事件解读）",
      "summary": "此次讲座的主讲人为李建伟老师（中国政法大学教授、博士生导师）\n\n本讲座著作权归讲座主讲人及主办方，本讲座仅供个人学习参考之用，请勿作任何商业用途，如有不当之处，敬请告知修改、更正或删除。投稿为自制是为了防止二次搬运添加水印，敬请理解。",
      "source": "B站",
      "platform_class": "platform-bilibili",
      "author": "小付酱Lawyer",
      "url": "http://www.bilibili.com/video/av114867189123936",
      "time": "2026-04-29 00:29",
      "heat": 851,
      "discussions": "4",
      "tags": [],
      "isHot": false,
      "detail": "<p>此次讲座的主讲人为李建伟老师（中国政法大学教授、博士生导师）\n\n本讲座著作权归讲座主讲人及主办方，本讲座仅供个人学习参考之用，请勿作任何商业用途，如有不当之处，敬请告知修改、更正或删除。投稿为自制是为了防止二次搬运添加水印，敬请理解。</p>"
    },
    {
      "id": "dd28d4f92ba8",
      "title": "5.1.11 企业取得境外所得计税时的抵免",
      "summary": "最新会计职称考试《经济法基础》高频考点分享与经典例题解析，为了帮助广大考生高效备考，高顿老师手把手带你突破难关，快学起来吧！",
      "source": "B站",
      "platform_class": "platform-bilibili",
      "author": "高顿教育",
      "url": "http://www.bilibili.com/video/av540356507",
      "time": "2026-04-29 00:29",
      "heat": 693,
      "discussions": "3",
      "tags": [],
      "isHot": false,
      "detail": "<p>最新会计职称考试《经济法基础》高频考点分享与经典例题解析，为了帮助广大考生高效备考，高顿老师手把手带你突破难关，快学起来吧！</p>"
    },
    {
      "id": "92a57161058a",
      "title": "【网中网新版机器人】税务会计报税流程/第三集",
      "summary": "此视频适用于【网中网企业数字化经营管理与决策平台】，以12月单月且年终业务进行财税讲解，本视频主讲税务会计次月税费申报，月末运营结束后进行财税流程可参考该教程，此视频为独创，目前仅B站首发，其他平台均为盗版，希望帮到你们。\n第一集跳转入口（计提工资、制造费用分配）：https://www.bilibili.com/video/BV13GW9z7Eaa/?vd_source=d5526546724c",
      "source": "B站",
      "platform_class": "platform-bilibili",
      "author": "财务决策李锦堂",
      "url": "http://www.bilibili.com/video/av115412129810601",
      "time": "2026-04-29 00:29",
      "heat": 670,
      "discussions": "4",
      "tags": [],
      "isHot": false,
      "detail": "<p>此视频适用于【网中网企业数字化经营管理与决策平台】，以12月单月且年终业务进行财税讲解，本视频主讲税务会计次月税费申报，月末运营结束后进行财税流程可参考该教程，此视频为独创，目前仅B站首发，其他平台均为盗版，希望帮到你们。\n第一集跳转入口（计提工资、制造费用分配）：https://www.bilibili.com/video/BV13GW9z7Eaa/?vd_source=d5526546724c</p>"
    },
    {
      "id": "ab9bcb422773",
      "title": "境外所得抵免专题（全）",
      "summary": "上课玲一金玲财税课堂",
      "source": "B站",
      "platform_class": "platform-bilibili",
      "author": "财税会计实操UP主",
      "url": "http://www.bilibili.com/video/av39192226",
      "time": "2026-04-29 00:29",
      "heat": 577,
      "discussions": "12",
      "tags": [],
      "isHot": false,
      "detail": "<p>上课玲一金玲财税课堂</p>"
    },
    {
      "id": "cf4e6dbf960e",
      "title": "433|国际重复征税含义＋分类＋抵免法（全额限额＋直接间接）(自用)",
      "summary": "433|国际重复征税含义＋分类＋抵免法（全额限额＋直接间接）(自用)",
      "source": "B站",
      "platform_class": "platform-bilibili",
      "author": "史今的迷妹123",
      "url": "http://www.bilibili.com/video/av112959334385917",
      "time": "2026-04-29 00:29",
      "heat": 552,
      "discussions": "15",
      "tags": [],
      "isHot": false,
      "detail": "<p>433|国际重复征税含义＋分类＋抵免法（全额限额＋直接间接）(自用)</p>"
    },
    {
      "id": "fe0f1606c180",
      "title": "击穿信托？ 家族信托红线在哪里？",
      "summary": "击穿信托？ 家族信托红线在哪里？",
      "source": "B站",
      "platform_class": "platform-bilibili",
      "author": "李建伟商法",
      "url": "http://www.bilibili.com/video/av113384251003909",
      "time": "2026-04-29 00:29",
      "heat": 527,
      "discussions": "1",
      "tags": [],
      "isHot": false,
      "detail": "<p>击穿信托？ 家族信托红线在哪里？</p>"
    },
    {
      "id": "275e35f8bd20",
      "title": "CRS， 收到税务局通知，境外炒股，到底要补多少钱？别猜了，3分钟算清楚！｜财富种植园",
      "summary": "收到稅務局通知心慌慌？境外資產補稅到底要補多少錢？\n別再自己瞎猜了！這期視頻手把手教你：上傳月結單，AI 3 分鐘幫你算得明明白白！\n很多人最近都收到了要求「境外所得自查」的短信或電話，第一反應都是：\n「我這幾年美股/港股到底賺了多少？」\n「虧損的部分能不能扣除？」\n「稅率是多少？要怎麼寫申報材料？」\n自己算，賬單幾百頁，先進先出（FIFO）算法算到頭大；請會計，收費貴不說，資料往來還麻煩。\n本期",
      "source": "B站",
      "platform_class": "platform-bilibili",
      "author": "财富种植园",
      "url": "http://www.bilibili.com/video/av115896269932539",
      "time": "2026-04-29 00:29",
      "heat": 466,
      "discussions": "12",
      "tags": [],
      "isHot": false,
      "detail": "<p>收到稅務局通知心慌慌？境外資產補稅到底要補多少錢？\n別再自己瞎猜了！這期視頻手把手教你：上傳月結單，AI 3 分鐘幫你算得明明白白！\n很多人最近都收到了要求「境外所得自查」的短信或電話，第一反應都是：\n「我這幾年美股/港股到底賺了多少？」\n「虧損的部分能不能扣除？」\n「稅率是多少？要怎麼寫申報材料？」\n自己算，賬單幾百頁，先進先出（FIFO）算法算到頭大；請會計，收費貴不說，資料往來還麻煩。\n本期</p>"
    },
    {
      "id": "5e6e60953b00",
      "title": "取得境外所得如何通过个税APP申报个人所得税(浙江税务)",
      "summary": "宝子们！5月29日还没报境外所得个税的注意啦！今年起用个税APP就能搞定，超省心～\n\n哪些算境外所得？像海外工资、境外股息、转让境外房产等9类收入都要报，具体看财政部2020年3号公告！记得每年3月1日-6月30日申报，现在只剩最后几天，别漏了！\n\n操作超简单：打开个税APP，首页搜“年度汇算（取得境外所得适用）”，填境内外综合所得、经营所得，利息股息等分类所得单独填；境外已缴税别慌，系统自动算抵",
      "source": "B站",
      "platform_class": "platform-bilibili",
      "author": "税务师木木",
      "url": "http://www.bilibili.com/video/av114588066516202",
      "time": "2026-04-29 00:29",
      "heat": 452,
      "discussions": "3",
      "tags": [],
      "isHot": false,
      "detail": "<p>宝子们！5月29日还没报境外所得个税的注意啦！今年起用个税APP就能搞定，超省心～\n\n哪些算境外所得？像海外工资、境外股息、转让境外房产等9类收入都要报，具体看财政部2020年3号公告！记得每年3月1日-6月30日申报，现在只剩最后几天，别漏了！\n\n操作超简单：打开个税APP，首页搜“年度汇算（取得境外所得适用）”，填境内外综合所得、经营所得，利息股息等分类所得单独填；境外已缴税别慌，系统自动算抵</p>"
    },
    {
      "id": "e1fef66ee54f",
      "title": "“走出去”企业常见境外税收涉税风险及防范",
      "summary": "“走出去”企业常见境外税收涉税风险及防范",
      "source": "B站",
      "platform_class": "platform-bilibili",
      "author": "会计学习吧",
      "url": "http://www.bilibili.com/video/av113221059021266",
      "time": "2026-04-29 00:29",
      "heat": 445,
      "discussions": "2",
      "tags": [],
      "isHot": false,
      "detail": "<p>“走出去”企业常见境外税收涉税风险及防范</p>"
    },
    {
      "id": "1a4906145af4",
      "title": "湾区渣男5-信托财富博弈背后的深度宅斗",
      "summary": "-",
      "source": "B站",
      "platform_class": "platform-bilibili",
      "author": "狗驲的虎扑",
      "url": "http://www.bilibili.com/video/av114147916255938",
      "time": "2026-04-29 00:29",
      "heat": 242,
      "discussions": "16",
      "tags": [],
      "isHot": false,
      "detail": "<p>-</p>"
    },
    {
      "id": "9b3b3b0c0e78",
      "title": "CRS: 2026 境外投資稅務申報教學：AI 自動計算美股/港股投資所得，個人所得稅 APP 報稅全攻略",
      "summary": "💡 境外投資報稅太複雜？請會計太貴？本視頻手把手教你使用最新的 AI 稅務工具，自動化處理你的券商月報表、年報表，一鍵生成符合審計要求的 Excel 底稿，讓你在個人所得稅 APP 申報時輕鬆無憂！\n\n📌 視頻核心內容：\n00:00 工具背景與核心價值（省時、省錢、防風險）\n01:08 免費體驗額度獲取與定價方案\n02:00 邀請碼機制：雙方均可獲得 50% 額外額度\n02:40 數據安全保障：本",
      "source": "B站",
      "platform_class": "platform-bilibili",
      "author": "财富种植园",
      "url": "http://www.bilibili.com/video/av116132493133650",
      "time": "2026-04-29 00:29",
      "heat": 227,
      "discussions": "14",
      "tags": [],
      "isHot": false,
      "detail": "<p>💡 境外投資報稅太複雜？請會計太貴？本視頻手把手教你使用最新的 AI 稅務工具，自動化處理你的券商月報表、年報表，一鍵生成符合審計要求的 Excel 底稿，讓你在個人所得稅 APP 申報時輕鬆無憂！\n\n📌 視頻核心內容：\n00:00 工具背景與核心價值（省時、省錢、防風險）\n01:08 免費體驗額度獲取與定價方案\n02:00 邀請碼機制：雙方均可獲得 50% 額外額度\n02:40 數據安全保障：本</p>"
    },
    {
      "id": "923c9bcb2d25",
      "title": "中国开启全球征税时代！境外收入恶意逃税可能要坐牢",
      "summary": "中国税务居民在海外赚了钱，都需要向中国税务机关报税。如果不报税被查出来，则将面临补税+罚款，恶意逃税者还将承担刑事责任，牢饭供应。\n \n本来境外收入报税交税这件事，喊了很多年，但因为技术原因并未普及开来。但是现在，技术的进步与国际合作的紧密，让心存侥幸者无所遁形。\n \n近日，中国的浙江、山东、上海、湖北四地税务机关同步发布公告，针对中国境内居民的境外收入申报问题开展集中核查。\n \n通过大数据识别出",
      "source": "B站",
      "platform_class": "platform-bilibili",
      "author": "无忧启程移民",
      "url": "http://www.bilibili.com/video/av114420143494580",
      "time": "2026-04-29 00:29",
      "heat": 194,
      "discussions": "8",
      "tags": [
        "全球征税"
      ],
      "isHot": false,
      "detail": "<p>中国税务居民在海外赚了钱，都需要向中国税务机关报税。如果不报税被查出来，则将面临补税+罚款，恶意逃税者还将承担刑事责任，牢饭供应。\n \n本来境外收入报税交税这件事，喊了很多年，但因为技术原因并未普及开来。但是现在，技术的进步与国际合作的紧密，让心存侥幸者无所遁形。\n \n近日，中国的浙江、山东、上海、湖北四地税务机关同步发布公告，针对中国境内居民的境外收入申报问题开展集中核查。\n \n通过大数据识别出</p>"
    },
    {
      "id": "c0123dc6b505",
      "title": "分公司都需要申报哪些税零申报全流程",
      "summary": "-",
      "source": "B站",
      "platform_class": "platform-bilibili",
      "author": "晗妈会计",
      "url": "http://www.bilibili.com/video/av114822914050754",
      "time": "2026-04-29 00:29",
      "heat": 177,
      "discussions": "1",
      "tags": [],
      "isHot": false,
      "detail": "<p>-</p>"
    },
    {
      "id": "aa434602e9d3",
      "title": "20250609(CRS解读、跨境财富管理（保险，信托）及税务解析",
      "summary": "20250609(CRS解读、跨境财富管理（保险，信托）及税务解析",
      "source": "B站",
      "platform_class": "platform-bilibili",
      "author": "视频分享助手",
      "url": "http://www.bilibili.com/video/av114668077057406",
      "time": "2026-04-29 00:29",
      "heat": 156,
      "discussions": "1",
      "tags": [],
      "isHot": false,
      "detail": "<p>20250609(CRS解读、跨境财富管理（保险，信托）及税务解析</p>"
    },
    {
      "id": "cdaf0da16f01",
      "title": "【1/3】家族信托、家庭信托、保险金信托介绍",
      "summary": "茫茫尘世中一个伴读小书童，温酒与你共同成长~",
      "source": "B站",
      "platform_class": "platform-bilibili",
      "author": "温酒醉琉璃",
      "url": "http://www.bilibili.com/video/av1202068801",
      "time": "2026-04-29 00:29",
      "heat": 112,
      "discussions": "4",
      "tags": [],
      "isHot": false,
      "detail": "<p>茫茫尘世中一个伴读小书童，温酒与你共同成长~</p>"
    },
    {
      "id": "ce22260cbe14",
      "title": "怎么设立家族信托？家族信托常见问答-（家族信托五）",
      "summary": "怎么设立家族信托？家族信托常见问答-（家族信托五）",
      "source": "B站",
      "platform_class": "platform-bilibili",
      "author": "Miss杨聊财富管理",
      "url": "http://www.bilibili.com/video/av501960844",
      "time": "2026-04-29 00:29",
      "heat": 101,
      "discussions": "1",
      "tags": [],
      "isHot": false,
      "detail": "<p>怎么设立家族信托？家族信托常见问答-（家族信托五）</p>"
    },
    {
      "id": "41e9712adacf",
      "title": "2025年境外收入在国内缴税的方法",
      "summary": "2025年境外收入在国内缴税的方法",
      "source": "B站",
      "platform_class": "platform-bilibili",
      "author": "淡定的飞马",
      "url": "http://www.bilibili.com/video/av116228072934922",
      "time": "2026-04-29 00:29",
      "heat": 97,
      "discussions": "8",
      "tags": [],
      "isHot": false,
      "detail": "<p>2025年境外收入在国内缴税的方法</p>"
    },
    {
      "id": "565780d22a57",
      "title": "内地信托vs香港信托，三个区别惊呆你！",
      "summary": "对于很多高净值人士来说，在海外进行资产配置是非常有必要，重新开关一年的香港，也是大多数人离岸配置的第一站。\n\n在的财富逐渐积累的情况下，不管内地还是离岸，信托一定是富豪们热衷的选择之一。和内地独具特色会暴雷的信托理财不同的是，在欧美国家和香港等地，信托其实就只是一种财富传承和遗产规划的法律工具而已。\n\n那今天给大家科普一下国内信托和香港的信托的是三个不同区别。",
      "source": "B站",
      "platform_class": "platform-bilibili",
      "author": "托雷教你避雷",
      "url": "http://www.bilibili.com/video/av1752965688",
      "time": "2026-04-29 00:29",
      "heat": 92,
      "discussions": "1",
      "tags": [],
      "isHot": false,
      "detail": "<p>对于很多高净值人士来说，在海外进行资产配置是非常有必要，重新开关一年的香港，也是大多数人离岸配置的第一站。\n\n在的财富逐渐积累的情况下，不管内地还是离岸，信托一定是富豪们热衷的选择之一。和内地独具特色会暴雷的信托理财不同的是，在欧美国家和香港等地，信托其实就只是一种财富传承和遗产规划的法律工具而已。\n\n那今天给大家科普一下国内信托和香港的信托的是三个不同区别。</p>"
    },
    {
      "id": "c7339402554c",
      "title": "Ozon无货源卖家税务指南：无票收入怎么报？3步搞定不踩坑",
      "summary": "Ozon无货源/一件代发卖家总愁无票收入怎么报税、做账？其实按规则处理很简单！\n这份指南讲清：\n无票收入（Ozon回款）需填增值税“未开票收入”栏，按季度回款如实申报\n无票支出单次≤500元可凭订单入账，超500元需调整企业所得税\n更有小额采购做账要点和风险提醒，新手按这份攻略做，合规申报不漏税，轻松搞定电商税！",
      "source": "B站",
      "platform_class": "platform-bilibili",
      "author": "眼底heshan",
      "url": "http://www.bilibili.com/video/av115466890645518",
      "time": "2026-04-29 00:29",
      "heat": 90,
      "discussions": "2",
      "tags": [],
      "isHot": false,
      "detail": "<p>Ozon无货源/一件代发卖家总愁无票收入怎么报税、做账？其实按规则处理很简单！\n这份指南讲清：\n无票收入（Ozon回款）需填增值税“未开票收入”栏，按季度回款如实申报\n无票支出单次≤500元可凭订单入账，超500元需调整企业所得税\n更有小额采购做账要点和风险提醒，新手按这份攻略做，合规申报不漏税，轻松搞定电商税！</p>"
    },
    {
      "id": "0e8e2fa17e4b",
      "title": "《如何利用海外家族信托做好财富传承》",
      "summary": "《如何利用海外家族信托做好财富传承》",
      "source": "B站",
      "platform_class": "platform-bilibili",
      "author": "侨外出国",
      "url": "http://www.bilibili.com/video/av947063286",
      "time": "2026-04-29 00:29",
      "heat": 88,
      "discussions": "1",
      "tags": [],
      "isHot": false,
      "detail": "<p>《如何利用海外家族信托做好财富传承》</p>"
    },
    {
      "id": "4d5d678ff878",
      "title": "什么是信托通道业务？如何核实信托产品的真实性？",
      "summary": "-",
      "source": "B站",
      "platform_class": "platform-bilibili",
      "author": "刘sir聊信托",
      "url": "http://www.bilibili.com/video/av701706157",
      "time": "2026-04-29 00:29",
      "heat": 85,
      "discussions": "0",
      "tags": [],
      "isHot": false,
      "detail": "<p>-</p>"
    },
    {
      "id": "f42784781134",
      "title": "龙湖地产吴亚军的未雨绸缪#信托 #家族信托#家族信托架构 #龙湖地产 #离岸信托",
      "summary": "-",
      "source": "B站",
      "platform_class": "platform-bilibili",
      "author": "光辉的长期主义",
      "url": "http://www.bilibili.com/video/av572415076",
      "time": "2026-04-29 00:29",
      "heat": 69,
      "discussions": "1",
      "tags": [],
      "isHot": false,
      "detail": "<p>-</p>"
    },
    {
      "id": "8047b25a3460",
      "title": "海外资产申报 - 加拿大非税务居民的利与弊",
      "summary": "如果您的大部分收入来自海外，应该如何定义自己的居民身份呢？\n本期将为您深度解析加拿大非税务局民的利与弊。\n在什么情况下您可以被定义为非税务局民？\n只有非税务局民才能不申报海外资产你知道吗？\n非税务局民有什么弊端呢",
      "source": "B站",
      "platform_class": "platform-bilibili",
      "author": "诚信理财金融频道",
      "url": "http://www.bilibili.com/video/av800072813",
      "time": "2026-04-29 00:29",
      "heat": 67,
      "discussions": "1",
      "tags": [
        "海外资产申报"
      ],
      "isHot": false,
      "detail": "<p>如果您的大部分收入来自海外，应该如何定义自己的居民身份呢？\n本期将为您深度解析加拿大非税务局民的利与弊。\n在什么情况下您可以被定义为非税务局民？\n只有非税务局民才能不申报海外资产你知道吗？\n非税务局民有什么弊端呢</p>"
    },
    {
      "id": "180b1c3c1059",
      "title": "谁是CRS全球征税最最最危险的？最容易暴雷的是哪些群体？陈震、薇娅他们是如何翻车的？",
      "summary": "谁是CRS全球征税最最最危险的？最容易暴雷的是哪些群体？陈震、薇娅他们是如何翻车的？",
      "source": "B站",
      "platform_class": "platform-bilibili",
      "author": "WilliamLC移民",
      "url": "http://www.bilibili.com/video/av116471443229215",
      "time": "2026-04-29 00:29",
      "heat": 65,
      "discussions": "8",
      "tags": [
        "全球征税"
      ],
      "isHot": false,
      "detail": "<p>谁是CRS全球征税最最最危险的？最容易暴雷的是哪些群体？陈震、薇娅他们是如何翻车的？</p>"
    },
    {
      "id": "67d827d9d1e8",
      "title": "税局提醒：4月起，申报表中未开票收入都应该这样操作！#会计 #财务 #会计实操 #未开票收入 #报税",
      "summary": "税局提醒：4月起，申报表中未开票收入都应该这样操作！#会计 #财务 #会计实操 #未开票收入 #报税",
      "source": "B站",
      "platform_class": "platform-bilibili",
      "author": "木子会计吖",
      "url": "http://www.bilibili.com/video/av116408059104438",
      "time": "2026-04-29 00:29",
      "heat": 60,
      "discussions": "4",
      "tags": [],
      "isHot": false,
      "detail": "<p>税局提醒：4月起，申报表中未开票收入都应该这样操作！#会计 #财务 #会计实操 #未开票收入 #报税</p>"
    },
    {
      "id": "a7cb298c7c25",
      "title": "香港信托和内地信托有什么区别?委托人会承担什么风险?",
      "summary": "香港信托和内地信托有什么区别?委托人会承担什么风险?",
      "source": "B站",
      "platform_class": "platform-bilibili",
      "author": "小龙哥说基金",
      "url": "http://www.bilibili.com/video/av1402468848",
      "time": "2026-04-29 00:29",
      "heat": 41,
      "discussions": "1",
      "tags": [],
      "isHot": false,
      "detail": "<p>香港信托和内地信托有什么区别?委托人会承担什么风险?</p>"
    },
    {
      "id": "6d29bf94a054",
      "title": "海外信托神话破灭,藏钱时代落幕",
      "summary": "-",
      "source": "B站",
      "platform_class": "platform-bilibili",
      "author": "寰宇财经说",
      "url": "http://www.bilibili.com/video/av116481593445009",
      "time": "2026-04-29 00:29",
      "heat": 23,
      "discussions": "0",
      "tags": [
        "海外信托"
      ],
      "isHot": false,
      "detail": "<p>-</p>"
    },
    {
      "id": "bb930d2c3a7e",
      "title": "【直播回放】肖兴利 | 境外资产追回的法律实务问题",
      "summary": "欢迎收看涉外刑事法律服务系列课程~ \n本期主要内容：聚焦我国境外资产追回的法律制度，结合典型案例详细拆解缺席审判程序、违法所得没收程序、境外民事诉讼程序、犯罪资产分享制度等四种程序的法律依据、规则内容及优势不足，在提出完善建议的同时，探讨了境外追逃追赃实务中的律师作用及业务机会。\n每周三14:00-15:30，盈科精英教育B站直播间，与您不见不散！",
      "source": "B站",
      "platform_class": "platform-bilibili",
      "author": "盈科精英教育",
      "url": "http://www.bilibili.com/video/av115388322939530",
      "time": "2026-04-29 00:29",
      "heat": 22,
      "discussions": "0",
      "tags": [],
      "isHot": false,
      "detail": "<p>欢迎收看涉外刑事法律服务系列课程~ \n本期主要内容：聚焦我国境外资产追回的法律制度，结合典型案例详细拆解缺席审判程序、违法所得没收程序、境外民事诉讼程序、犯罪资产分享制度等四种程序的法律依据、规则内容及优势不足，在提出完善建议的同时，探讨了境外追逃追赃实务中的律师作用及业务机会。\n每周三14:00-15:30，盈科精英教育B站直播间，与您不见不散！</p>"
    },
    {
      "id": "adf3b889b599",
      "title": "高净值境外资产必看3条新规",
      "summary": "#高净值境外资产必看3条新规！\n“钱出去、钱在境外、钱回来”三关\n\n- 好些朋友问我跨境保单、境外投资怎么看[让我看看]\n- 今天用《金融法（草案）》的角度，一条视频跟大家讲明白😉",
      "source": "B站",
      "platform_class": "platform-bilibili",
      "author": "miss_chiuchiu",
      "url": "http://www.bilibili.com/video/av116460303160803",
      "time": "2026-04-29 00:29",
      "heat": 13,
      "discussions": "0",
      "tags": [],
      "isHot": false,
      "detail": "<p>#高净值境外资产必看3条新规！\n“钱出去、钱在境外、钱回来”三关\n\n- 好些朋友问我跨境保单、境外投资怎么看[让我看看]\n- 今天用《金融法（草案）》的角度，一条视频跟大家讲明白😉</p>"
    },
    {
      "id": "e17c5a93c73a",
      "title": "海外工程造价实务-马来西亚①",
      "summary": "《海外工程造价实务》视频版。本节为马来西亚的第一集。结合相关规范，从底层逻辑解决实务问题。\n\n作者段然：中华人民共和国法律职业资格、联合王国皇家特许测量师国际专业资格、高级工程师、皇家特许工料测量师QS、注册一级造价工程师、注册一级建造师、皇家特许测量师学会专业会员MRICS、中国建设工程造价管理协会CCEA会员、Autodesk认证授权讲师。",
      "source": "B站",
      "platform_class": "platform-bilibili",
      "author": "小段工坊",
      "url": "http://www.bilibili.com/video/av116481878657756",
      "time": "2026-04-29 00:29",
      "heat": 11,
      "discussions": "0",
      "tags": [],
      "isHot": false,
      "detail": "<p>《海外工程造价实务》视频版。本节为马来西亚的第一集。结合相关规范，从底层逻辑解决实务问题。\n\n作者段然：中华人民共和国法律职业资格、联合王国皇家特许测量师国际专业资格、高级工程师、皇家特许工料测量师QS、注册一级造价工程师、注册一级建造师、皇家特许测量师学会专业会员MRICS、中国建设工程造价管理协会CCEA会员、Autodesk认证授权讲师。</p>"
    },
    {
      "id": "6580ad942e58",
      "title": "科沃斯正面临严峻的专利考验。从德国市场的禁售令，到国内5月即将开庭的侵权诉讼，专利战火已从海外蔓延至本土。",
      "summary": "-",
      "source": "B站",
      "platform_class": "platform-bilibili",
      "author": "新纪元Edge",
      "url": "http://www.bilibili.com/video/av116482818251435",
      "time": "2026-04-29 00:29",
      "heat": 9,
      "discussions": "0",
      "tags": [],
      "isHot": false,
      "detail": "<p>-</p>"
    },
    {
      "id": "55b3408b7d7f",
      "title": "2026年最新，抖店商家税务申报全流程指南",
      "summary": "2026年最新，抖店商家税务申报全流程指南",
      "source": "B站",
      "platform_class": "platform-bilibili",
      "author": "晓涛聊电商财税",
      "url": "http://www.bilibili.com/video/av116342124452737",
      "time": "2026-04-29 00:29",
      "heat": 8,
      "discussions": "0",
      "tags": [],
      "isHot": false,
      "detail": "<p>2026年最新，抖店商家税务申报全流程指南</p>"
    },
    {
      "id": "0f6d4e4e2f31",
      "title": "紧急必看！CG仓库存压钱、流量暴跌？Wayfair官方免费“清库存+抢流量”神器，一键盘活全店SKU！",
      "summary": "⚠️CG仓卖家全员预警：你的库存，正在偷偷吃掉你的净利润！\n❓是不是最近越备货越慌？\n❗货压在CG仓动销慢、周转卡死；\n❗长期堆仓马上要叠加高额阶梯仓储费；\n❗新品没卡位、老品没流量，想降价又怕打乱全店权重、被判违规比价；\n❗想清货又不敢乱降价，生怕账号风控踩红线……\n别硬扛了！Wayfair早就给合规出路了！\n✌平台官方自带免费利器——CG Markdown 官方合规调价清库工具，不用站外骚操作",
      "source": "B站",
      "platform_class": "platform-bilibili",
      "author": "小明哥wayfair",
      "url": "http://www.bilibili.com/video/av116479815061838",
      "time": "2026-04-29 00:29",
      "heat": 6,
      "discussions": "0",
      "tags": [],
      "isHot": false,
      "detail": "<p>⚠️CG仓卖家全员预警：你的库存，正在偷偷吃掉你的净利润！\n❓是不是最近越备货越慌？\n❗货压在CG仓动销慢、周转卡死；\n❗长期堆仓马上要叠加高额阶梯仓储费；\n❗新品没卡位、老品没流量，想降价又怕打乱全店权重、被判违规比价；\n❗想清货又不敢乱降价，生怕账号风控踩红线……\n别硬扛了！Wayfair早就给合规出路了！\n✌平台官方自带免费利器——CG Markdown 官方合规调价清库工具，不用站外骚操作</p>"
    },
    {
      "id": "0fcd143d7844",
      "title": "第二十期：境外财产如何继承？",
      "summary": "越来越多的人在海外有房产、有存款、有投资。人去世后，这些远在异国他乡的财产，该怎么继承？会不会被“充公”？\n涉外继承，核心是解决两个问题：用哪国法律？走什么程序？第一，法律适用——‘不动产’和‘动产’区别对待。第二，实务流程——公证书是‘通行证’。之后，你或委托的境外律师，要拿着这些认证过的文件，到财产所在地的法院或登记机构，按照当地的法律程序办理继承手续。每个国家的流程和税费都不同，非常复杂。\n",
      "source": "B站",
      "platform_class": "platform-bilibili",
      "author": "天幕油菜人",
      "url": "http://www.bilibili.com/video/av116480888799410",
      "time": "2026-04-29 00:29",
      "heat": 3,
      "discussions": "0",
      "tags": [],
      "isHot": false,
      "detail": "<p>越来越多的人在海外有房产、有存款、有投资。人去世后，这些远在异国他乡的财产，该怎么继承？会不会被“充公”？\n涉外继承，核心是解决两个问题：用哪国法律？走什么程序？第一，法律适用——‘不动产’和‘动产’区别对待。第二，实务流程——公证书是‘通行证’。之后，你或委托的境外律师，要拿着这些认证过的文件，到财产所在地的法院或登记机构，按照当地的法律程序办理继承手续。每个国家的流程和税费都不同，非常复杂。\n</p>"
    },
    {
      "id": "ccf65599763b",
      "title": "境外资产安全",
      "summary": "境外资产安全",
      "source": "B站",
      "platform_class": "platform-bilibili",
      "author": "新马buff",
      "url": "http://www.bilibili.com/video/av115070965194751",
      "time": "2026-04-29 00:29",
      "heat": 1,
      "discussions": "0",
      "tags": [],
      "isHot": false,
      "detail": "<p>境外资产安全</p>"
    },
    {
      "id": "39d2eeb961ea",
      "title": "海外税制讲解跨境税务筹划多国及香港税制解析完整版",
      "summary": "海外税制讲解跨境税务筹划多国及香港税制解析完整版",
      "source": "B站",
      "platform_class": "platform-bilibili",
      "author": "账号已注销",
      "url": "http://www.bilibili.com/video/av116448559104548",
      "time": "2026-04-29 00:29",
      "heat": 0,
      "discussions": "0",
      "tags": [],
      "isHot": false,
      "detail": "<p>海外税制讲解跨境税务筹划多国及香港税制解析完整版</p>"
    }
  ]
}