{
  "updated_at": "2026-04-06T20:03:22.684641+08:00",
  "count": 57,
  "topics": [
    {
      "id": "d9379aeeb507",
      "title": "全网最简单境外支付银行卡科普攻略指南！",
      "summary": "感谢观看！\n制作不易 喜欢的话记得关注！\n感谢你的支持！",
      "source": "B站",
      "platform_class": "platform-bilibili",
      "author": "临客SteelyLink",
      "url": "http://www.bilibili.com/video/av115765592199476",
      "time": "2026-04-06 20:03",
      "heat": 22441,
      "discussions": "491",
      "tags": [],
      "isHot": true,
      "detail": "<p>感谢观看！\n制作不易 喜欢的话记得关注！\n感谢你的支持！</p>"
    },
    {
      "id": "065313e17075",
      "title": "[生息演算] 要塞 征税的选择（隐藏）2人 一遍全收（挑战模式）",
      "summary": "这关蛮简单的，在奇遇旁边，我都没有看见。",
      "source": "B站",
      "platform_class": "platform-bilibili",
      "author": "浅予Asai",
      "url": "http://www.bilibili.com/video/av1250544992",
      "time": "2026-04-06 20:03",
      "heat": 12607,
      "discussions": "61",
      "tags": [],
      "isHot": true,
      "detail": "<p>这关蛮简单的，在奇遇旁边，我都没有看见。</p>"
    },
    {
      "id": "d001143871c7",
      "title": "刘备:那就四六征税 三丁抽一 三国类影视盘点",
      "summary": "只做高画质高质量视频剪辑，感谢充电的UP名单（疯纸丶，尼良辰，Frozen淅淅沥沥，Baba就是那么屌，我要变成欧皇卐，爱疯爱傻，会走的咸鱼，黑色1守望，Wurenpin，扶她奶酪，章鱼串串骚，德玛西亚的正义，微风拂面路随我走，从不投币钟爱白嫖，B站灾变黑龙，xy857，凌沧岚，我的老婆笑起真好看，不杀老幼妹纸，LEのmon，绯月流星，一只爆爆猪，聂黎姿，巨大dj，帅气予墨，JQc257，孙阿中，",
      "source": "B站",
      "platform_class": "platform-bilibili",
      "author": "账号已注销",
      "url": "http://www.bilibili.com/video/av84421841",
      "time": "2026-04-06 20:03",
      "heat": 11600,
      "discussions": "1021",
      "tags": [],
      "isHot": true,
      "detail": "<p>只做高画质高质量视频剪辑，感谢充电的UP名单（疯纸丶，尼良辰，Frozen淅淅沥沥，Baba就是那么屌，我要变成欧皇卐，爱疯爱傻，会走的咸鱼，黑色1守望，Wurenpin，扶她奶酪，章鱼串串骚，德玛西亚的正义，微风拂面路随我走，从不投币钟爱白嫖，B站灾变黑龙，xy857，凌沧岚，我的老婆笑起真好看，不杀老幼妹纸，LEのmon，绯月流星，一只爆爆猪，聂黎姿，巨大dj，帅气予墨，JQc257，孙阿中，</p>"
    },
    {
      "id": "657b1efbca8d",
      "title": "工人被AI替代怎么办？对AI征税！【聂辉华教授】",
      "summary": "最近，河南省老君山风景区因为一个“反常”决定火了。在很多景区都在使用无人机这种高科技运货上山的背景下，该景区明确拒绝用无人机取代挑山工。我的观点：老君山风景区的做法是一个温馨的故事，但不具有普遍性，而且并没有真正解决问题。我在想，有没有一种更好的方案，既能将货品安全送到山顶，同时又能不让年老的挑山工失业，或者得到合理的收入？",
      "source": "B站",
      "platform_class": "platform-bilibili",
      "author": "聂辉华教授",
      "url": "http://www.bilibili.com/video/av115682779990722",
      "time": "2026-04-06 20:03",
      "heat": 8242,
      "discussions": "683",
      "tags": [],
      "isHot": false,
      "detail": "<p>最近，河南省老君山风景区因为一个“反常”决定火了。在很多景区都在使用无人机这种高科技运货上山的背景下，该景区明确拒绝用无人机取代挑山工。我的观点：老君山风景区的做法是一个温馨的故事，但不具有普遍性，而且并没有真正解决问题。我在想，有没有一种更好的方案，既能将货品安全送到山顶，同时又能不让年老的挑山工失业，或者得到合理的收入？</p>"
    },
    {
      "id": "b383472acb8d",
      "title": "大明帝国，全球征税？",
      "summary": "大明帝国，全球征税？",
      "source": "B站",
      "platform_class": "platform-bilibili",
      "author": "历史侦查处",
      "url": "http://www.bilibili.com/video/av115653218535873",
      "time": "2026-04-06 20:03",
      "heat": 7202,
      "discussions": "219",
      "tags": [
        "全球征税"
      ],
      "isHot": false,
      "detail": "<p>大明帝国，全球征税？</p>"
    },
    {
      "id": "2b192ce20290",
      "title": "全球征税时代到来",
      "summary": "全球征税时代到来",
      "source": "B站",
      "platform_class": "platform-bilibili",
      "author": "EverEstate",
      "url": "http://www.bilibili.com/video/av115983377238843",
      "time": "2026-04-06 20:03",
      "heat": 6968,
      "discussions": "342",
      "tags": [
        "全球征税"
      ],
      "isHot": false,
      "detail": "<p>全球征税时代到来</p>"
    },
    {
      "id": "73a95a1ad689",
      "title": "为什么现在才开始大范围的CRS交换，境外收入补税？【David.D】",
      "summary": "为什么现在才开始大范围的CRS交换，境外收入补税？【David.D】",
      "source": "B站",
      "platform_class": "platform-bilibili",
      "author": "David邓博士金融学长",
      "url": "http://www.bilibili.com/video/av114901347472563",
      "time": "2026-04-06 20:03",
      "heat": 6480,
      "discussions": "233",
      "tags": [],
      "isHot": false,
      "detail": "<p>为什么现在才开始大范围的CRS交换，境外收入补税？【David.D】</p>"
    },
    {
      "id": "2d5a676a89d6",
      "title": "博德之门3 用嘴炮说死征税所收费员让它爆金币",
      "summary": "既有经验又有成就，美哉美哉~",
      "source": "B站",
      "platform_class": "platform-bilibili",
      "author": "黯喵喵喵",
      "url": "http://www.bilibili.com/video/av914703020",
      "time": "2026-04-06 20:03",
      "heat": 4449,
      "discussions": "72",
      "tags": [],
      "isHot": false,
      "detail": "<p>既有经验又有成就，美哉美哉~</p>"
    },
    {
      "id": "d11176c34a1c",
      "title": "富人的资产是怎么转移到海外的？【David.D】",
      "summary": "富人的资产是怎么转移到海外的？【David.D】",
      "source": "B站",
      "platform_class": "platform-bilibili",
      "author": "David邓博士金融学长",
      "url": "http://www.bilibili.com/video/av114120099634547",
      "time": "2026-04-06 20:03",
      "heat": 4177,
      "discussions": "37",
      "tags": [],
      "isHot": false,
      "detail": "<p>富人的资产是怎么转移到海外的？【David.D】</p>"
    },
    {
      "id": "22626155e24b",
      "title": "维多利亚3技巧:征税能力-行政机构什么时候能盈利",
      "summary": "这应该就不是个系列了, 纯粹是单独的分享一下一些游戏机制什么的.\n毕竟大妈3具体机制也暂时没人刨代码, 我也懒得去读, 具体机制琢磨什么的我也没别人深入, 还来体系化系列化的讲机制的话就有点那啥了.\n大致的说了下在什么情况修行政机构才会盈利, 以及如何计算每点征税能力带来的税收从而得出什么时候修行政机构才是盈利的.\n哦视频里忘了说钦点是加25%征税能力的...只是一般来讲计算不要依赖这个来算就是了",
      "source": "B站",
      "platform_class": "platform-bilibili",
      "author": "5thYL",
      "url": "http://www.bilibili.com/video/av860686176",
      "time": "2026-04-06 20:03",
      "heat": 4076,
      "discussions": "163",
      "tags": [],
      "isHot": false,
      "detail": "<p>这应该就不是个系列了, 纯粹是单独的分享一下一些游戏机制什么的.\n毕竟大妈3具体机制也暂时没人刨代码, 我也懒得去读, 具体机制琢磨什么的我也没别人深入, 还来体系化系列化的讲机制的话就有点那啥了.\n大致的说了下在什么情况修行政机构才会盈利, 以及如何计算每点征税能力带来的税收从而得出什么时候修行政机构才是盈利的.\n哦视频里忘了说钦点是加25%征税能力的...只是一般来讲计算不要依赖这个来算就是了</p>"
    },
    {
      "id": "d75566dcae79",
      "title": "15年投资老司机，全球资产配置思路",
      "summary": "15年投资老司机，全球资产配置思路",
      "source": "B站",
      "platform_class": "platform-bilibili",
      "author": "杰哥聊理财",
      "url": "http://www.bilibili.com/video/av113762442943418",
      "time": "2026-04-06 20:03",
      "heat": 3564,
      "discussions": "117",
      "tags": [],
      "isHot": false,
      "detail": "<p>15年投资老司机，全球资产配置思路</p>"
    },
    {
      "id": "3c59e0de4e74",
      "title": "频繁收到境外的电话和短信，其实都是软件操作的，别上当",
      "summary": "频繁收到境外的电话和短信，其实都是软件操作的，大家不要接不要点进去更不要上当，远离网络诈骗，健康生活！",
      "source": "B站",
      "platform_class": "platform-bilibili",
      "author": "奔跑的吾先生",
      "url": "http://www.bilibili.com/video/av460078942",
      "time": "2026-04-06 20:03",
      "heat": 3321,
      "discussions": "142",
      "tags": [],
      "isHot": false,
      "detail": "<p>频繁收到境外的电话和短信，其实都是软件操作的，大家不要接不要点进去更不要上当，远离网络诈骗，健康生活！</p>"
    },
    {
      "id": "9c2237f500d3",
      "title": "4月6日：人民币赢了，中国资产避风港！",
      "summary": "-",
      "source": "B站",
      "platform_class": "platform-bilibili",
      "author": "且听龙吟吟吟",
      "url": "http://www.bilibili.com/video/av116353046416270",
      "time": "2026-04-06 20:03",
      "heat": 3106,
      "discussions": "64",
      "tags": [],
      "isHot": false,
      "detail": "<p>-</p>"
    },
    {
      "id": "5d00061ea055",
      "title": "解密税收——为什么要收税？",
      "summary": "解密税收——为什么要收税？",
      "source": "B站",
      "platform_class": "platform-bilibili",
      "author": "杨浦税务",
      "url": "http://www.bilibili.com/video/av715499305",
      "time": "2026-04-06 20:03",
      "heat": 2931,
      "discussions": "17",
      "tags": [],
      "isHot": false,
      "detail": "<p>解密税收——为什么要收税？</p>"
    },
    {
      "id": "28dcc122ff36",
      "title": "梦幻西游：三界功绩兑换境外旗？",
      "summary": "某鱼直播：9372623 \nV：Chreanw  \n接各种资源,接调号,配号  \n企鹅吹水群：638493256",
      "source": "B站",
      "platform_class": "platform-bilibili",
      "author": "Chan简默",
      "url": "http://www.bilibili.com/video/av315990422",
      "time": "2026-04-06 20:03",
      "heat": 2111,
      "discussions": "52",
      "tags": [],
      "isHot": false,
      "detail": "<p>某鱼直播：9372623 \nV：Chreanw  \n接各种资源,接调号,配号  \n企鹅吹水群：638493256</p>"
    },
    {
      "id": "fcdd49bfef40",
      "title": "三国志11【富豪】【征税】【米道】【征收】",
      "summary": "-",
      "source": "B站",
      "platform_class": "platform-bilibili",
      "author": "三国志11小白",
      "url": "http://www.bilibili.com/video/av438122075",
      "time": "2026-04-06 20:03",
      "heat": 2034,
      "discussions": "82",
      "tags": [],
      "isHot": false,
      "detail": "<p>-</p>"
    },
    {
      "id": "953760b7f9a5",
      "title": "电商平台政策解读及增值税申报详细流程",
      "summary": "-",
      "source": "B站",
      "platform_class": "platform-bilibili",
      "author": "晗妈会计",
      "url": "http://www.bilibili.com/video/av115349114586330",
      "time": "2026-04-06 20:03",
      "heat": 1704,
      "discussions": "29",
      "tags": [],
      "isHot": false,
      "detail": "<p>-</p>"
    },
    {
      "id": "c6f00ebc3a9d",
      "title": "99元1年的境外轻量服务器竟然没人推荐？",
      "summary": "有一说一腾讯云这个价格我觉得非常给力，我自己就买了2年。虽然是轻量但有境外IP就好玩多了。\n活动地址如下：\nhttps://curl.qcloud.com/n9iTB3qR",
      "source": "B站",
      "platform_class": "platform-bilibili",
      "author": "略懂的大龙猫",
      "url": "http://www.bilibili.com/video/av113730599780685",
      "time": "2026-04-06 20:03",
      "heat": 1345,
      "discussions": "61",
      "tags": [],
      "isHot": false,
      "detail": "<p>有一说一腾讯云这个价格我觉得非常给力，我自己就买了2年。虽然是轻量但有境外IP就好玩多了。\n活动地址如下：\nhttps://curl.qcloud.com/n9iTB3qR</p>"
    },
    {
      "id": "3dda4a9ddc2d",
      "title": "移动境外流量怎么买？看这条视频就够了",
      "summary": "-",
      "source": "B站",
      "platform_class": "platform-bilibili",
      "author": "浑语阁",
      "url": "http://www.bilibili.com/video/av114330418810384",
      "time": "2026-04-06 20:03",
      "heat": 1283,
      "discussions": "18",
      "tags": [],
      "isHot": false,
      "detail": "<p>-</p>"
    },
    {
      "id": "dbbea7017e1c",
      "title": "CRS全球金融资产征税，门槛金额和交换标准，合法规避CRS的方法",
      "summary": "CRS全球金融资产征税，门槛金额和交换标准，合法规避CRS的方法",
      "source": "B站",
      "platform_class": "platform-bilibili",
      "author": "宝儿助理",
      "url": "http://www.bilibili.com/video/av114792882902695",
      "time": "2026-04-06 20:03",
      "heat": 896,
      "discussions": "26",
      "tags": [],
      "isHot": false,
      "detail": "<p>CRS全球金融资产征税，门槛金额和交换标准，合法规避CRS的方法</p>"
    },
    {
      "id": "4323317ce1f7",
      "title": "共享大脑，境外势力只要给钱，什么事都愿意做。",
      "summary": "-",
      "source": "B站",
      "platform_class": "platform-bilibili",
      "author": "吉吉国王唷",
      "url": "http://www.bilibili.com/video/av116356183752756",
      "time": "2026-04-06 20:03",
      "heat": 887,
      "discussions": "44",
      "tags": [],
      "isHot": false,
      "detail": "<p>-</p>"
    },
    {
      "id": "7fdfbb8a50b5",
      "title": "英国遭到拒绝后发出警告:中国若不配合，中企在英资产将被没收！",
      "summary": "英国遭到拒绝后发出警告:中国若不配合，中企在英资产将被没收！",
      "source": "B站",
      "platform_class": "platform-bilibili",
      "author": "胡赛拖鞋党",
      "url": "http://www.bilibili.com/video/av116355663659627",
      "time": "2026-04-06 20:03",
      "heat": 877,
      "discussions": "25",
      "tags": [],
      "isHot": false,
      "detail": "<p>英国遭到拒绝后发出警告:中国若不配合，中企在英资产将被没收！</p>"
    },
    {
      "id": "707ef4919553",
      "title": "【张捷财经】Manus创始人限制出境下的国家司法征税主权",
      "summary": "【张捷财经】Manus创始人限制出境下的国家司法征税主权",
      "source": "B站",
      "platform_class": "platform-bilibili",
      "author": "张捷财经观察",
      "url": "http://www.bilibili.com/video/av116339591221663",
      "time": "2026-04-06 20:03",
      "heat": 759,
      "discussions": "6",
      "tags": [],
      "isHot": false,
      "detail": "<p>【张捷财经】Manus创始人限制出境下的国家司法征税主权</p>"
    },
    {
      "id": "8d3b6a0d3fe0",
      "title": "特朗普全球关税案庭审实录：政府被9位大法官连珠炮式质疑，美国最高法院或将终结“总统单边全球收税时代”",
      "summary": "2025年11月5日，美国最高法院审理了“Learning Resources v. Trump”案，焦点是特朗普总统依据《国际紧急经济权力法》（IEEPA，50 U.S.C. §1701等）宣布“贸易逆差+芬太尼”双重国家紧急状态后，动用该法“regulate importation”条款大规模加征关税的权力是否合法。\n政府方（Solicitor General Sauer）主张：\n“regul",
      "source": "B站",
      "platform_class": "platform-bilibili",
      "author": "老研翻译",
      "url": "http://www.bilibili.com/video/av115656691293532",
      "time": "2026-04-06 20:03",
      "heat": 600,
      "discussions": "26",
      "tags": [],
      "isHot": false,
      "detail": "<p>2025年11月5日，美国最高法院审理了“Learning Resources v. Trump”案，焦点是特朗普总统依据《国际紧急经济权力法》（IEEPA，50 U.S.C. §1701等）宣布“贸易逆差+芬太尼”双重国家紧急状态后，动用该法“regulate importation”条款大规模加征关税的权力是否合法。\n政府方（Solicitor General Sauer）主张：\n“regul</p>"
    },
    {
      "id": "ea6817c00916",
      "title": "收到申报海外收入提醒应该怎么办？",
      "summary": "-",
      "source": "B站",
      "platform_class": "platform-bilibili",
      "author": "lyon的离岸账户",
      "url": "http://www.bilibili.com/video/av114794594047795",
      "time": "2026-04-06 20:03",
      "heat": 508,
      "discussions": "19",
      "tags": [],
      "isHot": false,
      "detail": "<p>-</p>"
    },
    {
      "id": "db6685bdc40a",
      "title": "税负效应——向消费者和生产者征税",
      "summary": "税负效应——向消费者和生产者征税",
      "source": "B站",
      "platform_class": "platform-bilibili",
      "author": "花儿和春天",
      "url": "http://www.bilibili.com/video/av114137212392546",
      "time": "2026-04-06 20:03",
      "heat": 479,
      "discussions": "4",
      "tags": [],
      "isHot": false,
      "detail": "<p>税负效应——向消费者和生产者征税</p>"
    },
    {
      "id": "cd1be47af60c",
      "title": "境外取现免手续的银行卡！境外取款",
      "summary": "-",
      "source": "B站",
      "platform_class": "platform-bilibili",
      "author": "鸿宇的环球旅行",
      "url": "http://www.bilibili.com/video/av1200338714",
      "time": "2026-04-06 20:03",
      "heat": 439,
      "discussions": "4",
      "tags": [],
      "isHot": false,
      "detail": "<p>-</p>"
    },
    {
      "id": "5e6e60953b00",
      "title": "取得境外所得如何通过个税APP申报个人所得税(浙江税务)",
      "summary": "宝子们！5月29日还没报境外所得个税的注意啦！今年起用个税APP就能搞定，超省心～\n\n哪些算境外所得？像海外工资、境外股息、转让境外房产等9类收入都要报，具体看财政部2020年3号公告！记得每年3月1日-6月30日申报，现在只剩最后几天，别漏了！\n\n操作超简单：打开个税APP，首页搜“年度汇算（取得境外所得适用）”，填境内外综合所得、经营所得，利息股息等分类所得单独填；境外已缴税别慌，系统自动算抵",
      "source": "B站",
      "platform_class": "platform-bilibili",
      "author": "税务师木木",
      "url": "http://www.bilibili.com/video/av114588066516202",
      "time": "2026-04-06 20:03",
      "heat": 396,
      "discussions": "1",
      "tags": [
        "境外所得"
      ],
      "isHot": false,
      "detail": "<p>宝子们！5月29日还没报境外所得个税的注意啦！今年起用个税APP就能搞定，超省心～\n\n哪些算境外所得？像海外工资、境外股息、转让境外房产等9类收入都要报，具体看财政部2020年3号公告！记得每年3月1日-6月30日申报，现在只剩最后几天，别漏了！\n\n操作超简单：打开个税APP，首页搜“年度汇算（取得境外所得适用）”，填境内外综合所得、经营所得，利息股息等分类所得单独填；境外已缴税别慌，系统自动算抵</p>"
    },
    {
      "id": "fbc4806b4a4d",
      "title": "大额资金出境的合法途径",
      "summary": "移民人士想要把国内的资产大额出境，合法的方式就是通过《个人财产对外转移售付汇管理暂行办法》简称《暂行办法》，它是中国人民银行与政府相关部门制定的，允许来自中国的合法移民走相关合法的流程，汇出超过5万美元的大笔资金到海外。",
      "source": "B站",
      "platform_class": "platform-bilibili",
      "author": "蓝蚁咨询",
      "url": "http://www.bilibili.com/video/av311017619",
      "time": "2026-04-06 20:03",
      "heat": 379,
      "discussions": "0",
      "tags": [],
      "isHot": false,
      "detail": "<p>移民人士想要把国内的资产大额出境，合法的方式就是通过《个人财产对外转移售付汇管理暂行办法》简称《暂行办法》，它是中国人民银行与政府相关部门制定的，允许来自中国的合法移民走相关合法的流程，汇出超过5万美元的大笔资金到海外。</p>"
    },
    {
      "id": "719114097063",
      "title": "逛日本街头住情侣酒店 记得买境外险",
      "summary": "逛日本街头住情侣酒店 记得买境外险",
      "source": "B站",
      "platform_class": "platform-bilibili",
      "author": "YouTube日本",
      "url": "http://www.bilibili.com/video/av116354657030467",
      "time": "2026-04-06 20:03",
      "heat": 377,
      "discussions": "8",
      "tags": [],
      "isHot": false,
      "detail": "<p>逛日本街头住情侣酒店 记得买境外险</p>"
    },
    {
      "id": "164b503b5b51",
      "title": "4-1企业所得税纳税人、征税对象、税率+片头片尾",
      "summary": "2026课程节选",
      "source": "B站",
      "platform_class": "platform-bilibili",
      "author": "吃手机不吐手机皮",
      "url": "http://www.bilibili.com/video/av116239028520783",
      "time": "2026-04-06 20:03",
      "heat": 292,
      "discussions": "1",
      "tags": [],
      "isHot": false,
      "detail": "<p>2026课程节选</p>"
    },
    {
      "id": "009234272473",
      "title": "负债被执行如何填好财产申报表，减少被拘留风险",
      "summary": "-",
      "source": "B站",
      "platform_class": "platform-bilibili",
      "author": "彪哥小课堂",
      "url": "http://www.bilibili.com/video/av115534502958225",
      "time": "2026-04-06 20:03",
      "heat": 264,
      "discussions": "7",
      "tags": [],
      "isHot": false,
      "detail": "<p>-</p>"
    },
    {
      "id": "b3f3bc378445",
      "title": "［微观经济学］（考研真题）第三章第15题： 政府对居民征税，一种是征收消费税 ，另一种是征收所得税 ，征收的税额都是一样，哪一种方式对居民更有利一些？",
      "summary": "微观经济学课后习题/期末考试题/考研真题，每日一题之：政府对居民征税一般有两种办法，一种是征收消费税 ，另一种是征收所得税 ，不论采取哪一种征税办法政府征收的税额都是一样，那么哪一种征税办法对居民会更为有利些？",
      "source": "B站",
      "platform_class": "platform-bilibili",
      "author": "经济学习题解答",
      "url": "http://www.bilibili.com/video/av831768303",
      "time": "2026-04-06 20:03",
      "heat": 262,
      "discussions": "6",
      "tags": [],
      "isHot": false,
      "detail": "<p>微观经济学课后习题/期末考试题/考研真题，每日一题之：政府对居民征税一般有两种办法，一种是征收消费税 ，另一种是征收所得税 ，不论采取哪一种征税办法政府征收的税额都是一样，那么哪一种征税办法对居民会更为有利些？</p>"
    },
    {
      "id": "26968484a99c",
      "title": "境外工作证明，境外证明，境外生活证明，富途牛牛，",
      "summary": "境外工作证明，境外证明，境外生活证明，富途牛牛，",
      "source": "B站",
      "platform_class": "platform-bilibili",
      "author": "Lris1120",
      "url": "http://www.bilibili.com/video/av114776726444563",
      "time": "2026-04-06 20:03",
      "heat": 246,
      "discussions": "10",
      "tags": [],
      "isHot": false,
      "detail": "<p>境外工作证明，境外证明，境外生活证明，富途牛牛，</p>"
    },
    {
      "id": "58831873638e",
      "title": "德国EPR怎么申报？什么时候申报？第三方申报EPR多少钱？",
      "summary": "德国EPR怎么申报？什么时候申报？第三方申报EPR多少钱？",
      "source": "B站",
      "platform_class": "platform-bilibili",
      "author": "远郊区打工人",
      "url": "http://www.bilibili.com/video/av113629819047715",
      "time": "2026-04-06 20:03",
      "heat": 234,
      "discussions": "5",
      "tags": [],
      "isHot": false,
      "detail": "<p>德国EPR怎么申报？什么时候申报？第三方申报EPR多少钱？</p>"
    },
    {
      "id": "eb523956fc67",
      "title": "再见了，零申报！2026无税不申报要来了！",
      "summary": "再见了，零申报！2026无税不申报要来了！",
      "source": "B站",
      "platform_class": "platform-bilibili",
      "author": "税课圈丨财务会计",
      "url": "http://www.bilibili.com/video/av116277012073438",
      "time": "2026-04-06 20:03",
      "heat": 229,
      "discussions": "3",
      "tags": [],
      "isHot": false,
      "detail": "<p>再见了，零申报！2026无税不申报要来了！</p>"
    },
    {
      "id": "923c9bcb2d25",
      "title": "中国开启全球征税时代！境外收入恶意逃税可能要坐牢",
      "summary": "中国税务居民在海外赚了钱，都需要向中国税务机关报税。如果不报税被查出来，则将面临补税+罚款，恶意逃税者还将承担刑事责任，牢饭供应。\n \n本来境外收入报税交税这件事，喊了很多年，但因为技术原因并未普及开来。但是现在，技术的进步与国际合作的紧密，让心存侥幸者无所遁形。\n \n近日，中国的浙江、山东、上海、湖北四地税务机关同步发布公告，针对中国境内居民的境外收入申报问题开展集中核查。\n \n通过大数据识别出",
      "source": "B站",
      "platform_class": "platform-bilibili",
      "author": "无忧启程移民",
      "url": "http://www.bilibili.com/video/av114420143494580",
      "time": "2026-04-06 20:03",
      "heat": 190,
      "discussions": "8",
      "tags": [
        "全球征税"
      ],
      "isHot": false,
      "detail": "<p>中国税务居民在海外赚了钱，都需要向中国税务机关报税。如果不报税被查出来，则将面临补税+罚款，恶意逃税者还将承担刑事责任，牢饭供应。\n \n本来境外收入报税交税这件事，喊了很多年，但因为技术原因并未普及开来。但是现在，技术的进步与国际合作的紧密，让心存侥幸者无所遁形。\n \n近日，中国的浙江、山东、上海、湖北四地税务机关同步发布公告，针对中国境内居民的境外收入申报问题开展集中核查。\n \n通过大数据识别出</p>"
    },
    {
      "id": "c0123dc6b505",
      "title": "分公司都需要申报哪些税零申报全流程",
      "summary": "-",
      "source": "B站",
      "platform_class": "platform-bilibili",
      "author": "晗妈会计",
      "url": "http://www.bilibili.com/video/av114822914050754",
      "time": "2026-04-06 20:03",
      "heat": 172,
      "discussions": "1",
      "tags": [],
      "isHot": false,
      "detail": "<p>-</p>"
    },
    {
      "id": "2414118a2bd0",
      "title": "VAT如何申报？以及怎么样下载申报数据？",
      "summary": "大家要选择正规的服务商，办理注册跟按时申报噢～有这个需求的也可后台滴",
      "source": "B站",
      "platform_class": "platform-bilibili",
      "author": "ET汉堡包",
      "url": "http://www.bilibili.com/video/av112829009102497",
      "time": "2026-04-06 20:03",
      "heat": 100,
      "discussions": "0",
      "tags": [],
      "isHot": false,
      "detail": "<p>大家要选择正规的服务商，办理注册跟按时申报噢～有这个需求的也可后台滴</p>"
    },
    {
      "id": "2b498a587864",
      "title": "张捷~征税权VS定价权①",
      "summary": "-",
      "source": "B站",
      "platform_class": "platform-bilibili",
      "author": "支持真国货就是爱自己",
      "url": "http://www.bilibili.com/video/av115683534834348",
      "time": "2026-04-06 20:03",
      "heat": 92,
      "discussions": "2",
      "tags": [],
      "isHot": false,
      "detail": "<p>-</p>"
    },
    {
      "id": "43aea42ed1c5",
      "title": "新增值税法差额征税有了大变化！",
      "summary": "新增值税法差额征税有了大变化！",
      "source": "B站",
      "platform_class": "platform-bilibili",
      "author": "会计实操谦谦老师",
      "url": "http://www.bilibili.com/video/av116331923965449",
      "time": "2026-04-06 20:03",
      "heat": 88,
      "discussions": "1",
      "tags": [],
      "isHot": false,
      "detail": "<p>新增值税法差额征税有了大变化！</p>"
    },
    {
      "id": "300dbec0e1d4",
      "title": "在中国法院起诉离婚，可以分割境外资产吗？",
      "summary": "在中国法院起诉离婚，可以分割境外资产吗？",
      "source": "B站",
      "platform_class": "platform-bilibili",
      "author": "张亚敏律师",
      "url": "http://www.bilibili.com/video/av113526018611756",
      "time": "2026-04-06 20:03",
      "heat": 84,
      "discussions": "1",
      "tags": [
        "境外资产"
      ],
      "isHot": false,
      "detail": "<p>在中国法院起诉离婚，可以分割境外资产吗？</p>"
    },
    {
      "id": "3060c00a24af",
      "title": "第1课：境外社会安全风险识别与应对",
      "summary": "第1课：境外社会安全风险识别与应对",
      "source": "B站",
      "platform_class": "platform-bilibili",
      "author": "海菁汇",
      "url": "http://www.bilibili.com/video/av115213353487553",
      "time": "2026-04-06 20:03",
      "heat": 77,
      "discussions": "1",
      "tags": [],
      "isHot": false,
      "detail": "<p>第1课：境外社会安全风险识别与应对</p>"
    },
    {
      "id": "41e9712adacf",
      "title": "2025年境外收入在国内缴税的方法",
      "summary": "2025年境外收入在国内缴税的方法",
      "source": "B站",
      "platform_class": "platform-bilibili",
      "author": "淡定的飞马",
      "url": "http://www.bilibili.com/video/av116228072934922",
      "time": "2026-04-06 20:03",
      "heat": 71,
      "discussions": "6",
      "tags": [],
      "isHot": false,
      "detail": "<p>2025年境外收入在国内缴税的方法</p>"
    },
    {
      "id": "909d1c19303a",
      "title": "一中国人超7亿房产在英被冻，资产转到国外也不安全吗？",
      "summary": "它打击的就是跨境洗钱、腐败、有组织犯罪，其实麻烦就麻烦在那些不清楚来源的，可能很多人就会考虑避着英国走了，英伦情再深刻，恐怕也不至于去送人头。",
      "source": "B站",
      "platform_class": "platform-bilibili",
      "author": "推石头的林律师",
      "url": "http://www.bilibili.com/video/av116356854842541",
      "time": "2026-04-06 20:03",
      "heat": 70,
      "discussions": "0",
      "tags": [],
      "isHot": false,
      "detail": "<p>它打击的就是跨境洗钱、腐败、有组织犯罪，其实麻烦就麻烦在那些不清楚来源的，可能很多人就会考虑避着英国走了，英伦情再深刻，恐怕也不至于去送人头。</p>"
    },
    {
      "id": "6fb3e99a3cd2",
      "title": "跨境离婚时，境外财产如何分？跨境婚姻必看知识",
      "summary": "跨境离婚时，境外财产如何分？跨境婚姻必看知识  \r#涉外律师 #境外律师 #跨境律师 #海外律师",
      "source": "B站",
      "platform_class": "platform-bilibili",
      "author": "JasonTianJie",
      "url": "http://www.bilibili.com/video/av744990267",
      "time": "2026-04-06 20:03",
      "heat": 55,
      "discussions": "1",
      "tags": [],
      "isHot": false,
      "detail": "<p>跨境离婚时，境外财产如何分？跨境婚姻必看知识  \r#涉外律师 #境外律师 #跨境律师 #海外律师</p>"
    },
    {
      "id": "3f632845c956",
      "title": "全球最低税协议：终结避税天堂的时代 对全球企业税收政策的重大变革及其影响",
      "summary": "本视频深入解析了由G20/OECD主导的全球最低税协议如何终结长达数十年的“避税天堂”时代。协议规定全球企业税率最低为百分之十五，旨在打击跨国巨头利润转移，确保税收公平。视频详细探讨了协议如何引发爱尔兰科技股成交量暴增、各方得失权衡（科技巨头利润受压 vs. 高税率国家财政收入增加），以及未来全球竞争将从“税率比拼”转向“人才与基础设施”综合实力较量的深远影响。这是一场重塑全球商业与资本格局的重大",
      "source": "B站",
      "platform_class": "platform-bilibili",
      "author": "元都-逆熵",
      "url": "http://www.bilibili.com/video/av115132722054625",
      "time": "2026-04-06 20:03",
      "heat": 44,
      "discussions": "1",
      "tags": [],
      "isHot": false,
      "detail": "<p>本视频深入解析了由G20/OECD主导的全球最低税协议如何终结长达数十年的“避税天堂”时代。协议规定全球企业税率最低为百分之十五，旨在打击跨国巨头利润转移，确保税收公平。视频详细探讨了协议如何引发爱尔兰科技股成交量暴增、各方得失权衡（科技巨头利润受压 vs. 高税率国家财政收入增加），以及未来全球竞争将从“税率比拼”转向“人才与基础设施”综合实力较量的深远影响。这是一场重塑全球商业与资本格局的重大</p>"
    },
    {
      "id": "b18d122da3b7",
      "title": "疑受境外势力支持，疯狂为日本洗白，辟谣芯片、添加剂、转基因，还支持涉毒封存",
      "summary": "-",
      "source": "B站",
      "platform_class": "platform-bilibili",
      "author": "乐亭二中刘薇",
      "url": "http://www.bilibili.com/video/av116357458893577",
      "time": "2026-04-06 20:03",
      "heat": 38,
      "discussions": "3",
      "tags": [],
      "isHot": false,
      "detail": "<p>-</p>"
    },
    {
      "id": "2973640eda24",
      "title": "CRS全球征税时代，天价罚单背后“隐形”的境外资产护城河！",
      "summary": "CRS全球征税时代，天价罚单背后“隐形”的境外资产护城河！",
      "source": "B站",
      "platform_class": "platform-bilibili",
      "author": "金橙果海外",
      "url": "http://www.bilibili.com/video/av116333517735113",
      "time": "2026-04-06 20:03",
      "heat": 32,
      "discussions": "0",
      "tags": [
        "境外资产",
        "全球征税"
      ],
      "isHot": false,
      "detail": "<p>CRS全球征税时代，天价罚单背后“隐形”的境外资产护城河！</p>"
    },
    {
      "id": "8c129aa2167b",
      "title": "26年4月份个体工商户0申报全流程",
      "summary": "#财税小白入门必修课 #基础入门实操演示 #会计实务真账实操演示 #个体工商户 #纳税申报实操 #会计~实操 #纳税申报实操",
      "source": "B站",
      "platform_class": "platform-bilibili",
      "author": "晗妈会计",
      "url": "http://www.bilibili.com/video/av116356922018918",
      "time": "2026-04-06 20:03",
      "heat": 27,
      "discussions": "0",
      "tags": [],
      "isHot": false,
      "detail": "<p>#财税小白入门必修课 #基础入门实操演示 #会计实务真账实操演示 #个体工商户 #纳税申报实操 #会计~实操 #纳税申报实操</p>"
    },
    {
      "id": "44081476ba3f",
      "title": "海外账户即将共同申报！海外资产也要报税！",
      "summary": "海外账户即将共同申报！海外资产也要报税！",
      "source": "B站",
      "platform_class": "platform-bilibili",
      "author": "Stephen移民咨询",
      "url": "http://www.bilibili.com/video/av114833852794166",
      "time": "2026-04-06 20:03",
      "heat": 21,
      "discussions": "0",
      "tags": [
        "海外资产"
      ],
      "isHot": false,
      "detail": "<p>海外账户即将共同申报！海外资产也要报税！</p>"
    },
    {
      "id": "ef680c0cdc32",
      "title": "资产拍卖就是韭菜局",
      "summary": "-",
      "source": "B站",
      "platform_class": "platform-bilibili",
      "author": "法拍真探",
      "url": "http://www.bilibili.com/video/av116357022686089",
      "time": "2026-04-06 20:03",
      "heat": 20,
      "discussions": "0",
      "tags": [],
      "isHot": false,
      "detail": "<p>-</p>"
    },
    {
      "id": "76b389a5dc9c",
      "title": "海外资产申报汇总",
      "summary": "海外资产都要申报什么？国内房子出租租金要申报吗？别人欠我钱也要申报吗？资产很少也要申报吗？",
      "source": "B站",
      "platform_class": "platform-bilibili",
      "author": "多咨处",
      "url": "http://www.bilibili.com/video/av876902196",
      "time": "2026-04-06 20:03",
      "heat": 9,
      "discussions": "0",
      "tags": [
        "海外资产",
        "海外资产申报"
      ],
      "isHot": false,
      "detail": "<p>海外资产都要申报什么？国内房子出租租金要申报吗？别人欠我钱也要申报吗？资产很少也要申报吗？</p>"
    },
    {
      "id": "2ea05c9ca5c7",
      "title": "被通知更正申报，应该如何处理？",
      "summary": "被通知更正申报，应该如何处理？",
      "source": "B站",
      "platform_class": "platform-bilibili",
      "author": "春戈聊电商财税",
      "url": "http://www.bilibili.com/video/av116339423445727",
      "time": "2026-04-06 20:03",
      "heat": 7,
      "discussions": "0",
      "tags": [],
      "isHot": false,
      "detail": "<p>被通知更正申报，应该如何处理？</p>"
    },
    {
      "id": "ae54b665b566",
      "title": "税费申报的风险点，全部讲清",
      "summary": "-",
      "source": "B站",
      "platform_class": "platform-bilibili",
      "author": "娜姐聊财税带教",
      "url": "http://www.bilibili.com/video/av116357425266817",
      "time": "2026-04-06 20:03",
      "heat": 4,
      "discussions": "0",
      "tags": [],
      "isHot": false,
      "detail": "<p>-</p>"
    },
    {
      "id": "16526fd44246",
      "title": "香港CRS2.0立法启动！海外资产彻底裸奔⚠️高净值人群必",
      "summary": "-",
      "source": "B站",
      "platform_class": "platform-bilibili",
      "author": "美港股苏苏",
      "url": "http://www.bilibili.com/video/av116356032764714",
      "time": "2026-04-06 20:03",
      "heat": 0,
      "discussions": "0",
      "tags": [
        "海外资产"
      ],
      "isHot": false,
      "detail": "<p>-</p>"
    },
    {
      "id": "45bfbb5eb810",
      "title": "海外资产申报是否需要评估报告？",
      "summary": "海外资产申报是否需要评估报告？",
      "source": "B站",
      "platform_class": "platform-bilibili",
      "author": "深美林评估",
      "url": "http://www.bilibili.com/video/av114386454775207",
      "time": "2026-04-06 20:03",
      "heat": 0,
      "discussions": "0",
      "tags": [
        "海外资产",
        "海外资产申报"
      ],
      "isHot": false,
      "detail": "<p>海外资产申报是否需要评估报告？</p>"
    }
  ]
}